Workbook

Sheet 00_Resumo
A1: 01 - Estimativa de Custos das Intervenções Estruturais
A2: Volume | B2: Id | C2: Grau | D2: Bairro | E2: Alto | G2: Contenções e Demolições | L2: Obras Complementares | R2: Subtotal 1 | S2: Subtotal 2 | U2: Subtotal 3 | W2: Valores Adicionais (%) | AC2: Subtotal 4 | AD2: Subtotal 5 | AE2: Subtotal 4 + Subtotal 5 | AG2: BDI (26,8%) | AI2: Subtotal 6 | AJ2: Subtotal 7 | AL2: Custo Total | AN2: Custo Por Domicílio
G3: Número de Domicílios | H3: Número de Domicílios - Soma | J3: Custo Estimado das Obras | L3: Custo Estimado dos Serviços Preliminares / Demolições / Limpeza | M3: Custo Estimado das Obras de Drenagem | N3: Custo Estimado das Obras de Mobilidade | O3: Custo Estimado das Obras de Esgoto | P3: Custo Estimado das Obras de Obras De Rsu | R3: Contenções e Demolições | S3: Obras Complementares | U3: =_xlfn.CONCAT(R3," ","+"," ",S3) -> Contenções e Demolições + Obras Complementares | W3: Projeto executivo, levantamentos, ensaios e estudos (5%) | X3: Serviços preliminares (limpeza do terreno, tapume e canteiro) (4%) | Y3: Equipamentos de monitoramento e alerta (1%) | Z3: Ações sociais e trabalho social (3%) | AA3: Avaliação pós-intervenção e ocupação (0,5%) | AC3: Subtotal 1 + Adicionais % | AD3: Subtotal 2 + Adicionais % | AI3: Subtotal 4 + BDI | AJ3: Subtotal 5 + BDI | AL3: Subtotal 6 + Subtotal 7
AC4: =_xlfn.CONCAT(R3," ","+"," ","Adicionais %") -> Contenções e Demolições + Adicionais % | AD4: =_xlfn.CONCAT(S3," ","+"," ","Adicionais %") -> Obras Complementares + Adicionais % | AE4: =_xlfn.CONCAT(R3," ","+"," ",S3," ","+"," ","Adicionais %") -> Contenções e Demolições + Obras Complementares + Adicionais % | AI4: =_xlfn.CONCAT(AC4," ","+"," ","BDI") -> Contenções e Demolições + Adicionais % + BDI | AJ4: =_xlfn.CONCAT(AD4," ","+"," ","BDI") -> Obras Complementares + Adicionais % + BDI | AL4: =_xlfn.CONCAT(R3," ","+"," ",S3," ","+"," ","Adicionais %"," ","+"," ","BDI") -> Contenções e Demolições + Obras Complementares + Adicionais % + BDI
A5: 1 | B5: =MID('01_Carvalho'!D5,16,6) -> A1S1R3 | C5: =RIGHT(B5,2) -> R3 | D5: =MID('01_Carvalho'!$C$3,51,9) -> Esperança | E5: =MID('01_Carvalho'!$C$3,34,8) -> Carvalho | G5: 6 | J5: ='01_Carvalho'!M5 -> 386572.95 | L5: =0 -> 0 | M5: 0 | N5: 0 | O5: 0 | P5: 0 | R5: =SUM(J5:J5) -> 386572.95 | S5: =SUM(L5:P5) -> 0 | U5: =R5+S5 -> 386572.95 | W5: =U5*0.05 -> 19328.648 | X5: =U5*0.04 -> 15462.918 | Y5: =U5*0.01 -> 3865.7295 | Z5: =U5*0.03 -> 11597.189 | AA5: =U5*0.005 -> 1932.8648 | AC5: =R5+SUM(W5:AA5) -> 438760.3 | AD5: 0 | AE5: =SUM(AC5:AD5) -> 438760.3 | AG5: =AE5*0.268 -> 117587.76 | AI5: =AC5+AC5*0.268 -> 556348.06 | AJ5: =AD5+AD5*0.268 -> 0 | AL5: =SUM(AI5:AJ5) -> 556348.06 | AN5: =AL5/G5 -> 92724.676
A6: 1 | B6: =MID('01_Carvalho'!D36,16,6) -> A1S2R4 | C6: =RIGHT(B6,2) -> R4 | D6: =MID('01_Carvalho'!$C$3,51,9) -> Esperança | E6: =MID('01_Carvalho'!$C$3,34,8) -> Carvalho | G6: 17 | J6: ='01_Carvalho'!M36 -> 743321.27 | L6: =0 -> 0 | M6: 0 | N6: 0 | O6: 0 | P6: 0 | R6: =SUM(J6:J6) -> 743321.27 | S6: =SUM(L6:P6) -> 0 | U6: =R6+S6 -> 743321.27 | W6: =U6*0.05 -> 37166.064 | X6: =U6*0.04 -> 29732.851 | Y6: =U6*0.01 -> 7433.2127 | Z6: =U6*0.03 -> 22299.638 | AA6: =U6*0.005 -> 3716.6064 | AC6: =R6+SUM(W6:AA6) -> 843669.64 | AD6: 0 | AE6: =SUM(AC6:AD6) -> 843669.64 | AG6: =AE6*0.268 -> 226103.46 | AI6: =AC6+AC6*0.268 -> 1069773.1 | AJ6: =AD6+AD6*0.268 -> 0 | AL6: =SUM(AI6:AJ6) -> 1069773.1 | AN6: =AL6/G6 -> 62927.83
A7: 1 | B7: =MID('01_Carvalho'!$D$67,16,6) -> A4S1R3 | C7: =RIGHT(B7,2) -> R3 | D7: =MID('01_Carvalho'!$C$3,51,9) -> Esperança | E7: =MID('01_Carvalho'!$C$3,34,8) -> Carvalho | G7: 24 | J7: ='01_Carvalho'!M67 -> 357741.8 | L7: =0 -> 0 | M7: 0 | N7: 0 | O7: 0 | P7: 0 | R7: =SUM(J7:J7) -> 357741.8 | S7: =SUM(L7:P7) -> 0 | U7: =R7+S7 -> 357741.8 | W7: =U7*0.05 -> 17887.09 | X7: =U7*0.04 -> 14309.672 | Y7: =U7*0.01 -> 3577.418 | Z7: =U7*0.03 -> 10732.254 | AA7: =U7*0.005 -> 1788.709 | AC7: =R7+SUM(W7:AA7) -> 406036.94 | AD7: 0 | AE7: =SUM(AC7:AD7) -> 406036.94 | AG7: =AE7*0.268 -> 108817.9 | AI7: =AC7+AC7*0.268 -> 514854.84 | AJ7: =AD7+AD7*0.268 -> 0 | AL7: =SUM(AI7:AJ7) -> 514854.84 | AN7: =AL7/G7 -> 21452.285
A8: 1 | B8: =MID('01_Carvalho'!$D$87,16,6) -> A4S2R4 | C8: =RIGHT(B8,2) -> R4 | D8: =MID('01_Carvalho'!$C$3,51,9) -> Esperança | E8: =MID('01_Carvalho'!$C$3,34,8) -> Carvalho | G8: 24 | J8: ='01_Carvalho'!M87 -> 171290.91 | L8: =0 -> 0 | M8: 0 | N8: 0 | O8: 0 | P8: 0 | R8: =SUM(J8:J8) -> 171290.91 | S8: =SUM(L8:P8) -> 0 | U8: =R8+S8 -> 171290.91 | W8: =U8*0.05 -> 8564.5455 | X8: =U8*0.04 -> 6851.6364 | Y8: =U8*0.01 -> 1712.9091 | Z8: =U8*0.03 -> 5138.7273 | AA8: =U8*0.005 -> 856.45455 | AC8: =R8+SUM(W8:AA8) -> 194415.18 | AD8: 0 | AE8: =SUM(AC8:AD8) -> 194415.18 | AG8: =AE8*0.268 -> 52103.269 | AI8: =AC8+AC8*0.268 -> 246518.45 | AJ8: =AD8+AD8*0.268 -> 0 | AL8: =SUM(AI8:AJ8) -> 246518.45 | AN8: =AL8/G8 -> 10271.602
A9: 1 | B9: =MID('01_Carvalho'!$D$125,16,6) -> A5S2R3 | C9: =RIGHT(B9,2) -> R3 | D9: =MID('01_Carvalho'!$C$3,51,9) -> Esperança | E9: =MID('01_Carvalho'!$C$3,34,8) -> Carvalho | G9: 35 | J9: ='01_Carvalho'!M125 -> 246744.4 | L9: =0 -> 0 | M9: 0 | N9: 0 | O9: 0 | P9: 0 | R9: =SUM(J9:J9) -> 246744.4 | S9: =SUM(L9:P9) -> 0 | U9: =R9+S9 -> 246744.4 | W9: =U9*0.05 -> 12337.22 | X9: =U9*0.04 -> 9869.776 | Y9: =U9*0.01 -> 2467.444 | Z9: =U9*0.03 -> 7402.332 | AA9: =U9*0.005 -> 1233.722 | AC9: =R9+SUM(W9:AA9) -> 280054.89 | AD9: 0 | AE9: =SUM(AC9:AD9) -> 280054.89 | AG9: =AE9*0.268 -> 75054.712 | AI9: =AC9+AC9*0.268 -> 355109.61 | AJ9: =AD9+AD9*0.268 -> 0 | AL9: =SUM(AI9:AJ9) -> 355109.61 | AN9: =AL9/G9 -> 10145.989
A10: 1 | B10: - | C10: - | D10: =MID('01_Carvalho'!$C$3,51,9) -> Esperança | E10: =MID('01_Carvalho'!$C$3,34,8) -> Carvalho | H10: =SUM(G5:G9) -> 106 | J10: 0 | L10: =0 -> 0 | M10: ='01_Carvalho'!J143 -> 49097.71 | N10: ='01_Carvalho'!J148 -> 429182.43 | O10: ='01_Carvalho'!J168 -> 10287.16 | P10: ='01_Carvalho'!J171 -> 7816 | R10: 0 | S10: =SUM(L10:P10) -> 496383.3 | U10: =R10+S10 -> 496383.3 | W10: =U10*0.05 -> 24819.165 | X10: =U10*0.04 -> 19855.332 | Y10: =U10*0.01 -> 4963.833 | Z10: =U10*0.03 -> 14891.499 | AA10: =U10*0.005 -> 2481.9165 | AC10: 0 | AD10: =S10+SUM(W10:AA10) -> 563395.05 | AE10: =SUM(AC10:AD10) -> 563395.05 | AG10: =AE10*0.268 -> 150989.87 | AI10: =AC10+AC10*0.268 -> 0 | AJ10: =AD10+AD10*0.268 -> 714384.92 | AL10: =SUM(AI10:AJ10) -> 714384.92 | AN10: =AL10/H10 -> 6739.4804
A12: 1 | B12: =MID('02_Esperança'!$B$5,16,6) -> A1S2R4 | C12: =RIGHT(B12,2) -> R4 | D12: =MID('02_Esperança'!$A$3,51,10) -> Esperança | E12: =MID('02_Esperança'!$A$3,34,9) -> Esperança | G12: 76 | J12: ='02_Esperança'!K5 -> 99348.32 | L12: 0 | M12: 0 | N12: 0 | O12: 0 | P12: 0 | R12: =SUM(J12:J12) -> 99348.32 | S12: =SUM(M12:P12) -> 0 | U12: =R12+S12 -> 99348.32 | W12: =U12*0.05 -> 4967.416 | X12: =U12*0.04 -> 3973.9328 | Y12: =U12*0.01 -> 993.4832 | Z12: =U12*0.03 -> 2980.4496 | AA12: =U12*0.005 -> 496.7416 | AC12: =R12+SUM(W12:AA12) -> 112760.34 | AD12: 0 | AE12: =SUM(AC12:AD12) -> 112760.34 | AG12: =AE12*0.268 -> 30219.772 | AI12: =AC12+AC12*0.268 -> 142980.12 | AJ12: =AD12+AD12*0.268 -> 0 | AL12: =SUM(AI12:AJ12) -> 142980.12 | AN12: =AL12/G12 -> 1881.3173
A13: 1 | B13: =MID('02_Esperança'!$B$36,16,6) -> A1S3R3 | C13: =RIGHT(B13,2) -> R3 | D13: =MID('02_Esperança'!$A$3,51,10) -> Esperança | E13: =MID('02_Esperança'!$A$3,34,9) -> Esperança | G13: 40 | J13: ='02_Esperança'!K36 -> 1422949.4 | L13: 0 | M13: 0 | N13: 0 | O13: 0 | P13: 0 | R13: =SUM(J13:J13) -> 1422949.4 | S13: =SUM(M13:P13) -> 0 | U13: =R13+S13 -> 1422949.4 | W13: =U13*0.05 -> 71147.47 | X13: =U13*0.04 -> 56917.976 | Y13: =U13*0.01 -> 14229.494 | Z13: =U13*0.03 -> 42688.482 | AA13: =U13*0.005 -> 7114.747 | AC13: =R13+SUM(W13:AA13) -> 1615047.6 | AD13: 0 | AE13: =SUM(AC13:AD13) -> 1615047.6 | AG13: =AE13*0.268 -> 432832.75 | AI13: =AC13+AC13*0.268 -> 2047880.3 | AJ13: =AD13+AD13*0.268 -> 0 | AL13: =SUM(AI13:AJ13) -> 2047880.3 | AN13: =AL13/G13 -> 51197.008
A14: 1 | B14: =MID('02_Esperança'!$B$74,16,6) -> A2S1R3 | C14: =RIGHT(B14,2) -> R3 | D14: =MID('02_Esperança'!$A$3,51,10) -> Esperança | E14: =MID('02_Esperança'!$A$3,34,9) -> Esperança | G14: 63 | J14: ='02_Esperança'!K74 -> 2394136.9 | L14: 0 | M14: 0 | N14: 0 | O14: 0 | P14: 0 | R14: =SUM(J14:J14) -> 2394136.9 | S14: =SUM(M14:P14) -> 0 | U14: =R14+S14 -> 2394136.9 | W14: =U14*0.05 -> 119706.85 | X14: =U14*0.04 -> 95765.476 | Y14: =U14*0.01 -> 23941.369 | Z14: =U14*0.03 -> 71824.107 | AA14: =U14*0.005 -> 11970.684 | AC14: =R14+SUM(W14:AA14) -> 2717345.4 | AD14: 0 | AE14: =SUM(AC14:AD14) -> 2717345.4 | AG14: =AE14*0.268 -> 728248.56 | AI14: =AC14+AC14*0.268 -> 3445593.9 | AJ14: =AD14+AD14*0.268 -> 0 | AL14: =SUM(AI14:AJ14) -> 3445593.9 | AN14: =AL14/G14 -> 54691.967
A15: 1 | B15: =MID('02_Esperança'!$B$132,16,6) -> A4S1R3 | C15: =RIGHT(B15,2) -> R3 | D15: =MID('02_Esperança'!$A$3,51,10) -> Esperança | E15: =MID('02_Esperança'!$A$3,34,9) -> Esperança | G15: 44 | J15: ='02_Esperança'!K132 -> 1647346.8 | L15: 0 | M15: 0 | N15: 0 | O15: 0 | P15: 0 | R15: =SUM(J15:J15) -> 1647346.8 | S15: =SUM(M15:P15) -> 0 | U15: =R15+S15 -> 1647346.8 | W15: =U15*0.05 -> 82367.339 | X15: =U15*0.04 -> 65893.871 | Y15: =U15*0.01 -> 16473.468 | Z15: =U15*0.03 -> 49420.403 | AA15: =U15*0.005 -> 8236.7339 | AC15: =R15+SUM(W15:AA15) -> 1869738.6 | AD15: 0 | AE15: =SUM(AC15:AD15) -> 1869738.6 | AG15: =AE15*0.268 -> 501089.94 | AI15: =AC15+AC15*0.268 -> 2370828.5 | AJ15: =AD15+AD15*0.268 -> 0 | AL15: =SUM(AI15:AJ15) -> 2370828.5 | AN15: =AL15/G15 -> 53882.467
A16: 1 | B16: - | C16: =RIGHT(B16,2) -> - | D16: =MID('02_Esperança'!$A$3,51,10) -> Esperança | E16: =MID('02_Esperança'!$A$3,34,9) -> Esperança | H16: =SUM(G12:G15) -> 223 | J16: 0 | L16: ='02_Esperança'!H164 -> 121034.78 | M16: ='02_Esperança'!H177 -> 84077.4 | N16: ='02_Esperança'!H182 -> 1791988.5 | O16: ='02_Esperança'!H202 -> 36357.36 | P16: ='02_Esperança'!H205 -> 7316 | R16: =SUM(J16:J16) -> 0 | S16: =SUM(L16:P16) -> 2040774.1 | U16: =R16+S16 -> 2040774.1 | W16: =U16*0.05 -> 102038.7 | X16: =U16*0.04 -> 81630.963 | Y16: =U16*0.01 -> 20407.741 | Z16: =U16*0.03 -> 61223.222 | AA16: =U16*0.005 -> 10203.87 | AC16: 0 | AD16: =S16+SUM(W16:AA16) -> 2316278.6 | AE16: =SUM(AC16:AD16) -> 2316278.6 | AG16: =AE16*0.268 -> 620762.66 | AI16: =AC16+AC16*0.268 -> 0 | AJ16: =AD16+AD16*0.268 -> 2937041.2 | AL16: =SUM(AI16:AJ16) -> 2937041.2 | AN16: =AL16/H16 -> 13170.589
A18: 1 | B18: =MID('03_Aureliano'!$B$5,16,6) -> A1S1R4 | C18: =RIGHT(B18,2) -> R4 | D18: =MID('03_Aureliano'!$A$3,49,9) -> Esperança | E18: =MID('03_Aureliano'!$A$3,31,9) -> Aureliano | G18: 58 | J18: ='03_Aureliano'!K5 -> 3705680.7 | L18: 0 | M18: 0 | N18: 0 | O18: 0 | P18: 0 | R18: =SUM(J18:J18) -> 3705680.7 | S18: =SUM(L18:P18) -> 0 | U18: =R18+S18 -> 3705680.7 | W18: =U18*0.05 -> 185284.04 | X18: =U18*0.04 -> 148227.23 | Y18: =U18*0.01 -> 37056.807 | Z18: =U18*0.03 -> 111170.42 | AA18: =U18*0.005 -> 18528.404 | AC18: =R18+SUM(W18:AA18) -> 4205947.6 | AD18: 0 | AE18: =SUM(AC18:AD18) -> 4205947.6 | AG18: =AE18*0.268 -> 1127194 | AI18: =AC18+AC18*0.268 -> 5333141.6 | AJ18: =AD18+AD18*0.268 -> 0 | AL18: =SUM(AI18:AJ18) -> 5333141.6 | AN18: =AL18/G18 -> 91950.717
A19: 1 | B19: =MID('03_Aureliano'!$B$63,16,6) -> A2S1R3 | C19: =RIGHT(B19,2) -> R3 | D19: =MID('03_Aureliano'!$A$3,49,9) -> Esperança | E19: =MID('03_Aureliano'!$A$3,31,9) -> Aureliano | G19: 22 | J19: ='03_Aureliano'!K63 -> 1052807.1 | L19: 0 | M19: 0 | N19: 0 | O19: 0 | P19: 0 | R19: =SUM(J19:J19) -> 1052807.1 | S19: =SUM(L19:P19) -> 0 | U19: =R19+S19 -> 1052807.1 | W19: =U19*0.05 -> 52640.356 | X19: =U19*0.04 -> 42112.284 | Y19: =U19*0.01 -> 10528.071 | Z19: =U19*0.03 -> 31584.213 | AA19: =U19*0.005 -> 5264.0356 | AC19: =R19+SUM(W19:AA19) -> 1194936.1 | AD19: 0 | AE19: =SUM(AC19:AD19) -> 1194936.1 | AG19: =AE19*0.268 -> 320242.87 | AI19: =AC19+AC19*0.268 -> 1515178.9 | AJ19: =AD19+AD19*0.268 -> 0 | AL19: =SUM(AI19:AJ19) -> 1515178.9 | AN19: =AL19/G19 -> 68871.77
A20: 1 | B20: =MID('03_Aureliano'!$B$92,16,6) -> A2S3R3 | C20: =RIGHT(B20,2) -> R3 | D20: =MID('03_Aureliano'!$A$3,49,9) -> Esperança | E20: =MID('03_Aureliano'!$A$3,31,9) -> Aureliano | G20: 31 | J20: ='03_Aureliano'!K92 -> 473053.69 | L20: 0 | M20: 0 | N20: 0 | O20: 0 | P20: 0 | R20: =SUM(J20:J20) -> 473053.69 | S20: =SUM(L20:P20) -> 0 | U20: =R20+S20 -> 473053.69 | W20: =U20*0.05 -> 23652.684 | X20: =U20*0.04 -> 18922.148 | Y20: =U20*0.01 -> 4730.5369 | Z20: =U20*0.03 -> 14191.611 | AA20: =U20*0.005 -> 2365.2684 | AC20: =R20+SUM(W20:AA20) -> 536915.94 | AD20: 0 | AE20: =SUM(AC20:AD20) -> 536915.94 | AG20: =AE20*0.268 -> 143893.47 | AI20: =AC20+AC20*0.268 -> 680809.41 | AJ20: =AD20+AD20*0.268 -> 0 | AL20: =SUM(AI20:AJ20) -> 680809.41 | AN20: =AL20/G20 -> 21961.594
H21: =SUM(G18:G20) -> 111 | J21: 0 | L21: ='03_Aureliano'!H120 -> 105476.46 | M21: ='03_Aureliano'!H133 -> 1018718.2 | N21: ='03_Aureliano'!H141 -> 333735.71 | O21: ='03_Aureliano'!H145 -> 44671.64 | P21: 0 | R21: =SUM(J21:J21) -> 0 | S21: =SUM(L21:P21) -> 1502602 | U21: =R21+S21 -> 1502602 | W21: =U21*0.05 -> 75130.099 | X21: =U21*0.04 -> 60104.079 | Y21: =U21*0.01 -> 15026.02 | Z21: =U21*0.03 -> 45078.059 | AA21: =U21*0.005 -> 7513.0099 | AC21: 0 | AD21: =S21+SUM(W21:AA21) -> 1705453.2 | AE21: =SUM(AC21:AD21) -> 1705453.2 | AG21: =AE21*0.268 -> 457061.47 | AI21: =AC21+AC21*0.268 -> 0 | AJ21: =AD21+AD21*0.268 -> 2162514.7 | AL21: =SUM(AI21:AJ21) -> 2162514.7 | AN21: =AL21/H21 -> 19482.114
A23: 1 | B23: =MID('04_Seringal'!$B$5,16,6) -> A2S1R3 | C23: =RIGHT(B23,2) -> R3 | D23: =MID('04_Seringal'!$A$3,51,9) -> Esperança | E23: =MID('04_Seringal'!$A$3,34,9) -> Seringal | G23: 30 | J23: ='04_Seringal'!K5 -> 459537.89 | L23: 0 | M23: 0 | N23: 0 | O23: 0 | P23: 0 | R23: =SUM(J23:J23) -> 459537.89 | S23: =SUM(L23:P23) -> 0 | U23: =R23+S23 -> 459537.89 | W23: =U23*0.05 -> 22976.895 | X23: =U23*0.04 -> 18381.516 | Y23: =U23*0.01 -> 4595.3789 | Z23: =U23*0.03 -> 13786.137 | AA23: =U23*0.005 -> 2297.6895 | AC23: =R23+SUM(W23:AA23) -> 521575.51 | AD23: 0 | AE23: =SUM(AC23:AD23) -> 521575.51 | AG23: =AE23*0.268 -> 139782.24 | AI23: =AC23+AC23*0.268 -> 661357.74 | AJ23: =AD23+AD23*0.268 -> 0 | AL23: =SUM(AI23:AJ23) -> 661357.74 | AN23: =AL23/G23 -> 22045.258
A24: 1 | B24: =MID('04_Seringal'!$B$32,16,6) -> A3S1R4 | C24: =RIGHT(B24,2) -> R4 | D24: =MID('04_Seringal'!$A$3,51,9) -> Esperança | E24: =MID('04_Seringal'!$A$3,34,9) -> Seringal | G24: 83 | J24: ='04_Seringal'!K32 -> 2170818.4 | L24: 0 | M24: 0 | N24: 0 | O24: 0 | P24: 0 | R24: =SUM(J24:J24) -> 2170818.4 | S24: =SUM(L24:P24) -> 0 | U24: =R24+S24 -> 2170818.4 | W24: =U24*0.05 -> 108540.92 | X24: =U24*0.04 -> 86832.737 | Y24: =U24*0.01 -> 21708.184 | Z24: =U24*0.03 -> 65124.553 | AA24: =U24*0.005 -> 10854.092 | AC24: =R24+SUM(W24:AA24) -> 2463878.9 | AD24: 0 | AE24: =SUM(AC24:AD24) -> 2463878.9 | AG24: =AE24*0.268 -> 660319.55 | AI24: =AC24+AC24*0.268 -> 3124198.5 | AJ24: =AD24+AD24*0.268 -> 0 | AL24: =SUM(AI24:AJ24) -> 3124198.5 | AN24: =AL24/G24 -> 37640.945
H25: =SUM(G23:G24) -> 113 | J25: ='03_Aureliano'!K12 -> 0 | L25: ='04_Seringal'!H131 -> 26057.63 | M25: ='04_Seringal'!H95 -> 203825.04 | N25: ='04_Seringal'!H103 -> 150790.72 | O25: ='04_Seringal'!H123 -> 21560.76 | P25: ='04_Seringal'!H126 -> 11224 | R25: =SUM(J25:J25) -> 0 | S25: =SUM(L25:P25) -> 413458.15 | U25: =R25+S25 -> 413458.15 | W25: =U25*0.05 -> 20672.907 | X25: =U25*0.04 -> 16538.326 | Y25: =U25*0.01 -> 4134.5815 | Z25: =U25*0.03 -> 12403.744 | AA25: =U25*0.005 -> 2067.2907 | AC25: 0 | AD25: =S25+SUM(W25:AA25) -> 469275 | AE25: =SUM(AC25:AD25) -> 469275 | AG25: =AE25*0.268 -> 125765.7 | AI25: =AC25+AC25*0.268 -> 0 | AJ25: =AD25+AD25*0.268 -> 595040.7 | AL25: =SUM(AI25:AJ25) -> 595040.7 | AN25: =AL25/H25 -> 5265.8469
A27: 1 | B27: =MID('05_Vila Freitas'!$B$5,16,6) -> A1S1R3 | C27: =RIGHT(B27,2) -> R3 | D27: =MID('05_Vila Freitas'!$A$3,52,9) -> Esperança | E27: =MID('05_Vila Freitas'!$A$3,31,12) -> Vila Freitas | G27: 85 | J27: ='05_Vila Freitas'!K5 -> 800252.69 | L27: 0 | M27: 0 | N27: 0 | O27: 0 | P27: 0 | R27: =SUM(J27:J27) -> 800252.69 | S27: =SUM(L27:P27) -> 0 | U27: =R27+S27 -> 800252.69 | W27: =U27*0.05 -> 40012.635 | X27: =U27*0.04 -> 32010.108 | Y27: =U27*0.01 -> 8002.5269 | Z27: =U27*0.03 -> 24007.581 | AA27: =U27*0.005 -> 4001.2635 | AC27: =R27+SUM(W27:AA27) -> 908286.81 | AD27: 0 | AE27: =SUM(AC27:AD27) -> 908286.81 | AG27: =AE27*0.268 -> 243420.86 | AI27: =AC27+AC27*0.268 -> 1151707.7 | AJ27: =AD27+AD27*0.268 -> 0 | AL27: =SUM(AI27:AJ27) -> 1151707.7 | AN27: =AL27/G27 -> 13549.502
H28: =G27 -> 85 | J28: ='03_Aureliano'!K15 -> 0 | L28: 0 | M28: ='05_Vila Freitas'!H40 -> 475239.53 | N28: ='05_Vila Freitas'!H48 -> 495930.39 | O28: ='05_Vila Freitas'!H54 -> 31269 | P28: ='05_Vila Freitas'!H57 -> 24092 | R28: =SUM(J28:J28) -> 0 | S28: =SUM(L28:P28) -> 1026530.9 | U28: =R28+S28 -> 1026530.9 | W28: =U28*0.05 -> 51326.546 | X28: =U28*0.04 -> 41061.237 | Y28: =U28*0.01 -> 10265.309 | Z28: =U28*0.03 -> 30795.927 | AA28: =U28*0.005 -> 5132.6546 | AC28: 0 | AD28: =S28+SUM(W28:AA28) -> 1165112.6 | AE28: =SUM(AC28:AD28) -> 1165112.6 | AG28: =AE28*0.268 -> 312250.17 | AI28: =AC28+AC28*0.268 -> 0 | AJ28: =AD28+AD28*0.268 -> 1477362.8 | AL28: =SUM(AI28:AJ28) -> 1477362.8 | AN28: =AL28/H28 -> 17380.738
A30: 1 | B30: =MID('06_Nova Esperança'!$B$5,16,6) -> A1S1R3 | C30: =RIGHT(B30,2) -> R3 | D30: =MID('06_Nova Esperança'!$A$3,54,9) -> Esperança | E30: =MID('06_Nova Esperança'!$A$3,31,14) -> Nova Esperança | G30: 48 | J30: ='06_Nova Esperança'!K5 -> 1071693.6 | L30: 0 | M30: 0 | N30: 0 | O30: 0 | P30: 0 | R30: =SUM(J30:J30) -> 1071693.6 | S30: =SUM(L30:P30) -> 0 | U30: =R30+S30 -> 1071693.6 | W30: =U30*0.05 -> 53584.68 | X30: =U30*0.04 -> 42867.744 | Y30: =U30*0.01 -> 10716.936 | Z30: =U30*0.03 -> 32150.808 | AA30: =U30*0.005 -> 5358.468 | AC30: =R30+SUM(W30:AA30) -> 1216372.2 | AD30: 0 | AE30: =SUM(AC30:AD30) -> 1216372.2 | AG30: =AE30*0.268 -> 325987.76 | AI30: =AC30+AC30*0.268 -> 1542360 | AJ30: =AD30+AD30*0.268 -> 0 | AL30: =SUM(AI30:AJ30) -> 1542360 | AN30: =AL30/G30 -> 32132.5
H31: =G30 -> 48 | J31: 0 | L31: 0 | M31: ='06_Nova Esperança'!H40 -> 207217.88 | N31: 0 | O31: 0 | P31: ='06_Nova Esperança'!H48 -> 5706 | R31: =SUM(J31:J31) -> 0 | S31: =SUM(L31:P31) -> 212923.88 | U31: =R31+S31 -> 212923.88 | W31: =U31*0.05 -> 10646.194 | X31: =U31*0.04 -> 8516.9551 | Y31: =U31*0.01 -> 2129.2388 | Z31: =U31*0.03 -> 6387.7163 | AA31: =U31*0.005 -> 1064.6194 | AC31: 0 | AD31: =S31+SUM(W31:AA31) -> 241668.6 | AE31: =SUM(AC31:AD31) -> 241668.6 | AG31: =AE31*0.268 -> 64767.185 | AI31: =AC31+AC31*0.268 -> 0 | AJ31: =AD31+AD31*0.268 -> 306435.79 | AL31: =SUM(AI31:AJ31) -> 306435.79 | AN31: =AL31/H31 -> 6384.0789
A33: 1 | B33: =MID('07_Floresta'!$B$5,16,6) -> A4S2R3 | C33: =RIGHT(B33,2) -> R3 | D33: =MID('07_Floresta'!$A$3,51,7) -> Malhado | E33: =MID('07_Floresta'!$A$3,34,8) -> Floresta | G33: 15 | J33: ='07_Floresta'!K5 -> 504489.82 | L33: 0 | M33: 0 | N33: 0 | O33: 0 | P33: 0 | R33: =SUM(J33:J33) -> 504489.82 | S33: =SUM(L33:P33) -> 0 | U33: =R33+S33 -> 504489.82 | W33: =U33*0.05 -> 25224.491 | X33: =U33*0.04 -> 20179.593 | Y33: =U33*0.01 -> 5044.8982 | Z33: =U33*0.03 -> 15134.695 | AA33: =U33*0.005 -> 2522.4491 | AC33: =R33+SUM(W33:AA33) -> 572595.95 | AD33: 0 | AE33: =SUM(AC33:AD33) -> 572595.95 | AG33: =AE33*0.268 -> 153455.71 | AI33: =AC33+AC33*0.268 -> 726051.66 | AJ33: =AD33+AD33*0.268 -> 0 | AL33: =SUM(AI33:AJ33) -> 726051.66 | AN33: =AL33/G33 -> 48403.444
A34: 1 | B34: =MID('07_Floresta'!$B$16,16,6) -> A4S5R3 | C34: =RIGHT(B34,2) -> R3 | D34: =MID('07_Floresta'!$A$3,51,7) -> Malhado | E34: =MID('07_Floresta'!$A$3,34,8) -> Floresta | G34: 63 | J34: ='07_Floresta'!K16 -> 2693265.8 | L34: 0 | M34: 0 | N34: 0 | O34: 0 | P34: 0 | R34: =SUM(J34:J34) -> 2693265.8 | S34: =SUM(L34:P34) -> 0 | U34: =R34+S34 -> 2693265.8 | W34: =U34*0.05 -> 134663.29 | X34: =U34*0.04 -> 107730.63 | Y34: =U34*0.01 -> 26932.658 | Z34: =U34*0.03 -> 80797.974 | AA34: =U34*0.005 -> 13466.329 | AC34: =R34+SUM(W34:AA34) -> 3056856.7 | AD34: 0 | AE34: =SUM(AC34:AD34) -> 3056856.7 | AG34: =AE34*0.268 -> 819237.59 | AI34: =AC34+AC34*0.268 -> 3876094.3 | AJ34: =AD34+AD34*0.268 -> 0 | AL34: =SUM(AI34:AJ34) -> 3876094.3 | AN34: =AL34/G34 -> 61525.306
A35: 1 | B35: =MID('07_Floresta'!$B$47,16,6) -> A4S6R4 | C35: =RIGHT(B35,2) -> R4 | D35: =MID('07_Floresta'!$A$3,51,7) -> Malhado | E35: =MID('07_Floresta'!$A$3,34,8) -> Floresta | G35: 124 | J35: ='07_Floresta'!K47 -> 757999.24 | L35: 0 | M35: 0 | N35: 0 | O35: 0 | P35: 0 | R35: =SUM(J35:J35) -> 757999.24 | S35: =SUM(L35:P35) -> 0 | U35: =R35+S35 -> 757999.24 | W35: =U35*0.05 -> 37899.962 | X35: =U35*0.04 -> 30319.97 | Y35: =U35*0.01 -> 7579.9924 | Z35: =U35*0.03 -> 22739.977 | AA35: =U35*0.005 -> 3789.9962 | AC35: 0 | AD35: =S35+SUM(W35:AA35) -> 102329.9 | AE35: =SUM(AC35:AD35) -> 102329.9 | AG35: =AE35*0.268 -> 27424.413 | AI35: =AC35+AC35*0.268 -> 0 | AJ35: =AD35+AD35*0.268 -> 129754.31 | AL35: =SUM(AI35:AJ35) -> 129754.31 | AN35: =AL35/G35 -> 1046.4057
H36: =SUM(G33:G35) -> 202 | J36: 0 | L36: 0 | M36: 0 | N36: 0 | O36: 0 | P36: 0 | R36: =SUM(J36:J36) -> 0 | S36: =SUM(L36:P36) -> 0 | U36: =R36+S36 -> 0 | W36: =U36*0.05 -> 0 | X36: =U36*0.04 -> 0 | Y36: =U36*0.01 -> 0 | Z36: =U36*0.03 -> 0 | AA36: =U36*0.005 -> 0 | AC36: 0 | AD36: =S36+SUM(W36:AA36) -> 0 | AE36: =SUM(AC36:AD36) -> 0 | AG36: =AE36*0.268 -> 0 | AI36: =AC36+AC36*0.268 -> 0 | AJ36: =AD36+AD36*0.268 -> 0 | AL36: =SUM(AI36:AJ36) -> 0 | AN36: =AL36/H36 -> 0
A38: 1 | B38: =MID('08_Coqueiro'!$B$5,16,6) -> A2S1R3 | C38: =RIGHT(B38,2) -> R3 | D38: =MID('08_Coqueiro'!$A$3,51,7) -> Malhado | E38: =MID('08_Coqueiro'!$A$3,34,8) -> Coqueiro | G38: 25 | J38: ='08_Coqueiro'!K5 -> 995770.49 | L38: 0 | M38: 0 | N38: 0 | O38: 0 | P38: 0 | R38: =SUM(J38:J38) -> 995770.49 | S38: =SUM(L38:P38) -> 0 | U38: =R38+S38 -> 995770.49 | W38: =U38*0.05 -> 49788.524 | X38: =U38*0.04 -> 39830.82 | Y38: =U38*0.01 -> 9957.7049 | Z38: =U38*0.03 -> 29873.115 | AA38: =U38*0.005 -> 4978.8525 | AC38: =R38+SUM(W38:AA38) -> 1130199.5 | AD38: 0 | AE38: =SUM(AC38:AD38) -> 1130199.5 | AG38: =AE38*0.268 -> 302893.47 | AI38: =AC38+AC38*0.268 -> 1433093 | AJ38: =AD38+AD38*0.268 -> 0 | AL38: =SUM(AI38:AJ38) -> 1433093 | AN38: =AL38/G38 -> 57323.719
A39: 1 | B39: =MID('08_Coqueiro'!$B$41,16,6) -> A3S2R3 | C39: =RIGHT(B39,2) -> R3 | D39: =MID('08_Coqueiro'!$A$3,51,7) -> Malhado | E39: =MID('08_Coqueiro'!$A$3,34,8) -> Coqueiro | G39: 98 | J39: ='08_Coqueiro'!K41 -> 3858154.4 | L39: 0 | M39: 0 | N39: 0 | O39: 0 | P39: 0 | R39: =SUM(J39:J39) -> 3858154.4 | S39: =SUM(L39:P39) -> 0 | U39: =R39+S39 -> 3858154.4 | W39: =U39*0.05 -> 192907.72 | X39: =U39*0.04 -> 154326.18 | Y39: =U39*0.01 -> 38581.544 | Z39: =U39*0.03 -> 115744.63 | AA39: =U39*0.005 -> 19290.772 | AC39: =R39+SUM(W39:AA39) -> 4379005.3 | AD39: 0 | AE39: =SUM(AC39:AD39) -> 4379005.3 | AG39: =AE39*0.268 -> 1173573.4 | AI39: =AC39+AC39*0.268 -> 5552578.7 | AJ39: =AD39+AD39*0.268 -> 0 | AL39: =SUM(AI39:AJ39) -> 5552578.7 | AN39: =AL39/G39 -> 56658.966
A40: 1 | B40: =MID('08_Coqueiro'!$B$57,16,6) -> A5S1R3 | C40: =RIGHT(B40,2) -> R3 | D40: =MID('08_Coqueiro'!$A$3,51,7) -> Malhado | E40: =MID('08_Coqueiro'!$A$3,34,8) -> Coqueiro | G40: 9 | J40: ='08_Coqueiro'!K57 -> 34360.77 | L40: 0 | M40: 0 | N40: 0 | O40: 0 | P40: 0 | R40: =SUM(J40:J40) -> 34360.77 | S40: =SUM(L40:P40) -> 0 | U40: =R40+S40 -> 34360.77 | W40: =U40*0.05 -> 1718.0385 | X40: =U40*0.04 -> 1374.4308 | Y40: =U40*0.01 -> 343.6077 | Z40: =U40*0.03 -> 1030.8231 | AA40: =U40*0.005 -> 171.80385 | AC40: =R40+SUM(W40:AA40) -> 38999.474 | AD40: 0 | AE40: =SUM(AC40:AD40) -> 38999.474 | AG40: =AE40*0.268 -> 10451.859 | AI40: =AC40+AC40*0.268 -> 49451.333 | AJ40: =AD40+AD40*0.268 -> 0 | AL40: =SUM(AI40:AJ40) -> 49451.333 | AN40: =AL40/G40 -> 5494.5926
A41: 1 | B41: =MID('08_Coqueiro'!$B$73,16,6) -> A6S1R4 | C41: =RIGHT(B41,2) -> R4 | D41: =MID('08_Coqueiro'!$A$3,51,7) -> Malhado | E41: =MID('08_Coqueiro'!$A$3,34,8) -> Coqueiro | G41: 10 | J41: ='08_Coqueiro'!K73 -> 453427.49 | L41: 0 | M41: 0 | N41: 0 | O41: 0 | P41: 0 | R41: =SUM(J41:J41) -> 453427.49 | S41: =SUM(L41:P41) -> 0 | U41: =R41+S41 -> 453427.49 | W41: =U41*0.05 -> 22671.375 | X41: =U41*0.04 -> 18137.1 | Y41: =U41*0.01 -> 4534.2749 | Z41: =U41*0.03 -> 13602.825 | AA41: =U41*0.005 -> 2267.1375 | AC41: =R41+SUM(W41:AA41) -> 514640.2 | AD41: 0 | AE41: =SUM(AC41:AD41) -> 514640.2 | AG41: =AE41*0.268 -> 137923.57 | AI41: =AC41+AC41*0.268 -> 652563.78 | AJ41: =AD41+AD41*0.268 -> 0 | AL41: =SUM(AI41:AJ41) -> 652563.78 | AN41: =AL41/G41 -> 65256.378
H42: =SUM(G38:G41) -> 142 | J42: 0 | L42: ='08_Coqueiro'!H94 -> 139725.19 | M42: ='08_Coqueiro'!H100 -> 487554.32 | N42: ='08_Coqueiro'!H106 -> 4882545.1 | O42: ='08_Coqueiro'!H126 -> 224274.18 | P42: ='08_Coqueiro'!H129 -> 72436 | R42: =SUM(J42:J42) -> 0 | S42: =SUM(L42:P42) -> 5806534.8 | U42: =R42+S42 -> 5806534.8 | W42: =U42*0.05 -> 290326.74 | X42: =U42*0.04 -> 232261.39 | Y42: =U42*0.01 -> 58065.348 | Z42: =U42*0.03 -> 174196.04 | AA42: =U42*0.005 -> 29032.674 | AC42: 0 | AD42: =S42+SUM(W42:AA42) -> 6590417 | AE42: =SUM(AC42:AD42) -> 6590417 | AG42: =AE42*0.268 -> 1766231.8 | AI42: =AC42+AC42*0.268 -> 0 | AJ42: =AD42+AD42*0.268 -> 8356648.8 | AL42: =SUM(AI42:AJ42) -> 8356648.8 | AN42: =AL42/H42 -> 58849.639
A44: 1 | B44: =MID('09_Legião'!$B$5,16,6) -> A4S3R3 | C44: =RIGHT(B44,2) -> R3 | D44: =MID('09_Legião'!$A$3,49,7) -> Malhado | E44: =MID('09_Legião'!$A$3,34,6) -> Legião | G44: 13 | J44: ='09_Legião'!K5 -> 74337.03 | L44: 0 | M44: 0 | N44: 0 | O44: 0 | P44: 0 | R44: =SUM(J44:J44) -> 74337.03 | S44: =SUM(L44:P44) -> 0 | U44: =R44+S44 -> 74337.03 | W44: =U44*0.05 -> 3716.8515 | X44: =U44*0.04 -> 2973.4812 | Y44: =U44*0.01 -> 743.3703 | Z44: =U44*0.03 -> 2230.1109 | AA44: =U44*0.005 -> 371.68515 | AC44: =R44+SUM(W44:AA44) -> 84372.529 | AD44: 0 | AE44: =SUM(AC44:AD44) -> 84372.529 | AG44: =AE44*0.268 -> 22611.838 | AI44: =AC44+AC44*0.268 -> 106984.37 | AJ44: =AD44+AD44*0.268 -> 0 | AL44: =SUM(AI44:AJ44) -> 106984.37 | AN44: =AL44/G44 -> 8229.5667
A45: 1 | B45: =MID('09_Legião'!$B$32,16,6) -> A4S5R3 | C45: =RIGHT(B45,2) -> R3 | D45: =MID('09_Legião'!$A$3,49,7) -> Malhado | E45: =MID('09_Legião'!$A$3,34,6) -> Legião | G45: 22 | J45: ='09_Legião'!K32 -> 767384.04 | L45: 0 | M45: 0 | N45: 0 | O45: 0 | P45: 0 | R45: =SUM(J45:J45) -> 767384.04 | S45: =SUM(L45:P45) -> 0 | U45: =R45+S45 -> 767384.04 | W45: =U45*0.05 -> 38369.202 | X45: =U45*0.04 -> 30695.362 | Y45: =U45*0.01 -> 7673.8404 | Z45: =U45*0.03 -> 23021.521 | AA45: =U45*0.005 -> 3836.9202 | AC45: =R45+SUM(W45:AA45) -> 870980.89 | AD45: 0 | AE45: =SUM(AC45:AD45) -> 870980.89 | AG45: =AE45*0.268 -> 233422.88 | AI45: =AC45+AC45*0.268 -> 1104403.8 | AJ45: =AD45+AD45*0.268 -> 0 | AL45: =SUM(AI45:AJ45) -> 1104403.8 | AN45: =AL45/G45 -> 50200.171
A46: 1 | B46: =MID('09_Legião'!$B$52,16,6) -> A4S7R3 | C46: =RIGHT(B46,2) -> R3 | D46: =MID('09_Legião'!$A$3,49,7) -> Malhado | E46: =MID('09_Legião'!$A$3,34,6) -> Legião | G46: 38 | J46: ='09_Legião'!K52 -> 1032007.3 | L46: 0 | M46: 0 | N46: 0 | O46: 0 | P46: 0 | R46: =SUM(J46:J46) -> 1032007.3 | S46: =SUM(L46:P46) -> 0 | U46: =R46+S46 -> 1032007.3 | W46: =U46*0.05 -> 51600.366 | X46: =U46*0.04 -> 41280.293 | Y46: =U46*0.01 -> 10320.073 | Z46: =U46*0.03 -> 30960.22 | AA46: =U46*0.005 -> 5160.0366 | AC46: =R46+SUM(W46:AA46) -> 1171328.3 | AD46: 0 | AE46: =SUM(AC46:AD46) -> 1171328.3 | AG46: =AE46*0.268 -> 313915.99 | AI46: =AC46+AC46*0.268 -> 1485244.3 | AJ46: =AD46+AD46*0.268 -> 0 | AL46: =SUM(AI46:AJ46) -> 1485244.3 | AN46: =AL46/G46 -> 39085.376
H47: =SUM(G44:G46) -> 73 | J47: 0 | L47: 0 | M47: 0 | N47: 0 | O47: 0 | P47: 0 | R47: =SUM(J47:J47) -> 0 | S47: =SUM(L47:P47) -> 0 | U47: =R47+S47 -> 0 | W47: =U47*0.05 -> 0 | X47: =U47*0.04 -> 0 | Y47: =U47*0.01 -> 0 | Z47: =U47*0.03 -> 0 | AA47: =U47*0.005 -> 0 | AC47: 0 | AD47: =S47+SUM(W47:AA47) -> 0 | AE47: =SUM(AC47:AD47) -> 0 | AG47: =AE47*0.268 -> 0 | AI47: =AC47+AC47*0.268 -> 0 | AJ47: =AD47+AD47*0.268 -> 0 | AL47: =SUM(AI47:AJ47) -> 0 | AN47: =AL47/H47 -> 0
A49: 1 | B49: =MID('10_Amparo'!$B$5,16,6) -> A2S1R3 | C49: =RIGHT(B49,2) -> R3 | D49: =MID('10_Amparo'!$A$3,49,7) -> Malhado | E49: =MID('10_Amparo'!$A$3,34,6) -> Amparo | G49: 35 | J49: ='10_Amparo'!K5 -> 901859.2 | L49: 0 | M49: 0 | N49: 0 | O49: 0 | P49: 0 | R49: =SUM(J49:J49) -> 901859.2 | S49: =SUM(L49:P49) -> 0 | U49: =R49+S49 -> 901859.2 | W49: =U49*0.05 -> 45092.96 | X49: =U49*0.04 -> 36074.368 | Y49: =U49*0.01 -> 9018.592 | Z49: =U49*0.03 -> 27055.776 | AA49: =U49*0.005 -> 4509.296 | AC49: =R49+SUM(W49:AA49) -> 1023610.2 | AD49: 0 | AE49: =SUM(AC49:AD49) -> 1023610.2 | AG49: =AE49*0.268 -> 274327.53 | AI49: =AC49+AC49*0.268 -> 1297937.7 | AJ49: =AD49+AD49*0.268 -> 0 | AL49: =SUM(AI49:AJ49) -> 1297937.7 | AN49: =AL49/G49 -> 37083.935
A50: 1 | B50: =MID('10_Amparo'!$B$71,16,6) -> A2S2R3 | C50: =RIGHT(B50,2) -> R3 | D50: =MID('10_Amparo'!$A$3,49,7) -> Malhado | E50: =MID('10_Amparo'!$A$3,34,6) -> Amparo | G50: 49 | J50: ='10_Amparo'!K71 -> 1027315.7 | L50: 0 | M50: 0 | N50: 0 | O50: 0 | P50: 0 | R50: =SUM(J50:J50) -> 1027315.7 | S50: =SUM(L50:P50) -> 0 | U50: =R50+S50 -> 1027315.7 | W50: =U50*0.05 -> 51365.786 | X50: =U50*0.04 -> 41092.628 | Y50: =U50*0.01 -> 10273.157 | Z50: =U50*0.03 -> 30819.471 | AA50: =U50*0.005 -> 5136.5786 | AC50: =R50+SUM(W50:AA50) -> 1166003.3 | AD50: 0 | AE50: =SUM(AC50:AD50) -> 1166003.3 | AG50: =AE50*0.268 -> 312488.89 | AI50: =AC50+AC50*0.268 -> 1478492.2 | AJ50: =AD50+AD50*0.268 -> 0 | AL50: =SUM(AI50:AJ50) -> 1478492.2 | AN50: =AL50/G50 -> 30173.311
A51: 1 | B51: =MID('10_Amparo'!$B$21,16,6) -> A3S3R4 | C51: =RIGHT(B51,2) -> R4 | D51: =MID('10_Amparo'!$A$3,49,7) -> Malhado | E51: =MID('10_Amparo'!$A$3,34,6) -> Amparo | G51: 98 | J51: ='10_Amparo'!K21 -> 116492.07 | L51: 0 | M51: 0 | N51: 0 | O51: 0 | P51: 0 | R51: =SUM(J51:J51) -> 116492.07 | S51: =SUM(L51:P51) -> 0 | U51: =R51+S51 -> 116492.07 | W51: =U51*0.05 -> 5824.6035 | X51: =U51*0.04 -> 4659.6828 | Y51: =U51*0.01 -> 1164.9207 | Z51: =U51*0.03 -> 3494.7621 | AA51: =U51*0.005 -> 582.46035 | AC51: =R51+SUM(W51:AA51) -> 132218.5 | AD51: 0 | AE51: =SUM(AC51:AD51) -> 132218.5 | AG51: =AE51*0.268 -> 35434.558 | AI51: =AC51+AC51*0.268 -> 167653.06 | AJ51: =AD51+AD51*0.268 -> 0 | AL51: =SUM(AI51:AJ51) -> 167653.06 | AN51: =AL51/G51 -> 1710.7455
A52: 1 | B52: =MID('10_Amparo'!$B$37,16,6) -> A3S5R3 | C52: =RIGHT(B52,2) -> R3 | D52: =MID('10_Amparo'!$A$3,49,7) -> Malhado | E52: =MID('10_Amparo'!$A$3,34,6) -> Amparo | G52: 48 | J52: ='10_Amparo'!K37 -> 1154361.5 | L52: 0 | M52: 0 | N52: 0 | O52: 0 | P52: 0 | R52: =SUM(J52:J52) -> 1154361.5 | S52: =SUM(L52:P52) -> 0 | U52: =R52+S52 -> 1154361.5 | W52: =U52*0.05 -> 57718.073 | X52: =U52*0.04 -> 46174.459 | Y52: =U52*0.01 -> 11543.615 | Z52: =U52*0.03 -> 34630.844 | AA52: =U52*0.005 -> 5771.8074 | AC52: =R52+SUM(W52:AA52) -> 1310200.3 | AD52: 0 | AE52: =SUM(AC52:AD52) -> 1310200.3 | AG52: =AE52*0.268 -> 351133.67 | AI52: =AC52+AC52*0.268 -> 1661333.9 | AJ52: =AD52+AD52*0.268 -> 0 | AL52: =SUM(AI52:AJ52) -> 1661333.9 | AN52: =AL52/G52 -> 34611.124
A53: 1 | B53: =MID('10_Amparo'!$B$53,16,6) -> A3S6R4 | C53: =RIGHT(B53,2) -> R4 | D53: =MID('10_Amparo'!$A$3,49,7) -> Malhado | E53: =MID('10_Amparo'!$A$3,34,6) -> Amparo | G53: 24 | J53: ='10_Amparo'!K53 -> 734263.17 | L53: 0 | M53: 0 | N53: 0 | O53: 0 | P53: 0 | R53: =SUM(J53:J53) -> 734263.17 | S53: =SUM(L53:P53) -> 0 | U53: =R53+S53 -> 734263.17 | W53: =U53*0.05 -> 36713.158 | X53: =U53*0.04 -> 29370.527 | Y53: =U53*0.01 -> 7342.6317 | Z53: =U53*0.03 -> 22027.895 | AA53: =U53*0.005 -> 3671.3158 | AC53: =R53+SUM(W53:AA53) -> 833388.7 | AD53: 0 | AE53: =SUM(AC53:AD53) -> 833388.7 | AG53: =AE53*0.268 -> 223348.17 | AI53: =AC53+AC53*0.268 -> 1056736.9 | AJ53: =AD53+AD53*0.268 -> 0 | AL53: =SUM(AI53:AJ53) -> 1056736.9 | AN53: =AL53/G53 -> 44030.703
C54: =RIGHT(B54,2) | H54: =SUM(G49:G53) -> 254 | J54: 0 | L54: ='10_Amparo'!H88 -> 876930.38 | M54: ='10_Amparo'!H94 -> 579371.19 | N54: ='10_Amparo'!H102 -> 3619626.2 | O54: ='10_Amparo'!H122 -> 283051.52 | P54: ='10_Amparo'!H127 -> 38988 | R54: =SUM(J54:J54) -> 0 | S54: =SUM(L54:P54) -> 5397967.3 | U54: =R54+S54 -> 5397967.3 | W54: =U54*0.05 -> 269898.36 | X54: =U54*0.04 -> 215918.69 | Y54: =U54*0.01 -> 53979.673 | Z54: =U54*0.03 -> 161939.02 | AA54: =U54*0.005 -> 26989.836 | AC54: 0 | AD54: =S54+SUM(W54:AA54) -> 6126692.9 | AE54: =SUM(AC54:AD54) -> 6126692.9 | AG54: =AE54*0.268 -> 1641953.7 | AI54: =AC54+AC54*0.268 -> 0 | AJ54: =AD54+AD54*0.268 -> 7768646.6 | AL54: =SUM(AI54:AJ54) -> 7768646.6 | AN54: =AL54/H54 -> 30585.223
A56: 1 | B56: =MID('11_Nerival'!$B$5,16,6) -> A1S1R4 | C56: =RIGHT(B56,2) -> R4 | D56: =MID('11_Nerival'!$A$3,47,11) -> Barra Taipe | E56: =MID('11_Nerival'!$A$3,31,7) -> Nerival | G56: 16 | J56: ='11_Nerival'!K5 -> 264588.04 | L56: 0 | M56: 0 | N56: 0 | O56: 0 | P56: 0 | R56: =SUM(J56:J56) -> 264588.04 | S56: =SUM(L56:P56) -> 0 | U56: =R56+S56 -> 264588.04 | W56: =U56*0.05 -> 13229.402 | X56: =U56*0.04 -> 10583.522 | Y56: =U56*0.01 -> 2645.8804 | Z56: =U56*0.03 -> 7937.6412 | AA56: =U56*0.005 -> 1322.9402 | AC56: =R56+SUM(W56:AA56) -> 300307.43 | AD56: 0 | AE56: =SUM(AC56:AD56) -> 300307.43 | AG56: =AE56*0.268 -> 80482.39 | AI56: =AC56+AC56*0.268 -> 380789.82 | AJ56: =AD56+AD56*0.268 -> 0 | AL56: =SUM(AI56:AJ56) -> 380789.82 | AN56: =AL56/G56 -> 23799.363
A57: 1 | B57: =MID('11_Nerival'!$B$19,16,6) -> A1S2R3 | C57: =RIGHT(B57,2) -> R3 | D57: =MID('11_Nerival'!$A$3,47,11) -> Barra Taipe | E57: =MID('11_Nerival'!$A$3,31,7) -> Nerival | G57: 40 | J57: ='11_Nerival'!K19 -> 296480.31 | L57: 0 | M57: 0 | N57: 0 | O57: 0 | P57: 0 | R57: =SUM(J57:J57) -> 296480.31 | S57: =SUM(L57:P57) -> 0 | U57: =R57+S57 -> 296480.31 | W57: =U57*0.05 -> 14824.016 | X57: =U57*0.04 -> 11859.212 | Y57: =U57*0.01 -> 2964.8031 | Z57: =U57*0.03 -> 8894.4093 | AA57: =U57*0.005 -> 1482.4016 | AC57: =R57+SUM(W57:AA57) -> 336505.15 | AD57: 0 | AE57: =SUM(AC57:AD57) -> 336505.15 | AG57: =AE57*0.268 -> 90183.381 | AI57: =AC57+AC57*0.268 -> 426688.53 | AJ57: =AD57+AD57*0.268 -> 0 | AL57: =SUM(AI57:AJ57) -> 426688.53 | AN57: =AL57/G57 -> 10667.213
A58: 1 | B58: =MID('11_Nerival'!$B$54,16,6) -> A2S1R4 | C58: =RIGHT(B58,2) -> R4 | D58: =MID('11_Nerival'!$A$3,47,11) -> Barra Taipe | E58: =MID('11_Nerival'!$A$3,31,7) -> Nerival | G58: 16 | J58: ='11_Nerival'!K54 -> 836296 | L58: 0 | M58: 0 | N58: 0 | O58: 0 | P58: 0 | R58: =SUM(J58:J58) -> 836296 | S58: =SUM(L58:P58) -> 0 | U58: =R58+S58 -> 836296 | W58: =U58*0.05 -> 41814.8 | X58: =U58*0.04 -> 33451.84 | Y58: =U58*0.01 -> 8362.96 | Z58: =U58*0.03 -> 25088.88 | AA58: =U58*0.005 -> 4181.48 | AC58: =R58+SUM(W58:AA58) -> 949195.96 | AD58: 0 | AE58: =SUM(AC58:AD58) -> 949195.96 | AG58: =AE58*0.268 -> 254384.52 | AI58: =AC58+AC58*0.268 -> 1203580.5 | AJ58: =AD58+AD58*0.268 -> 0 | AL58: =SUM(AI58:AJ58) -> 1203580.5 | AN58: =AL58/G58 -> 75223.78
A59: 1 | B59: =MID('11_Nerival'!$B$85,16,6) -> A2S2R3 | C59: =RIGHT(B59,2) -> R3 | D59: =MID('11_Nerival'!$A$3,47,11) -> Barra Taipe | E59: =MID('11_Nerival'!$A$3,31,7) -> Nerival | G59: 41 | J59: ='11_Nerival'!K85 -> 2259860 | L59: 0 | M59: 0 | N59: 0 | O59: 0 | P59: 0 | R59: =SUM(J59:J59) -> 2259860 | S59: =SUM(L59:P59) -> 0 | U59: =R59+S59 -> 2259860 | W59: =U59*0.05 -> 112993 | X59: =U59*0.04 -> 90394.4 | Y59: =U59*0.01 -> 22598.6 | Z59: =U59*0.03 -> 67795.8 | AA59: =U59*0.005 -> 11299.3 | AC59: =R59+SUM(W59:AA59) -> 2564941.1 | AD59: 0 | AE59: =SUM(AC59:AD59) -> 2564941.1 | AG59: =AE59*0.268 -> 687404.22 | AI59: =AC59+AC59*0.268 -> 3252345.3 | AJ59: =AD59+AD59*0.268 -> 0 | AL59: =SUM(AI59:AJ59) -> 3252345.3 | AN59: =AL59/G59 -> 79325.496
A60: 1 | B60: =MID('11_Nerival'!$B$116,16,6) -> A3S2R3 | C60: =RIGHT(B60,2) -> R3 | D60: =MID('11_Nerival'!$A$3,47,11) -> Barra Taipe | E60: =MID('11_Nerival'!$A$3,31,7) -> Nerival | G60: 4 | J60: ='11_Nerival'!K116 -> 229768.93 | L60: 0 | M60: 0 | N60: 0 | O60: 0 | P60: 0 | R60: =SUM(J60:J60) -> 229768.93 | S60: =SUM(L60:P60) -> 0 | U60: =R60+S60 -> 229768.93 | W60: =U60*0.05 -> 11488.447 | X60: =U60*0.04 -> 9190.7572 | Y60: =U60*0.01 -> 2297.6893 | Z60: =U60*0.03 -> 6893.0679 | AA60: =U60*0.005 -> 1148.8447 | AC60: =R60+SUM(W60:AA60) -> 260787.74 | AD60: 0 | AE60: =SUM(AC60:AD60) -> 260787.74 | AG60: =AE60*0.268 -> 69891.113 | AI60: =AC60+AC60*0.268 -> 330678.85 | AJ60: =AD60+AD60*0.268 -> 0 | AL60: =SUM(AI60:AJ60) -> 330678.85 | AN60: =AL60/G60 -> 82669.712
A61: 1 | B61: =MID('11_Nerival'!$B$143,16,6) -> A3S4R3 | C61: =RIGHT(B61,2) -> R3 | D61: =MID('11_Nerival'!$A$3,47,11) -> Barra Taipe | E61: =MID('11_Nerival'!$A$3,31,7) -> Nerival | G61: 9 | J61: ='11_Nerival'!K143 -> 155966.45 | L61: 0 | M61: 0 | N61: 0 | O61: 0 | P61: 0 | R61: =SUM(J61:J61) -> 155966.45 | S61: =SUM(L61:P61) -> 0 | U61: =R61+S61 -> 155966.45 | W61: =U61*0.05 -> 7798.3225 | X61: =U61*0.04 -> 6238.658 | Y61: =U61*0.01 -> 1559.6645 | Z61: =U61*0.03 -> 4678.9935 | AA61: =U61*0.005 -> 779.83225 | AC61: =R61+SUM(W61:AA61) -> 177021.92 | AD61: 0 | AE61: =SUM(AC61:AD61) -> 177021.92 | AG61: =AE61*0.268 -> 47441.875 | AI61: =AC61+AC61*0.268 -> 224463.8 | AJ61: =AD61+AD61*0.268 -> 0 | AL61: =SUM(AI61:AJ61) -> 224463.8 | AN61: =AL61/G61 -> 24940.422
A62: 1 | B62: =MID('11_Nerival'!$B$157,16,6) -> A3S5R4 | C62: =RIGHT(B62,2) -> R4 | D62: =MID('11_Nerival'!$A$3,47,11) -> Barra Taipe | E62: =MID('11_Nerival'!$A$3,31,7) -> Nerival | G62: 16 | J62: ='11_Nerival'!K157 -> 349817.36 | L62: 0 | M62: 0 | N62: 0 | O62: 0 | P62: 0 | R62: =SUM(J62:J62) -> 349817.36 | S62: =SUM(L62:P62) -> 0 | U62: =R62+S62 -> 349817.36 | W62: =U62*0.05 -> 17490.868 | X62: =U62*0.04 -> 13992.694 | Y62: =U62*0.01 -> 3498.1736 | Z62: =U62*0.03 -> 10494.521 | AA62: =U62*0.005 -> 1749.0868 | AC62: =R62+SUM(W62:AA62) -> 397042.7 | AD62: 0 | AE62: =SUM(AC62:AD62) -> 397042.7 | AG62: =AE62*0.268 -> 106407.44 | AI62: =AC62+AC62*0.268 -> 503450.15 | AJ62: =AD62+AD62*0.268 -> 0 | AL62: =SUM(AI62:AJ62) -> 503450.15 | AN62: =AL62/G62 -> 31465.634
A63: 1 | B63: =MID('11_Nerival'!$B$186,16,6) -> A3S6R3 | C63: =RIGHT(B63,2) -> R3 | D63: =MID('11_Nerival'!$A$3,47,11) -> Barra Taipe | E63: =MID('11_Nerival'!$A$3,31,7) -> Nerival | G63: 34 | J63: ='11_Nerival'!K186 -> 984713.28 | L63: 0 | M63: 0 | N63: 0 | O63: 0 | P63: 0 | R63: =SUM(J63:J63) -> 984713.28 | S63: =SUM(L63:P63) -> 0 | U63: =R63+S63 -> 984713.28 | W63: =U63*0.05 -> 49235.664 | X63: =U63*0.04 -> 39388.531 | Y63: =U63*0.01 -> 9847.1328 | Z63: =U63*0.03 -> 29541.398 | AA63: =U63*0.005 -> 4923.5664 | AC63: =R63+SUM(W63:AA63) -> 1117649.6 | AD63: 0 | AE63: =SUM(AC63:AD63) -> 1117649.6 | AG63: =AE63*0.268 -> 299530.09 | AI63: =AC63+AC63*0.268 -> 1417179.7 | AJ63: =AD63+AD63*0.268 -> 0 | AL63: =SUM(AI63:AJ63) -> 1417179.7 | AN63: =AL63/G63 -> 41681.755
H64: =SUM(G56:G63) -> 176 | J64: 0 | L64: ='11_Nerival'!H203 -> 79985.1 | M64: ='11_Nerival'!H216 -> 109222.28 | N64: ='11_Nerival'!H221 -> 3214069 | O64: ='11_Nerival'!H241 -> 215241.56 | P64: ='11_Nerival'!H246 -> 31672 | R64: =SUM(J64:J64) -> 0 | S64: =SUM(L64:P64) -> 3650189.9 | U64: =R64+S64 -> 3650189.9 | W64: =U64*0.05 -> 182509.5 | X64: =U64*0.04 -> 146007.6 | Y64: =U64*0.01 -> 36501.899 | Z64: =U64*0.03 -> 109505.7 | AA64: =U64*0.005 -> 18250.95 | AC64: 0 | AD64: =S64+SUM(W64:AA64) -> 4142965.6 | AE64: =SUM(AC64:AD64) -> 4142965.6 | AG64: =AE64*0.268 -> 1110314.8 | AH64: =W64+SUM(AA64:AE64) -> 8486691.6 | AI64: =AC64+AC64*0.268 -> 0 | AJ64: =AD64+AD64*0.268 -> 5253280.3 | AL64: =SUM(AI64:AJ64) -> 5253280.3 | AN64: =AL64/H64 -> 29848.184
A66: 1 | B66: =MID('12_Cano'!$B$5,16,6) -> A5S1R4 | C66: =RIGHT(B66,2) -> R4 | D66: =MID('12_Cano'!$A$3,47,11) -> Barra Taipe | E66: =MID('12_Cano'!$A$3,34,4) -> Cano | G66: 115 | J66: ='12_Cano'!K5 -> 1086649.4 | L66: 0 | M66: 0 | N66: 0 | O66: 0 | P66: 0 | R66: =SUM(J66:J66) -> 1086649.4 | S66: =SUM(L66:P66) -> 0 | U66: =R66+S66 -> 1086649.4 | W66: =U66*0.05 -> 54332.473 | X66: =U66*0.04 -> 43465.978 | Y66: =U66*0.01 -> 10866.494 | Z66: =U66*0.03 -> 32599.483 | AA66: =U66*0.005 -> 5433.2472 | AC66: =R66+SUM(W66:AA66) -> 1233347.1 | AD66: 0 | AE66: =SUM(AC66:AD66) -> 1233347.1 | AG66: =AE66*0.268 -> 330537.03 | AI66: =AC66+AC66*0.268 -> 1563884.2 | AJ66: =AD66+AD66*0.268 -> 0 | AL66: =SUM(AI66:AJ66) -> 1563884.2 | AN66: =AL66/G66 -> 13598.993
H67: =G66 -> 115 | J67: 0 | L67: 0 | M67: 0 | N67: 0 | O67: 0 | P67: 0 | R67: =SUM(J67:J67) -> 0 | S67: =SUM(L67:P67) -> 0 | U67: =R67+S67 -> 0 | W67: =U67*0.05 -> 0 | X67: =U67*0.04 -> 0 | Y67: =U67*0.01 -> 0 | Z67: =U67*0.03 -> 0 | AA67: =U67*0.005 -> 0 | AC67: 0 | AD67: =S67+SUM(W67:AA67) -> 0 | AE67: =SUM(AC67:AD67) -> 0 | AG67: =AE67*0.268 -> 0 | AI67: =AC67+AC67*0.268 -> 0 | AJ67: =AD67+AD67*0.268 -> 0 | AL67: =SUM(AI67:AJ67) -> 0 | AN67: =AL67/H67 -> 0
A69: 1 | B69: =MID('13_Soledade'!$B$5,16,6) -> A1S1R4 | C69: =RIGHT(B69,2) -> R4 | D69: =MID('13_Soledade'!$A$3,48,11) -> Barra Taipe | E69: =MID('13_Soledade'!$A$3,31,8) -> Soledade | G69: 34 | J69: ='13_Soledade'!K5 -> 2062102.7 | L69: 0 | M69: 0 | N69: 0 | O69: 0 | P69: 0 | R69: =SUM(J69:J69) -> 2062102.7 | S69: =SUM(L69:P69) -> 0 | U69: =R69+S69 -> 2062102.7 | W69: =U69*0.05 -> 103105.13 | X69: =U69*0.04 -> 82484.108 | Y69: =U69*0.01 -> 20621.027 | Z69: =U69*0.03 -> 61863.081 | AA69: =U69*0.005 -> 10310.513 | AC69: =R69+SUM(W69:AA69) -> 2340486.6 | AD69: 0 | AE69: =SUM(AC69:AD69) -> 2340486.6 | AG69: =AE69*0.268 -> 627250.4 | AI69: =AC69+AC69*0.268 -> 2967737 | AJ69: =AD69+AD69*0.268 -> 0 | AL69: =SUM(AI69:AJ69) -> 2967737 | AN69: =AL69/G69 -> 87286.381
A70: 1 | B70: =MID('13_Soledade'!$B$43,16,6) -> A2S1R3 | C70: =RIGHT(B70,2) -> R3 | D70: =MID('13_Soledade'!$A$3,48,11) -> Barra Taipe | E70: =MID('13_Soledade'!$A$3,31,8) -> Soledade | G70: 42 | J70: ='13_Soledade'!K43 -> 314583.5 | L70: 0 | M70: 0 | N70: 0 | O70: 0 | P70: 0 | R70: =SUM(J70:J70) -> 314583.5 | S70: =SUM(L70:P70) -> 0 | U70: =R70+S70 -> 314583.5 | W70: =U70*0.05 -> 15729.175 | X70: =U70*0.04 -> 12583.34 | Y70: =U70*0.01 -> 3145.835 | Z70: =U70*0.03 -> 9437.5049 | AA70: =U70*0.005 -> 1572.9175 | AC70: =R70+SUM(W70:AA70) -> 357052.27 | AD70: 0 | AE70: =SUM(AC70:AD70) -> 357052.27 | AG70: =AE70*0.268 -> 95690.008 | AI70: =AC70+AC70*0.268 -> 452742.28 | AJ70: =AD70+AD70*0.268 -> 0 | AL70: =SUM(AI70:AJ70) -> 452742.28 | AN70: =AL70/G70 -> 10779.578
A71: 1 | B71: =MID('13_Soledade'!$B$81,16,6) -> A3S1R4 | C71: =RIGHT(B71,2) -> R4 | D71: =MID('13_Soledade'!$A$3,48,11) -> Barra Taipe | E71: =MID('13_Soledade'!$A$3,31,8) -> Soledade | G71: 41 | J71: ='13_Soledade'!K81 -> 537603.65 | L71: 0 | M71: 0 | N71: 0 | O71: 0 | P71: 0 | R71: =SUM(J71:J71) -> 537603.65 | S71: =SUM(L71:P71) -> 0 | U71: =R71+S71 -> 537603.65 | W71: =U71*0.05 -> 26880.182 | X71: =U71*0.04 -> 21504.146 | Y71: =U71*0.01 -> 5376.0365 | Z71: =U71*0.03 -> 16128.109 | AA71: =U71*0.005 -> 2688.0182 | AC71: =R71+SUM(W71:AA71) -> 610180.14 | AD71: 0 | AE71: =SUM(AC71:AD71) -> 610180.14 | AG71: =AE71*0.268 -> 163528.28 | AI71: =AC71+AC71*0.268 -> 773708.42 | AJ71: =AD71+AD71*0.268 -> 0 | AL71: =SUM(AI71:AJ71) -> 773708.42 | AN71: =AL71/G71 -> 18870.937
H72: =SUM(G69:G71) -> 117 | J72: 0 | L72: ='13_Soledade'!H116 -> 429849.51 | M72: ='13_Soledade'!H129 -> 932688.46 | N72: ='13_Soledade'!H137 -> 1326678.5 | O72: ='13_Soledade'!H157 -> 84481.54 | P72: ='13_Soledade'!H160 -> 41212 | R72: =SUM(J72:J72) -> 0 | S72: =SUM(L72:P72) -> 2814910 | U72: =R72+S72 -> 2814910 | W72: =U72*0.05 -> 140745.5 | X72: =U72*0.04 -> 112596.4 | Y72: =U72*0.01 -> 28149.1 | Z72: =U72*0.03 -> 84447.301 | AA72: =U72*0.005 -> 14074.55 | AC72: 0 | AD72: =S72+SUM(W72:AA72) -> 3194922.9 | AE72: =SUM(AC72:AD72) -> 3194922.9 | AG72: =AC72*0.268 -> 0 | AI72: =AC72+AC72*0.268 -> 0 | AJ72: =AD72+AD72*0.268 -> 4051162.2 | AL72: =SUM(AI72:AJ72) -> 4051162.2 | AN72: =AL72/H72 -> 34625.318
A74: SOMA | G74: =SUM(G5:G73) -> 1765 | H74: =SUM(H5:H73) -> 1765 | J74: =SUM(J5:J72) -> 41687215 | L74: =SUM(L5:L72) -> 1779059 | M74: =SUM(M5:M72) -> 4147012 | N74: =SUM(N5:N72) -> 16244547 | O74: =SUM(O5:O72) -> 951194.72 | P74: =SUM(P5:P72) -> 240462 | Q74: =SUM(Q5:Q72) -> 0 | R74: =SUM(R5:R72) -> 41687215 | S74: =SUM(S5:S72) -> 23362274 | ... V74: =SUM(V5:V72) -> 0 | AB74: =SUM(AB5:AB72) -> 0 | AC74: =SUM(AC5:AC72) -> 46454659 | AD74: =SUM(AD5:AD72) -> 26618511 | AE74: =SUM(AE5:AE72) -> 73073171 | AH74: =SUM(AH5:AH72) -> 8486691.6 | AI74: =SUM(AI5:AI72) -> 58904508 | AJ74: =SUM(AJ5:AJ72) -> 33752272 | AL74: =SUM(AL5:AL72) -> 92656780 | AM74: =SUM(AM5:AM72) -> 0 | AN74: =AL74/H74 -> 52496.759

Sheet 01_Carvalho
C1: PMRR DE ILHÉUS
C3: Empreendimento: 000058 - Alto do Carvalho (Bairro Esperança) | I3: VALOR TOTAL
A4: CODIGO_ALTO | B4: CODIGO_ORSE | C4: ITEM | D4: DESCRIÇÃO DO ITEM | E4: UNID | F4: QUANT | G4: PREÇO UNIT | I4: Valor Parcial | K4: Parcial (%) | M4: Soma | N4: (%)
A5: ESPCAR_A1S1R3 | C5: 1 | D5: Setor de Risco A1S1R3 (Contenções e Demolições) | M5: =SUM(J6:J34) -> 386572.95 | N5: =M5/$I$177 -> 0.20285395
A6: ESPCAR_A1S1R3 | C6: 01.01 | D6: SERVIÇOS PRELIMINARES | J6: =I7 -> 9766.77 | K6: =J6/$M$5 -> 0.025265011
A7: ESPCAR_A1S1R3 | C7: 01.01.001 | D7: LIMPEZA DE TERRENO | I7: =SUM(I8:I11) -> 9766.77 | K7: =I7/$M$5 -> 0.025265011
A8: ESPCAR_A1S1R3 | B8: 0003/ ORSE | C8: 01.01.001.001 | D8: Limpeza manual de terreno com vegetação rasteira, incluindo roçagem e queima | E8: m2 | F8: 356 | G8: 4.38 | I8: 1559.28 | K8: =I8/$M$5 -> 0.0040335983
A9: ESPCAR_A1S1R3 | B9: 5029/ ORSE | C9: 01.01.001.002 | D9: Destocamento de árvores de porte médio e raízes profundas, sem auxílio mecânico | E9: un | F9: 8.9 | G9: 217.25 | I9: 1933.53 | K9: =I9/$M$5 -> 0.0050017209
A10: ESPCAR_A1S1R3 | B10: 0026/ ORSE | C10: 01.01.001.003 | D10: Coleta e carga manuais de entulho | E10: m3 | F10: 106.8 | G10: 17.54 | I10: 1873.27 | K10: =I10/$M$5 -> 0.0048458383
A11: ESPCAR_A1S1R3 | B11: 97917/ SINAPI | C11: 01.01.001.004 | D11: Transporte com caminhão basculante de 6 m³, em via urbana em revestimento primário (unidade: txkm). af_07/2020 | E11: txkm | F11: 2146.68 | G11: 2.05 | I11: 4400.69 | K11: =I11/$M$5 -> 0.011383854
A12: ESPCAR_A1S1R3 | C12: 01.02 | D12: ESTRUTURAS DE CONTENÇÃO | J12: =I13+I15 -> 360679.14 | K12: =J12/$M$5 -> 0.93301702
A13: ESPCAR_A1S1R3 | C13: 01.02.001 | D13: SOLO GRAMPEADO | I13: =I14 -> 221132.96 | K13: =I13/$M$5 -> 0.57203423
A14: ESPCAR_A1S1R3 | B14: 13481/ ORSE | C14: 01.02.001.001 | D14: Solo Grampeado para controlede erosão com malha hexagonal de dupla torção, revestimento em PVC e com resistência de puncionamento de 105 KN e resistência à tração de 89 KN/m. Associada a geomanta tridimensional verde. | E14: m2 | F14: 293 | G14: 754.72 | I14: 221132.96 | K14: =I14/$M$5 -> 0.57203423
A15: ESPCAR_A1S1R3 | C15: 01.02.002 | D15: MURO DE ARRIMO | I15: =SUM(I16:I29) -> 139546.18 | K15: =I15/$M$5 -> 0.36098278
A16: ESPCAR_A1S1R3 | B16: 03672/ SINAPI | C16: 01.02.002.001 | D16: Concretagem de pilares, fck = 25 mpa, com uso de bomba - lançamento, adensamento e acabamento. af_02/2022_ps | E16: m3 | F16: 25.2 | G16: 641.26 | I16: 16159.75 | K16: =I16/$M$5 -> 0.041802589
A17: ESPCAR_A1S1R3 | B17: 02923/ SINAPI | C17: 01.02.002.002 | D17: Armação de cinta de alvenaria estrutural; diâmetro de 16,0 mm. af_09/2021 | E17: kg | F17: 630 | G17: 8.64 | I17: 5443.2 | K17: =I17/$M$5 -> 0.014080654
A18: ESPCAR_A1S1R3 | B18: 02922/ SINAPI | C18: 01.02.002.003 | D18: Armação de verga e contraverga de alvenaria estrutural; diâmetro de 16,0 mm. af_09/2021 | E18: kg | F18: 1134 | G18: 9.66 | I18: 10954.44 | K18: =I18/$M$5 -> 0.028337316
A19: ESPCAR_A1S1R3 | B19: 02921/ SINAPI | C19: 01.02.002.004 | D19: Armação vertical de alvenaria estrutural; diâmetro de 16,0 mm. af_09/2021 | E19: kg | F19: 1134 | G19: 8.84 | I19: 10024.56 | K19: =I19/$M$5 -> 0.025931871
A20: ESPCAR_A1S1R3 | B20: 93382/ SINAPI | C20: 01.02.002.005 | D20: Reaterro manual de valas, com compactador de solos de percussão. af_08/2023 | E20: m3 | F20: 50.4 | G20: 25.13 | I20: 1266.55 | K20: =I20/$M$5 -> 0.0032763544
A21: ESPCAR_A1S1R3 | B21: 89994/ SINAPI | C21: 01.02.002.006 | D21: Grauteamento de cinta intermediária ou de contraverga em alvenaria estrutural. af_09/2021 | E21: m3 | F21: 1.26 | G21: 900.01 | I21: 1134.01 | K21: =I21/$M$5 -> 0.0029334955
A22: ESPCAR_A1S1R3 | B22: 89995/ SINAPI | C22: 01.02.002.007 | D22: Grauteamento de cinta superior ou de verga em alvenaria estrutural. af_09/2021 | E22: m3 | F22: 1.26 | G22: 1002.12 | I22: 1262.67 | K22: =I22/$M$5 -> 0.0032663175
A23: ESPCAR_A1S1R3 | B23: 89993/ SINAPI | C23: 01.02.002.008 | D23: Grauteamento vertical em alvenaria estrutural. af_09/2021 | E23: m3 | F23: 31.5 | G23: 1037.21 | I23: 32672.12 | K23: =I23/$M$5 -> 0.084517347
A24: ESPCAR_A1S1R3 | B24: 9377/ ORSE | C24: 01.02.002.009 | D24: Tubo pvc rigido soldavel, serie reforçada, p/esgoto e aguas pluviais, d= 100mm | E24: m | F24: 31.5 | G24: 45.3 | I24: 1426.95 | K24: =I24/$M$5 -> 0.0036912826
A25: ESPCAR_A1S1R3 | B25: 89472/ SINAPI | C25: 01.02.002.010 | D25: Alvenaria de blocos de concreto estrutural 14x19x39 cm (espessura 14 cm), fbk = 14 mpa, utilizando colher de pedreiro. af_10/2022 | E25: m2 | F25: 63 | G25: 106.17 | I25: 6688.71 | K25: =I25/$M$5 -> 0.017302582
A26: ESPCAR_A1S1R3 | B26: 96525/ SINAPI | C26: 01.02.002.011 | D26: Escavação mecanizada para viga baldrame ou sapata corrida com mini-escavadeira (incluindo escavação para colocação de fôrmas). af_01/2024 | E26: m3 | F26: 50.4 | G26: 56.85 | I26: 2865.24 | K26: =I26/$M$5 -> 0.0074118999
A27: ESPCAR_A1S1R3 | B27: 04927/ SINAPI | C27: 01.02.002.012 | D27: Fabricação, montagem e desmontagem de fôrma para sapata corrida, em madeira serrada, e=25 mm, 4 utilizações. af_01/2024 | E27: m2 | F27: 50.4 | G27: 76.84 | I27: 3872.74 | K27: =I27/$M$5 -> 0.010018135
... A29: ESPCAR_A1S1R3 | B29: 04924/SINAPI | C29: 01.02.002.014 | D29: Concretagem de sapata corrida, fck 30 mpa, com uso de bomba - lançamento, adensamento e acabamento. af_01/2024 | E29: m3 | F29: 50.4 | G29: 734.02 | I29: 36994.61 | K29: =I29/$M$5 -> 0.09569891
A30: ESPCAR_A1S1R3 | B30: -- | C30: 01.03 | D30: DRENAGEM DAS ESTRUTURAS DE CONTENÇÃO | J30: =I31+I33 -> 16127.04 | K30: =J30/$M$5 -> 0.041717973
A31: ESPCAR_A1S1R3 | B31: -- | C31: 01.03.001 | D31: CANALETA | I31: =I32 -> 2444 | K31: =I31/$M$5 -> 0.006322222
A32: ESPCAR_A1S1R3 | B32: 02989/ SINAPI | C32: 01.03.001.001 | D32: Canaleta meia cana pré-moldada de concreto (d = 20 cm) - fornecimento e instalação. af_08/2021 | E32: m | F32: 80 | G32: 30.55 | I32: 2444 | K32: =I32/$M$5 -> 0.006322222
A33: ESPCAR_A1S1R3 | B33: -- | C33: 01.03.002 | D33: ESCADA HIDRÁULICA | I33: =I34 -> 13683.04 | K33: =I33/$M$5 -> 0.035395751
A34: ESPCAR_A1S1R3 | B34: 03925/ SINAPI | C34: 01.03.002.001 | D34: Escada hidráulica, largura até 1m, tipo descida d'água de corte ou aterro em degraus (dcd 02, 04 e dad 02), em concreto usinado, fck = 20 mpa, lançado com bomba, incluindo armação, materiais e fôrmas (3 utilizações). af_08/2022 | E34: m3 | F34: 8 | G34: 1710.38 | I34: 13683.04 | K34: =I34/$M$5 -> 0.035395751
A36: ESPCAR_A1S2R4 | B36: -- | C36: 2 | D36: Setor de Risco A1S2R4 (Contenções e Demolições) | M36: =SUM(J37:J65) -> 743321.27 | N36: =M36/$I$177 -> 0.39005743
A37: ESPCAR_A1S2R4 | B37: -- | C37: 02.01 | D37: SERVIÇOS PRELIMINARES | J37: =I38 -> 25048.97 | K37: =J37/$M$36 -> 0.033698713
A38: ESPCAR_A1S2R4 | B38: -- | C38: 02.01.001 | D38: LIMPEZA DE TERRENO | I38: =SUM(I39:I42) -> 25048.97 | K38: =I38/$M$36 -> 0.033698713
A39: ESPCAR_A1S2R4 | B39: 0003/ ORSE | C39: 02.01.001.001 | D39: Limpeza manual de terreno com vegetação rasteira, incluindo roçagem e queima | E39: m2 | F39: 913 | G39: 4.38 | I39: 3998.94 | K39: =I39/$M$36 -> 0.0053798272
A40: ESPCAR_A1S2R4 | B40: 5029/ ORSE | C40: 02.01.001.002 | D40: Destocamento de árvores de porte médio e raízes profundas, sem auxílio mecânico | E40: un | F40: 22.83 | G40: 217.25 | I40: 4958.73 | K40: =I40/$M$36 -> 0.0066710455
A41: ESPCAR_A1S2R4 | B41: 0026/ ORSE | C41: 02.01.001.003 | D41: Coleta e carga manuais de entulho | E41: m3 | F41: 273.9 | G41: 17.54 | I41: 4804.21 | K41: =I41/$M$36 -> 0.0064631677
A42: ESPCAR_A1S2R4 | B42: 97917/ SINAPI | C42: 02.01.001.004 | D42: Transporte com caminhão basculante de 6 m³, em via urbana em revestimento primário (unidade: txkm). af_07/2020 | E42: txkm | F42: 5505.9 | G42: 2.05 | I42: 11287.09 | K42: =I42/$M$36 -> 0.015184672
A43: ESPCAR_A1S2R4 | B43: -- | C43: 02.02 | D43: ESTRUTURAS DE CONTENÇÃO | J43: =I44+I46 -> 712670.02 | K43: =J43/$M$36 -> 0.95876447
A44: ESPCAR_A1S2R4 | B44: -- | C44: 02.02.001 | D44: SOLO GRAMPEADO | I44: =I45 -> 668681.92 | K44: =I44/$M$36 -> 0.89958669
A45: ESPCAR_A1S2R4 | B45: 13481/ ORSE | C45: 02.02.001.001 | D45: Solo Grampeado para controlede erosão com malha hexagonal de dupla torção, revestimento em PVC e com resistência de puncionamento de 105 KN e resistência à tração de 89 KN/m. Associada a geomanta tridimensional verde. | E45: m2 | F45: 886 | G45: 754.72 | I45: 668681.92 | K45: =I45/$M$36 -> 0.89958669
A46: ESPCAR_A1S2R4 | C46: 02.02.002 | D46: MURO DE ARRIMO | I46: =SUM(I47:I60) -> 43988.1 | K46: =I46/$M$36 -> 0.059177777
A47: ESPCAR_A1S2R4 | B47: 03672/ SINAPI | C47: 02.02.002.001 | D47: Concretagem de pilares, fck = 25 mpa, com uso de bomba - lançamento, adensamento e acabamento. af_02/2022_ps | E47: m3 | F47: 10.8 | G47: 641.26 | I47: 6925.61 | K47: =I47/$M$36 -> 0.0093171153
A48: ESPCAR_A1S2R4 | B48: 02923/ SINAPI | C48: 02.02.002.002 | D48: Armação de cinta de alvenaria estrutural; diâmetro de 16,0 mm. af_09/2021 | E48: kg | F48: 270 | G48: 8.64 | I48: 2332.8 | K48: =I48/$M$36 -> 0.0031383469
A49: ESPCAR_A1S2R4 | B49: 02922/ SINAPI | C49: 02.02.002.003 | D49: Armação de verga e contraverga de alvenaria estrutural; diâmetro de 16,0 mm. af_09/2021 | E49: kg | F49: 486 | G49: 9.66 | I49: 4694.76 | K49: =I49/$M$36 -> 0.0063159231
A50: ESPCAR_A1S2R4 | B50: 02921/ SINAPI | C50: 02.02.002.004 | D50: Armação vertical de alvenaria estrutural; diâmetro de 16,0 mm. af_09/2021 | E50: kg | F50: 486 | G50: 8.84 | I50: 4296.24 | K50: =I50/$M$36 -> 0.0057797889
A51: ESPCAR_A1S2R4 | B51: 93382/ SINAPI | C51: 02.02.002.005 | D51: Reaterro manual de valas, com compactador de solos de percussão. af_08/2023 | E51: m3 | F51: 21.6 | G51: 25.13 | I51: 542.81 | K51: =I51/$M$36 -> 0.00073024952
A52: ESPCAR_A1S2R4 | B52: 89994/ SINAPI | C52: 02.02.002.006 | D52: Grauteamento de cinta intermediária ou de contraverga em alvenaria estrutural. af_09/2021 | E52: m3 | F52: 0.54 | G52: 900.01 | I52: 486.01 | K52: =I52/$M$36 -> 0.00065383572
A53: ESPCAR_A1S2R4 | B53: 89995/ SINAPI | C53: 02.02.002.007 | D53: Grauteamento de cinta superior ou de verga em alvenaria estrutural. af_09/2021 | E53: m3 | F53: 0.54 | G53: 1002.12 | I53: 541.14 | K53: =I53/$M$36 -> 0.00072800285
A54: ESPCAR_A1S2R4 | B54: 89993/ SINAPI | C54: 02.02.002.008 | D54: Grauteamento vertical em alvenaria estrutural. af_09/2021 | E54: m3 | F54: 13.5 | G54: 1037.21 | I54: 14002.33 | K54: =I54/$M$36 -> 0.018837521
A55: ESPCAR_A1S2R4 | B55: 9377/ ORSE | C55: 02.02.002.009 | D55: Tubo pvc rigido soldavel, serie reforçada, p/esgoto e aguas pluviais, d= 100mm | E55: m | F55: 13.5 | G55: 45.3 | I55: 611.55 | K55: =I55/$M$36 -> 0.00082272636
A56: ESPCAR_A1S2R4 | B56: 89472/ SINAPI | C56: 02.02.002.010 | D56: Alvenaria de blocos de concreto estrutural 14x19x39 cm (espessura 14 cm), fbk = 14 mpa, utilizando colher de pedreiro. af_10/2022 | E56: m2 | F56: 27 | G56: 106.17 | I56: 2866.59 | K56: =I56/$M$36 -> 0.0038564617
A57: ESPCAR_A1S2R4 | B57: 96525/ SINAPI | C57: 02.02.002.011 | D57: Escavação mecanizada para viga baldrame ou sapata corrida com mini-escavadeira (incluindo escavação para colocação de fôrmas). af_01/2024 | E57: m3 | F57: 1.6 | G57: 56.85 | I57: 90.96 | K57: =I57/$M$36 -> 0.0001223697
A58: ESPCAR_A1S2R4 | B58: 04927/ SINAPI | C58: 02.02.002.012 | D58: Fabricação, montagem e desmontagem de fôrma para sapata corrida, em madeira serrada, e=25 mm, 4 utilizações. af_01/2024 | E58: m2 | F58: 21.6 | G58: 76.84 | I58: 1659.74 | K58: =I58/$M$36 -> 0.0022328703
... A60: ESPCAR_A1S2R4 | B60: 04924/ SINAPI | C60: 02.02.002.014 | D60: Concretagem de sapata corrida, fck 30 mpa, com uso de bomba - lançamento, adensamento e acabamento. af_01/2024 | E60: m3 | F60: 1.6 | G60: 734.02 | I60: 1174.43 | K60: =I60/$M$36 -> 0.0015799763
A61: ESPCAR_A1S2R4 | C61: 02.03 | D61: DRENAGEM DAS ESTRUTURAS DE CONTENÇÃO | J61: =I62+I64 -> 5602.28 | K61: =J61/$M$36 -> 0.0075368219
A62: ESPCAR_A1S2R4 | C62: 02.03.001 | D62: CANALETA | I62: =I63 -> 3207.75 | K62: =I62/$M$36 -> 0.0043154288
A63: ESPCAR_A1S2R4 | B63: 02989/ SINAPI | C63: 02.03.001.001 | D63: Canaleta meia cana pré-moldada de concreto (d = 20 cm) - fornecimento e instalação. af_08/2021 | E63: m | F63: 105 | G63: 30.55 | I63: 3207.75 | K63: =I63/$M$36 -> 0.0043154288
A64: ESPCAR_A1S2R4 | C64: 02.03.002 | D64: ESCADA HIDRÁULICA | I64: =I65 -> 2394.53 | K64: =I64/$M$36 -> 0.0032213931
A65: ESPCAR_A1S2R4 | B65: 03925/ SINAPI | C65: 02.03.002.001 | D65: Escada hidráulica, largura até 1m, tipo descida d'água de corte ou aterro em degraus (dcd 02, 04 e dad 02), em concreto usinado, fck = 20 mpa, lançado com bomba, incluindo armação, materiais e fôrmas (3 utilizações). af_08/2022 | E65: m3 | F65: 1.4 | G65: 1710.38 | I65: 2394.53 | K65: =I65/$M$36 -> 0.0032213931
A67: ESPCAR_A4S1R3 | B67: -- | C67: 3 | D67: Setor de Risco A4S1R3 (Contenções e Demolições) | M67: =SUM(J68:J85) -> 357741.8 | N67: =M67/$I$177 -> 0.18772482
A68: ESPCAR_A4S1R3 | C68: 03.01 | D68: SERVIÇOS PRELIMINARES | J68: =I69 -> 20384.02 | K68: =J68/$M$67 -> 0.056979699
A69: ESPCAR_A4S1R3 | C69: 03.01.001 | D69: LIMPEZA DE TERRENO | I69: =SUM(I70:I73) -> 20384.02 | K69: =I69/$M$67 -> 0.056979699
A70: ESPCAR_A4S1R3 | B70: 0003/ ORSE | C70: 03.01.001.001 | D70: Limpeza manual de terreno com vegetação rasteira, incluindo roçagem e queima | E70: m2 | F70: 743 | G70: 4.38 | I70: 3254.34 | K70: =I70/$M$67 -> 0.0090968961
A71: ESPCAR_A4S1R3 | B71: 5029/ ORSE | C71: 03.01.001.002 | D71: Destocamento de árvores de porte médio e raízes profundas, sem auxílio mecânico | E71: un | F71: 18.58 | G71: 217.25 | I71: 4035.42 | K71: =I71/$M$67 -> 0.011280259
A72: ESPCAR_A4S1R3 | B72: 0026/ ORSE | C72: 03.01.001.003 | D72: Coleta e carga manuais de entulho | E72: m3 | F72: 222.9 | G72: 17.54 | I72: 3909.67 | K72: =I72/$M$67 -> 0.010928748
A73: ESPCAR_A4S1R3 | B73: 97917/ SINAPI | C73: 03.01.001.004 | D73: Transporte com caminhão basculante de 6 m³, em via urbana em revestimento primário (unidade: txkm). af_07/2020 | E73: txkm | F73: 4480.29 | G73: 2.05 | I73: 9184.59 | K73: =I73/$M$67 -> 0.025673796
A74: ESPCAR_A4S1R3 | C74: 03.02 | D74: ESTRUTURAS DE CONTENÇÃO | J74: =I75+I77 -> 328804.83 | K74: =J74/$M$67 -> 0.91911214
A75: ESPCAR_A4S1R3 | C75: 03.02.001 | D75: SOLO GRAMPEADO | I75: =I76 -> 270944.48 | K75: =I75/$M$67 -> 0.7573744
A76: ESPCAR_A4S1R3 | B76: 13481/ ORSE | C76: 03.02.001.001 | D76: Solo Grampeado para controlede erosão com malha hexagonal de dupla torção, revestimento em PVC e com resistência de puncionamento de 105 KN e resistência à tração de 89 KN/m. Associada a geomanta tridimensional verde. | E76: m2 | F76: 359 | G76: 754.72 | I76: 270944.48 | K76: =I76/$M$67 -> 0.7573744
A77: ESPCAR_A4S1R3 | C77: 03.02.002 | D77: RETALUDAMENTO / RECONSTRUÇÃO EM CORTE/ATERRO | I77: =SUM(I78:I80) -> 57860.35 | K77: =I77/$M$67 -> 0.16173774
A78: ESPCAR_A4S1R3 | B78: 2498/ ORSE | C78: 03.02.002.001 | D78: Escavação manual de vala ou cava em material de 1ª categoria, profundidade entre 1,50 e 3,00m | E78: m3 | F78: 691.2 | G78: 78.85 | I78: 54501.12 | K78: =I78/$M$67 -> 0.15234764
A79: ESPCAR_A4S1R3 | B79: 2509/ ORSE | C79: 03.02.002.002 | D79: Carga manual de material de 1ª categoria | E79: m3 | F79: 115.2 | G79: 10.49 | I79: 1208.45 | K79: =I79/$M$67 -> 0.003377995
A80: ESPCAR_A4S1R3 | B80: 11448/ ORSE | C80: 03.02.002.003 | D80: Compactação manual com compactador a percussão sapinho, a 95% do pn | E80: m3 | F80: 115.2 | G80: 18.67 | I80: 2150.78 | K80: =I80/$M$67 -> 0.0060121015
A81: ESPCAR_A4S1R3 | C81: 03.03 | D81: DRENAGEM DAS ESTRUTURAS DE CONTENÇÃO | J81: =I82+I84 -> 8552.95 | K81: =J81/$M$67 -> 0.023908165
A82: ESPCAR_A4S1R3 | C82: 03.03.001 | D82: CANALETA | I82: =I83 -> 4277 | K82: =I82/$M$67 -> 0.01195555
A83: ESPCAR_A4S1R3 | B83: 02989/ SINAPI | C83: 03.03.001.001 | D83: Canaleta meia cana pré-moldada de concreto (d = 20 cm) - fornecimento e instalação. af_08/2021 | E83: m | F83: 140 | G83: 30.55 | I83: 4277 | K83: =I83/$M$67 -> 0.01195555
A84: ESPCAR_A4S1R3 | C84: 03.03.002 | D84: ESCADA HIDRÁULICA | I84: =I85 -> 4275.95 | K84: =I84/$M$67 -> 0.011952615
A85: ESPCAR_A4S1R3 | B85: 03925/ SINAPI | C85: 03.03.002.001 | D85: Escada hidráulica, largura até 1m, tipo descida d'água de corte ou aterro em degraus (dcd 02, 04 e dad 02), em concreto usinado, fck = 20 mpa, lançado com bomba, incluindo armação, materiais e fôrmas (3 utilizações). af_08/2022 | E85: m3 | F85: 2.5 | G85: 1710.38 | I85: 4275.95 | K85: =I85/$M$67 -> 0.011952615
A87: ESPCAR_A4S2R4 | C87: 4 | D87: Setor de Risco A4S2R4 (Contenções e Demolições) | M87: =SUM(J88:J123) -> 171290.91 | N87: =M87/$I$177 -> 0.089884812
A88: ESPCAR_A4S2R4 | C88: 04.01 | D88: SERVIÇOS PRELIMINARES | J88: =I89 -> 1646.09 | K88: =J88/$M$87 -> 0.0096099087
A89: ESPCAR_A4S2R4 | C89: 04.01.001 | D89: LIMPEZA DE TERRENO | I89: =SUM(I90:I93) -> 1646.09 | K89: =I89/$M$87 -> 0.0096099087
A90: ESPCAR_A4S2R4 | B90: 0003/ ORSE | C90: 04.01.001.001 | D90: Limpeza manual de terreno com vegetação rasteira, incluindo roçagem e queima | E90: m2 | F90: 60 | G90: 4.38 | I90: 262.8 | K90: =I90/$M$87 -> 0.001534232
A91: ESPCAR_A4S2R4 | B91: 5029/ ORSE | C91: 04.01.001.002 | D91: Destocamento de árvores de porte médio e raízes profundas, sem auxílio mecânico | E91: un | F91: 1.5 | G91: 217.25 | I91: 325.88 | K91: =I91/$M$87 -> 0.0019024944
A92: ESPCAR_A4S2R4 | B92: 0026/ ORSE | C92: 04.01.001.003 | D92: Coleta e carga manuais de entulho | E92: m3 | F92: 18 | G92: 17.54 | I92: 315.72 | K92: =I92/$M$87 -> 0.0018431801
A93: ESPCAR_A4S2R4 | B93: 97917/ SINAPI | C93: 04.01.001.004 | D93: Transporte com caminhão basculante de 6 m³, em via urbana em revestimento primário (unidade: txkm). af_07/2020 | E93: txkm | F93: 361.8 | G93: 2.05 | I93: 741.69 | K93: =I93/$M$87 -> 0.0043300021
A94: ESPCAR_A4S2R4 | C94: 04.02 | D94: ESTRUTURAS DE CONTENÇÃO | J94: =I95+I99 -> 167665.52 | K94: =J94/$M$87 -> 0.9788349
A95: ESPCAR_A4S2R4 | C95: 04.02.001 | D95: RETALUDAMENTO / RECONSTRUÇÃO EM CORTE/ATERRO | I95: =SUM(I96:I98) -> 904.07 | K95: =I95/$M$87 -> 0.00527798
A96: ESPCAR_A4S2R4 | C96: 04.02.001.001 | D96: Escavação manual de vala ou cava em material de 1ª categoria, profundidade entre 1,50 e 3,00m | E96: m3 | F96: 10.8 | G96: 78.85 | I96: 851.58 | K96: =I96/$M$87 -> 0.0049715423
A97: ESPCAR_A4S2R4 | C97: 04.02.001.002 | D97: Carga manual de material de 1ª categoria | E97: m3 | F97: 1.8 | G97: 10.49 | I97: 18.88 | K97: =I97/$M$87 -> 0.00011022184
A98: ESPCAR_A4S2R4 | C98: 04.02.001.003 | D98: Compactação manual com compactador a percussão sapinho, a 95% do pn | E98: m3 | F98: 1.8 | G98: 18.67 | I98: 33.61 | K98: =I98/$M$87 -> 0.0001962159
A99: ESPCAR_A4S2R4 | C99: 04.02.002 | D99: CORTINA ATIRANTADA | I99: =I100+I106 -> 166761.45 | K99: =I99/$M$87 -> 0.97355692
A100: ESPCAR_A4S2R4 | C100: 04.02.002.001 | D100: FUNDAÇÃO - ESTACAS | I100: =SUM(I101:I105) -> 76913.21 | K100: =I100/$M$87 -> 0.44902097
A101: ESPCAR_A4S2R4 | C101: 04.02.002.001.001 | D101: Perfuratriz com torre metálica para execução de estaca hélice contínua, profundidade máxima de 30 m, diâmetro máximo de 800 mm, potência instalada de 268 hp, mesa rotativa com torque máximo de 170 knm - depreciação. af_06/2015 | E101: h | F101: 91.8 | G101: 238.49 | I101: 21893.38 | K101: =I101/$M$87 -> 0.12781402
A102: ESPCAR_A4S2R4 | C102: 04.02.002.001.002 | D102: Execução de estaca hélice contínua monitorada Ø 500mm, concreto fck=40Mpa, inclusive aço, bombeamento; exclusive mobilização e desmobilização de equipamento e bate-estacas | E102: m | F102: 162 | G102: 337.82 | I102: 54726.84 | K102: =I102/$M$87 -> 0.31949646
A103: ESPCAR_A4S2R4 | C103: 04.02.002.001.003 | D103: Transporte horizontal com carrinho de mão, de sacos de 50 kg (unidade: kgxkm). af_07/2019 | E103: kgxkm | F103: 310.5 | G103: 0.76 | I103: 235.98 | K103: =I103/$M$87 -> 0.0013776563
A104: ESPCAR_A4S2R4 | C104: 04.02.002.001.004 | D104: Carga manual de material de 1ª categoria | E104: m3 | F104: 5.4 | G104: 10.49 | I104: 56.65 | K104: =I104/$M$87 -> 0.00033072391
A105: ESPCAR_A4S2R4 | C105: 04.02.002.001.005 | D105: Transporte com caminhão basculante de 14 m³, em via urbana pavimentada, adicional para dmt excedente a 30 km (unidade: m3xkm). af_07/2020 | E105: m3xkm | F105: 0.43 | G105: 0.83 | I105: 0.36 | K105: =I105/$M$87 -> 2.1016877e-06
A106: ESPCAR_A4S2R4 | C106: 04.02.002.002 | D106: ESTRUTURA - CORTINA | I106: =SUM(I107:I118) -> 89848.24 | K106: =I106/$M$87 -> 0.52453595
...

Sheet 02_Esperança
A1: PMRR DE ILHÉUS
A3: Empreendimento: 000055 - Alto da Esperança (Bairro Esperança) | G3: VALOR TOTAL
A4: ITEM | B4: DESCRIÇÃO DO ITEM | C4: UNID | D4: QUANT | E4: PREÇO UNIT | G4: Valor Parcial | I4: Parcial (%) | K4: Soma | L4: (%)
A5: 1 | B5: Setor de Risco A1S2R4 (Contenções e Demolições) | K5: =SUM(H5:H34) -> 99348.32 | L5: =K5/$G$211 -> 0.017856259
A6: 01.01 | B6: SERVIÇOS PRELIMINARES | H6: =G7 -> 2167.35 | I6: =H6/$K$5 -> 0.021815668
A7: 01.01.001 | B7: LIMPEZA DE TERRENO | G7: =SUM(G8:G11) -> 2167.35 | I7: =G7/$K$5 -> 0.021815668
A8: 01.01.001.001 | B8: Limpeza manual de terreno com vegetação rasteira, incluindo roçagem e queima | C8: m2 | D8: 79 | E8: 4.38 | G8: 346.02 | I8: =G8/$K$5 -> 0.0034828973
A9: 01.01.001.002 | B9: Destocamento de árvores de porte médio e raízes profundas, sem auxílio mecânico | C9: un | D9: 1.98 | E9: 217.25 | G9: 429.07 | I9: =G9/$K$5 -> 0.004318845
A10: 01.01.001.003 | B10: Coleta e carga manuais de entulho | C10: m3 | D10: 23.7 | E10: 17.54 | G10: 415.7 | I10: =G10/$K$5 -> 0.004184268
A11: 01.01.001.004 | B11: Transporte com caminhão basculante de 6 m³, em via urbana em revestimento primário (unidade: txkm). af_07/2020 | C11: txkm | D11: 476.37 | E11: 2.05 | G11: 976.56 | I11: =G11/$K$5 -> 0.0098296579
A12: 01.02 | B12: ESTRUTURAS DE CONTENÇÃO | H12: =G13+G15 -> 94670.05 | I12: =H12/$K$5 -> 0.95291043
A13: 01.02.001 | B13: SOLO GRAMPEADO | G13: =G14 -> 41509.6 | I13: =G13/$K$5 -> 0.41781884
A14: 01.02.001.001 | B14: Solo Grampeado para controlede erosão com malha hexagonal de dupla torção, revestimento em PVC e com resistência de puncionamento de 105 KN e resistência à tração de 89 KN/m. Associada a geomanta tridimensional verde. | C14: m2 | D14: 55 | E14: 754.72 | G14: 41509.6 | I14: =G14/$K$5 -> 0.41781884
A15: 01.02.002 | B15: MURO DE ARRIMO | G15: =SUM(G16:G29) -> 53160.45 | I15: =G15/$K$5 -> 0.53509158
A16: 01.02.002.001 | B16: Concretagem de pilares, fck = 25 mpa, com uso de bomba - lançamento, adensamento e acabamento. af_02/2022_ps | C16: m3 | D16: 9.6 | E16: 641.26 | G16: 6156.1 | I16: =G16/$K$5 -> 0.061964812
A17: 01.02.002.002 | B17: Armação de cinta de alvenaria estrutural; diâmetro de 16,0 mm. af_09/2021 | C17: kg | D17: 240 | E17: 8.64 | G17: 2073.6 | I17: =G17/$K$5 -> 0.020872019
A18: 01.02.002.003 | B18: Armação de verga e contraverga de alvenaria estrutural; diâmetro de 16,0 mm. af_09/2021 | C18: kg | D18: 432 | E18: 9.66 | G18: 4173.12 | I18: =G18/$K$5 -> 0.042004938
A19: 01.02.002.004 | B19: Armação vertical de alvenaria estrutural; diâmetro de 16,0 mm. af_09/2021 | C19: kg | D19: 432 | E19: 8.84 | G19: 3818.88 | I19: =G19/$K$5 -> 0.038439301
A20: 01.02.002.005 | B20: Reaterro manual de valas, com compactador de solos de percussão. af_08/2023 | C20: m3 | D20: 19.2 | E20: 25.13 | G20: 482.5 | I20: =G20/$K$5 -> 0.0048566498
A21: 01.02.002.006 | B21: Grauteamento de cinta intermediária ou de contraverga em alvenaria estrutural. af_09/2021 | C21: m3 | D21: 0.48 | E21: 900.01 | G21: 432 | I21: =G21/$K$5 -> 0.0043483372
A22: 01.02.002.007 | B22: Grauteamento de cinta superior ou de verga em alvenaria estrutural. af_09/2021 | C22: m3 | D22: 0.48 | E22: 1002.12 | G22: 481.02 | I22: =G22/$K$5 -> 0.0048417527
A23: 01.02.002.008 | B23: Grauteamento vertical em alvenaria estrutural. af_09/2021 | C23: m3 | D23: 12 | E23: 1037.21 | G23: 12446.52 | I23: =G23/$K$5 -> 0.12528164
A24: 01.02.002.009 | B24: Tubo pvc rigido soldavel, serie reforçada, p/esgoto e aguas pluviais, d= 100mm | C24: m | D24: 12 | E24: 45.3 | G24: 543.6 | I24: =G24/$K$5 -> 0.0054716577
A25: 01.02.002.010 | B25: Alvenaria de blocos de concreto estrutural 14x19x39 cm (espessura 14 cm), fbk = 14 mpa, utilizando colher de pedreiro. af_10/2022 | C25: m2 | D25: 24 | E25: 106.17 | G25: 2548.08 | I25: =G25/$K$5 -> 0.025647943
A26: 01.02.002.011 | B26: Escavação mecanizada para viga baldrame ou sapata corrida com mini-escavadeira (incluindo escavação para colocação de fôrmas). af_01/2024 | C26: m3 | D26: 19.2 | E26: 56.85 | G26: 1091.52 | I26: =G26/$K$5 -> 0.010986799
A27: 01.02.002.012 | B27: Fabricação, montagem e desmontagem de fôrma para sapata corrida, em madeira serrada, e=25 mm, 4 utilizações. af_01/2024 | C27: m2 | D27: 19.2 | E27: 76.84 | G27: 1475.33 | I27: =G27/$K$5 -> 0.014850075
... A29: 01.02.002.014 | B29: Concretagem de sapata corrida, fck 30 mpa, com uso de bomba - lançamento, adensamento e acabamento. af_01/2024 | C29: m3 | D29: 19.2 | E29: 734.02 | G29: 14093.18 | I29: =G29/$K$5 -> 0.14185625
A30: 01.03 | B30: DRENAGEM DAS ESTRUTURAS DE CONTENÇÃO | H30: =G31+G33 -> 2510.92 | I30: =H30/$K$5 -> 0.025273905
A31: 01.03.001 | B31: CANALETA | G31: =G32 -> 1313.65 | I31: =G31/$K$5 -> 0.013222669
A32: 01.03.001.001 | B32: Canaleta meia cana pré-moldada de concreto (d = 20 cm) - fornecimento e instalação. af_08/2021 | C32: m | D32: 43 | E32: 30.55 | G32: 1313.65 | I32: =G32/$K$5 -> 0.013222669
A33: 01.03.002 | B33: ESCADA HIDRÁULICA | G33: =G34 -> 1197.27 | I33: =G33/$K$5 -> 0.012051235
A34: 01.03.002.001 | B34: Escada hidráulica, largura até 1m, tipo descida d'água de corte ou aterro em degraus (dcd 02, 04 e dad 02), em concreto usinado, fck = 20 mpa, lançado com bomba, incluindo armação, materiais e fôrmas (3 utilizações). af_08/2022 | C34: m3 | D34: 0.7 | E34: 1710.38 | G34: 1197.27 | I34: =G34/$K$5 -> 0.012051235
A36: 2 | B36: Setor de Risco A1S3R3 (Contenções e Demolições) | K36: =SUM(H36:H72) -> 1422949.4 | L36: =K36/$G$211 -> 0.25575221
A37: 02.01 | B37: SERVIÇOS PRELIMINARES | H37: =G38+G43 -> 47382.07 | I37: =H37/$K$36 -> 0.033298492
A38: 02.01.001 | B38: LIMPEZA DE TERRENO | G38: =SUM(G39:G42) -> 43127.42 | I38: =G38/$K$36 -> 0.03030847
A39: 02.01.001.001 | B39: Limpeza manual de terreno com vegetação rasteira, incluindo roçagem e queima | C39: m2 | D39: 1572 | E39: 4.38 | G39: 6885.36 | I39: =G39/$K$36 -> 0.0048387947
A40: 02.01.001.002 | B40: Destocamento de árvores de porte médio e raízes profundas, sem auxílio mecânico | C40: un | D40: 39.3 | E40: 217.25 | G40: 8537.92 | I40: =G40/$K$36 -> 0.0060001571
A41: 02.01.001.003 | B41: Coleta e carga manuais de entulho | C41: m3 | D41: 471.6 | E41: 17.54 | G41: 8271.86 | I41: =G41/$K$36 -> 0.0058131793
A42: 02.01.001.004 | B42: Transporte com caminhão basculante de 6 m³, em via urbana em revestimento primário (unidade: txkm). af_07/2020 | C42: txkm | D42: 9479.16 | E42: 2.05 | G42: 19432.28 | I42: =G42/$K$36 -> 0.013656339
A43: 02.01.002 | B43: DEMOLIÇÃO DE EDIFICAÇÕES | G43: =SUM(G44:G49) -> 4254.65 | I43: =G43/$K$36 -> 0.002990022
A44: 02.01.002.001 | B44: Demolição de alvenaria de bloco furado, de forma manual, sem reaproveitamento. af_09/2023 | C44: m3 | D44: 26.4 | E44: 54.08 | G44: 1427.71 | I44: =G44/$K$36 -> 0.0010033456
A45: 02.01.002.002 | B45: Demolição de lajes, em concreto armado, de forma mecanizada com martelete, sem reaproveitamento. af_09/2023 | C45: m3 | D45: 6.6 | E45: 78.37 | G45: 517.24 | I45: =G45/$K$36 -> 0.00036349852
A46: 02.01.002.003 | B46: Demolição de pilares e vigas em concreto armado, de forma mecanizada com martelete, sem reaproveitamento. af_09/2023 | C46: m3 | D46: 2.31 | E46: 168.28 | G46: 388.73 | I46: =G46/$K$36 -> 0.0002731861
A47: 02.01.002.004 | B47: Demolição de revestimento cerâmico, de forma mecanizada com martelete, sem reaproveitamento. af_09/2023 | C47: m2 | D47: 35.2 | E47: 6.36 | G47: 223.87 | I47: =G47/$K$36 -> 0.00015732815
A48: 02.01.002.005 | B48: Coleta e carga manuais de entulho | C48: m3 | D48: 35.2 | E48: 17.54 | G48: 617.41 | I48: =G48/$K$36 -> 0.00043389455
A49: 02.01.002.006 | B49: Transporte com caminhão basculante de 6 m³, em via urbana em revestimento primário (unidade: txkm). af_07/2020 | C49: txkm | D49: 526.68 | E49: 2.05 | G49: 1079.69 | I49: =G49/$K$36 -> 0.00075876907
A50: 02.02 | B50: ESTRUTURAS DE CONTENÇÃO | H50: =G51+G53 -> 1361655.7 | I50: =H50/$K$36 -> 0.95692486
A51: 02.02.001 | B51: SOLO GRAMPEADO | G51: =G52 -> 1095853.4 | I51: =G51/$K$36 -> 0.77012818
A52: 02.02.001.001 | B52: Solo Grampeado para controlede erosão com malha hexagonal de dupla torção, revestimento em PVC e com resistência de puncionamento de 105 KN e resistência à tração de 89 KN/m. Associada a geomanta tridimensional verde. | C52: m2 | D52: 1452 | E52: 754.72 | G52: 1095853.4 | I52: =G52/$K$36 -> 0.77012818
A53: 02.02.002 | B53: MURO DE ARRIMO | G53: =SUM(G54:G67) -> 265802.23 | I53: =G53/$K$36 -> 0.18679668
A54: 02.02.002.001 | B54: Concretagem de pilares, fck = 25 mpa, com uso de bomba - lançamento, adensamento e acabamento. af_02/2022_ps | C54: m3 | D54: 48 | E54: 641.26 | G54: 30780.48 | I54: =G54/$K$36 -> 0.021631465
A55: 02.02.002.002 | B55: Armação de cinta de alvenaria estrutural; diâmetro de 16,0 mm. af_09/2021 | C55: kg | D55: 1200 | E55: 8.64 | G55: 10368 | I55: =G55/$K$36 -> 0.0072862745
A56: 02.02.002.003 | B56: Armação de verga e contraverga de alvenaria estrutural; diâmetro de 16,0 mm. af_09/2021 | C56: kg | D56: 2160 | E56: 9.66 | G56: 20865.6 | I56: =G56/$K$36 -> 0.014663627
A57: 02.02.002.004 | B57: Armação vertical de alvenaria estrutural; diâmetro de 16,0 mm. af_09/2021 | C57: kg | D57: 2160 | E57: 8.84 | G57: 19094.4 | I57: =G57/$K$36 -> 0.013418889
A58: 02.02.002.005 | B58: Reaterro manual de valas, com compactador de solos de percussão. af_08/2023 | C58: m3 | D58: 96 | E58: 25.13 | G58: 2412.48 | I58: =G58/$K$36 -> 0.0016954081
A59: 02.02.002.006 | B59: Grauteamento de cinta intermediária ou de contraverga em alvenaria estrutural. af_09/2021 | C59: m3 | D59: 2.4 | E59: 900.01 | G59: 2160.02 | I59: =G59/$K$36 -> 0.0015179879
A60: 02.02.002.007 | B60: Grauteamento de cinta superior ou de verga em alvenaria estrutural. af_09/2021 | C60: m3 | D60: 2.4 | E60: 1002.12 | G60: 2405.09 | I60: =G60/$K$36 -> 0.0016902147
A61: 02.02.002.008 | B61: Grauteamento vertical em alvenaria estrutural. af_09/2021 | C61: m3 | D61: 60 | E61: 1037.21 | G61: 62232.6 | I61: =G61/$K$36 -> 0.043734935
A62: 02.02.002.009 | B62: Tubo pvc rigido soldavel, serie reforçada, p/esgoto e aguas pluviais, d= 100mm | C62: m | D62: 60 | E62: 45.3 | G62: 2718 | I62: =G62/$K$36 -> 0.0019101171
A63: 02.02.002.010 | B63: Alvenaria de blocos de concreto estrutural 14x19x39 cm (espessura 14 cm), fbk = 14 mpa, utilizando colher de pedreiro. af_10/2022 | C63: m2 | D63: 120 | E63: 106.17 | G63: 12740.4 | I63: =G63/$K$36 -> 0.0089535158
A64: 02.02.002.011 | B64: Escavação mecanizada para viga baldrame ou sapata corrida com mini-escavadeira (incluindo escavação para colocação de fôrmas). af_01/2024 | C64: m3 | D64: 96 | E64: 56.85 | G64: 5457.6 | I64: =G64/$K$36 -> 0.0038354139
A65: 02.02.002.012 | B65: Fabricação, montagem e desmontagem de fôrma para sapata corrida, em madeira serrada, e=25 mm, 4 utilizações. af_01/2024 | C65: m2 | D65: 96 | E65: 76.84 | G65: 7376.64 | I65: =G65/$K$36 -> 0.0051840494
... A67: 02.02.002.014 | B67: Concretagem de sapata corrida, fck 30 mpa, com uso de bomba - lançamento, adensamento e acabamento. af_01/2024 | C67: m3 | D67: 96 | E67: 734.02 | G67: 70465.92 | I67: =G67/$K$36 -> 0.04952103
A68: 02.03 | B68: DRENAGEM DAS ESTRUTURAS DE CONTENÇÃO | H68: =G69+G71 -> 13911.67 | I68: =H68/$K$36 -> 0.0097766441
A69: 02.03.001 | B69: CANALETA | G69: =G70 -> 10661.95 | I69: =G69/$K$36 -> 0.0074928525
A70: 02.03.001.001 | B70: Canaleta meia cana pré-moldada de concreto (d = 20 cm) - fornecimento e instalação. af_08/2021 | C70: m | D70: 349 | E70: 30.55 | G70: 10661.95 | I70: =G70/$K$36 -> 0.0074928525
A71: 02.03.002 | B71: ESCADA HIDRÁULICA | G71: =G72 -> 3249.72 | I71: =G71/$K$36 -> 0.0022837917
A72: 02.03.002.001 | B72: Escada hidráulica, largura até 1m, tipo descida d'água de corte ou aterro em degraus (dcd 02, 04 e dad 02), em concreto usinado, fck = 20 mpa, lançado com bomba, incluindo armação, materiais e fôrmas (3 utilizações). af_08/2022 | C72: m3 | D72: 1.9 | E72: 1710.38 | G72: 3249.72 | I72: =G72/$K$36 -> 0.0022837917
A74: 3 | B74: Setor de Risco A2S1R3 (Contenções e Demolições) | K74: =SUM(H74:H130) -> 2394136.9 | L74: =K74/$G$211 -> 0.43030751
A75: 03.01 | B75: SERVIÇOS PRELIMINARES | H75: =G76+G81 -> 62894.42 | I75: =H75/$K$74 -> 0.026270185
A76: 03.01.001 | B76: LIMPEZA DE TERRENO | G76: =SUM(G77:G80) -> 58929.85 | I76: =G76/$K$74 -> 0.024614236
A77: 03.01.001.001 | B77: Limpeza manual de terreno com vegetação rasteira, incluindo roçagem e queima | C77: m2 | D77: 2148 | E77: 4.38 | G77: 9408.24 | I77: =G77/$K$74 -> 0.0039297001
A78: 03.01.001.002 | B78: Destocamento de árvores de porte médio e raízes profundas, sem auxílio mecânico | C78: un | D78: 53.7 | E78: 217.25 | G78: 11666.33 | I78: =G78/$K$74 -> 0.0048728751
A79: 03.01.001.003 | B79: Coleta e carga manuais de entulho | C79: m3 | D79: 644.4 | E79: 17.54 | G79: 11302.78 | I79: =G79/$K$74 -> 0.0047210249
A80: 03.01.001.004 | B80: Transporte com caminhão basculante de 6 m³, em via urbana em revestimento primário (unidade: txkm). af_07/2020 | C80: txkm | D80: 12952.44 | E80: 2.05 | G80: 26552.5 | I80: =G80/$K$74 -> 0.011090636
A81: 03.01.002 | B81: DEMOLIÇÃO DE EDIFICAÇÕES | G81: =SUM(G82:G87) -> 3964.57 | I81: =G81/$K$74 -> 0.0016559496
A82: 03.01.002.001 | B82: Demolição de alvenaria de bloco furado, de forma manual, sem reaproveitamento. af_09/2023 | C82: m3 | D82: 24.6 | E82: 54.08 | G82: 1330.37 | I82: =G82/$K$74 -> 0.00055567833
A83: 03.01.002.002 | B83: Demolição de lajes, em concreto armado, de forma mecanizada com martelete, sem reaproveitamento. af_09/2023 | C83: m3 | D83: 6.15 | E83: 78.37 | G83: 481.98 | I83: =G83/$K$74 -> 0.00020131681
A84: 03.01.002.003 | B84: Demolição de pilares e vigas em concreto armado, de forma mecanizada com martelete, sem reaproveitamento. af_09/2023 | C84: m3 | D84: 2.15 | E84: 168.28 | G84: 362.22 | I84: =G84/$K$74 -> 0.00015129461
A85: 03.01.002.004 | B85: Demolição de revestimento cerâmico, de forma mecanizada com martelete, sem reaproveitamento. af_09/2023 | C85: m2 | D85: 32.8 | E85: 6.36 | G85: 208.61 | I85: =G85/$K$74 -> 8.7133697e-05
A86: 03.01.002.005 | B86: Coleta e carga manuais de entulho | C86: m3 | D86: 32.8 | E86: 17.54 | G86: 575.31 | I86: =G86/$K$74 -> 0.00024029954
A87: 03.01.002.006 | B87: Transporte com caminhão basculante de 6 m³, em via urbana em revestimento primário (unidade: txkm). af_07/2020 | C87: txkm | D87: 490.77 | E87: 2.05 | G87: 1006.08 | I87: =G87/$K$74 -> 0.0004202266
A88: 03.02 | B88: ESTRUTURAS DE CONTENÇÃO | H88: =G89+G106+G91 -> 2313470.1 | I88: =H88/$K$74 -> 0.96630652
A89: 03.02.001 | B89: SOLO GRAMPEADO | G89: =G90 -> 1284533.4 | I89: =G89/$K$74 -> 0.53653299
A90: 03.02.001.001 | B90: Solo Grampeado para controlede erosão com malha hexagonal de dupla torção, revestimento em PVC e com resistência de puncionamento de 105 KN e resistência à tração de 89 KN/m. Associada a geomanta tridimensional verde. | C90: m2 | D90: 1702 | E90: 754.72 | G90: 1284533.4 | I90: =G90/$K$74 -> 0.53653299
A91: 03.02.002 | B91: MURO DE ARRIMO | G91: =SUM(G92:G105) -> 883792.43 | I91: =G91/$K$74 -> 0.36914866
A92: 03.02.002.001 | B92: Concretagem de pilares, fck = 25 mpa, com uso de bomba - lançamento, adensamento e acabamento. af_02/2022_ps | C92: m3 | D92: 159.6 | E92: 641.26 | G92: 102345.1 | I92: =G92/$K$74 -> 0.042748224
A93: 03.02.002.002 | B93: Armação de cinta de alvenaria estrutural; diâmetro de 16,0 mm. af_09/2021 | C93: kg | D93: 3990 | E93: 8.64 | G93: 34473.6 | I93: =G93/$K$74 -> 0.014399177
A94: 03.02.002.003 | B94: Armação de verga e contraverga de alvenaria estrutural; diâmetro de 16,0 mm. af_09/2021 | C94: kg | D94: 7182 | E94: 9.66 | G94: 69378.12 | I94: =G94/$K$74 -> 0.028978343
A95: 03.02.002.004 | B95: Armação vertical de alvenaria estrutural; diâmetro de 16,0 mm. af_09/2021 | C95: kg | D95: 7182 | E95: 8.84 | G95: 63488.88 | I95: =G95/$K$74 -> 0.026518484
A96: 03.02.002.005 | B96: Reaterro manual de valas, com compactador de solos de percussão. af_08/2023 | C96: m3 | D96: 319.2 | E96: 25.13 | G96: 8021.5 | I96: =G96/$K$74 -> 0.0033504767
A97: 03.02.002.006 | B97: Grauteamento de cinta intermediária ou de contraverga em alvenaria estrutural. af_09/2021 | C97: m3 | D97: 7.98 | E97: 900.01 | G97: 7182.08 | I97: =G97/$K$74 -> 0.0029998619
A98: 03.02.002.007 | B98: Grauteamento de cinta superior ou de verga em alvenaria estrutural. af_09/2021 | C98: m3 | D98: 7.98 | E98: 1002.12 | G98: 7996.92 | I98: =G98/$K$74 -> 0.00334021
A99: 03.02.002.008 | B99: Grauteamento vertical em alvenaria estrutural. af_09/2021 | C99: m3 | D99: 199.5 | E99: 1037.21 | G99: 206923.39 | I99: =G99/$K$74 -> 0.086429222
A100: 03.02.002.009 | B100: Tubo pvc rigido soldavel, serie reforçada, p/esgoto e aguas pluviais, d= 100mm | C100: m | D100: 199.5 | E100: 45.3 | G100: 9037.35 | I100: =G100/$K$74 -> 0.0037747841
A101: 03.02.002.010 | B101: Alvenaria de blocos de concreto estrutural 14x19x39 cm (espessura 14 cm), fbk = 14 mpa, utilizando colher de pedreiro. af_10/2022 | C101: m2 | D101: 399 | E101: 106.17 | G101: 42361.83 | I101: =G101/$K$74 -> 0.017693988
A102: 03.02.002.011 | B102: Escavação mecanizada para viga baldrame ou sapata corrida com mini-escavadeira (incluindo escavação para colocação de fôrmas). af_01/2024 | C102: m3 | D102: 319.2 | E102: 56.85 | G102: 18146.52 | I102: =G102/$K$74 -> 0.0075795666
A103: 03.02.002.012 | B103: Fabricação, montagem e desmontagem de fôrma para sapata corrida, em madeira serrada, e=25 mm, 4 utilizações. af_01/2024 | C103: m2 | D103: 319.2 | E103: 76.84 | G103: 24527.33 | I103: =G103/$K$74 -> 0.010244748
... A105: 03.02.002.014 | B105: Concretagem de sapata corrida, fck 30 mpa, com uso de bomba - lançamento, adensamento e acabamento. af_01/2024 | C105: m3 | D105: 319.2 | E105: 734.02 | G105: 234299.18 | I105: =G105/$K$74 -> 0.097863735
A106: 03.02.003 | B106: CORTINA ATIRANTADA | G106: =G107+G113 -> 145144.22 | I106: =G106/$K$74 -> 0.060624862
...

Sheet 03_Aureliano
A1: PMRR DE ILHÉUS
A3: Empreendimento: 000071 - Alto Aureliano (Bairro Esperança) | G3: VALOR TOTAL
A4: ITEM | B4: DESCRIÇÃO DO ITEM | C4: UNID | D4: QUANT | E4: PREÇO UNIT | G4: Valor Parcial | I4: Parcial (%) | K4: Soma | L4: (%)
A5: 1 | B5: Setor de Risco A1S1R4 (Contenções e Demolições) | K5: =SUM(H5:H61) -> 3705680.7 | L5: =K5/$G$149 -> 0.70833438
A6: 01.01 | B6: SERVIÇOS PRELIMINARES | H6: =G7+G12 -> 77577.85 | I6: =H6/$K$5 -> 0.020934845
A7: 01.01.001 | B7: LIMPEZA DE TERRENO | G7: =SUM(G8:G11) -> 70809.09 | I7: =G7/$K$5 -> 0.019108254
A8: 01.01.001.001 | B8: Limpeza manual de terreno com vegetação rasteira, incluindo roçagem e queima | C8: m2 | D8: 2581 | E8: 4.38 | G8: 11304.78 | I8: =G8/$K$5 -> 0.0030506622
A9: 01.01.001.002 | B9: Destocamento de árvores de porte médio e raízes profundas, sem auxílio mecânico | C9: un | D9: 64.53 | E9: 217.25 | G9: 14018.06 | I9: =G9/$K$5 -> 0.0037828569
A10: 01.01.001.003 | B10: Coleta e carga manuais de entulho | C10: m3 | D10: 774.3 | E10: 17.54 | G10: 13581.22 | I10: =G10/$K$5 -> 0.0036649731
A11: 01.01.001.004 | B11: Transporte com caminhão basculante de 6 m³, em via urbana em revestimento primário (unidade: txkm). af_07/2020 | C11: txkm | D11: 15563.43 | E11: 2.05 | G11: 31905.03 | I11: =G11/$K$5 -> 0.0086097623
A12: 01.01.002 | B12: DEMOLIÇÃO DE EDIFICAÇÕES | G12: =SUM(G13:G18) -> 6768.76 | I12: =G12/$K$5 -> 0.0018265902
A13: 01.01.002.001 | B13: Demolição de alvenaria de bloco furado, de forma manual, sem reaproveitamento. af_09/2023 | C13: m3 | D13: 42 | E13: 54.08 | G13: 2271.36 | I13: =G13/$K$5 -> 0.00061294002
A14: 01.01.002.002 | B14: Demolição de lajes, em concreto armado, de forma mecanizada com martelete, sem reaproveitamento. af_09/2023 | C14: m3 | D14: 10.5 | E14: 78.37 | G14: 822.88 | I14: =G14/$K$5 -> 0.00022205907
A15: 01.01.002.003 | B15: Demolição de pilares e vigas em concreto armado, de forma mecanizada com martelete, sem reaproveitamento. af_09/2023 | C15: m3 | D15: 3.68 | E15: 168.28 | G15: 618.43 | I15: =G15/$K$5 -> 0.00016688702
A16: 01.01.002.004 | B16: Demolição de revestimento cerâmico, de forma mecanizada com martelete, sem reaproveitamento. af_09/2023 | C16: m2 | D16: 56 | E16: 6.36 | G16: 356.16 | I16: =G16/$K$5 -> 9.6111896e-05
A17: 01.01.002.005 | B17: Coleta e carga manuais de entulho | C17: m3 | D17: 56 | E17: 17.54 | G17: 982.24 | I17: =G17/$K$5 -> 0.00026506331
A18: 01.01.002.006 | B18: Transporte com caminhão basculante de 6 m³, em via urbana em revestimento primário (unidade: txkm). af_07/2020 | C18: txkm | D18: 837.9 | E18: 2.05 | G18: 1717.69 | I18: =G18/$K$5 -> 0.00046352887
A19: 01.02 | B19: ESTRUTURAS DE CONTENÇÃO | H19: =G20+G22+G37 -> 3607402.4 | I19: =H19/$K$5 -> 0.97347902
A20: 01.02.001 | B20: SOLO GRAMPEADO | G20: =G21 -> 1135853.6 | I20: =G20/$K$5 -> 0.30651686
A21: 01.02.001.001 | B21: Solo Grampeado para controlede erosão com malha hexagonal de dupla torção, revestimento em PVC e com resistência de puncionamento de 105 KN e resistência à tração de 89 KN/m. Associada a geomanta tridimensional verde. | C21: m2 | D21: 1505 | E21: 754.72 | G21: 1135853.6 | I21: =G21/$K$5 -> 0.30651686
A22: 01.02.002 | B22: MURO DE ARRIMO | G22: =SUM(G23:G36) -> 2159643.1 | I22: =G22/$K$5 -> 0.58279256
A23: 01.02.002.001 | B23: Concretagem de pilares, fck = 25 mpa, com uso de bomba - lançamento, adensamento e acabamento. af_02/2022_ps | C23: m3 | D23: 390 | E23: 641.26 | G23: 250091.4 | I23: =G23/$K$5 -> 0.067488653
A24: 01.02.002.002 | B24: Armação de cinta de alvenaria estrutural; diâmetro de 16,0 mm. af_09/2021 | C24: kg | D24: 9750 | E24: 8.64 | G24: 84240 | I24: =G24/$K$5 -> 0.022732665
A25: 01.02.002.003 | B25: Armação de verga e contraverga de alvenaria estrutural; diâmetro de 16,0 mm. af_09/2021 | C25: kg | D25: 17550 | E25: 9.66 | G25: 169533 | I25: =G25/$K$5 -> 0.045749489
A26: 01.02.002.004 | B26: Armação vertical de alvenaria estrutural; diâmetro de 16,0 mm. af_09/2021 | C26: kg | D26: 17550 | E26: 8.84 | G26: 155142 | I26: =G26/$K$5 -> 0.041865992
A27: 01.02.002.005 | B27: Reaterro manual de valas, com compactador de solos de percussão. af_08/2023 | C27: m3 | D27: 780 | E27: 25.13 | G27: 19601.4 | I27: =G27/$K$5 -> 0.0052895545
A28: 01.02.002.006 | B28: Grauteamento de cinta intermediária ou de contraverga em alvenaria estrutural. af_09/2021 | C28: m3 | D28: 19.5 | E28: 900.01 | G28: 17550.19 | I28: =G28/$K$5 -> 0.0047360233
A29: 01.02.002.007 | B29: Grauteamento de cinta superior ou de verga em alvenaria estrutural. af_09/2021 | C29: m3 | D29: 19.5 | E29: 1002.12 | G29: 19541.34 | I29: =G29/$K$5 -> 0.0052733469
A30: 01.02.002.008 | B30: Grauteamento vertical em alvenaria estrutural. af_09/2021 | C30: m3 | D30: 487.5 | E30: 1037.21 | G30: 505639.88 | I30: =G30/$K$5 -> 0.13644993
A31: 01.02.002.009 | B31: Tubo pvc rigido soldavel, serie reforçada, p/esgoto e aguas pluviais, d= 100mm | C31: m | D31: 487.5 | E31: 45.3 | G31: 22083.75 | I31: =G31/$K$5 -> 0.0059594314
A32: 01.02.002.010 | B32: Alvenaria de blocos de concreto estrutural 14x19x39 cm (espessura 14 cm), fbk = 14 mpa, utilizando colher de pedreiro. af_10/2022 | C32: m2 | D32: 975 | E32: 106.17 | G32: 103515.75 | I32: =G32/$K$5 -> 0.027934341
A33: 01.02.002.011 | B33: Escavação mecanizada para viga baldrame ou sapata corrida com mini-escavadeira (incluindo escavação para colocação de fôrmas). af_01/2024 | C33: m3 | D33: 780 | E33: 56.85 | G33: 44343 | I33: =G33/$K$5 -> 0.011966223
A34: 01.02.002.012 | B34: Fabricação, montagem e desmontagem de fôrma para sapata corrida, em madeira serrada, e=25 mm, 4 utilizações. af_01/2024 | C34: m2 | D34: 780 | E34: 76.84 | G34: 59935.2 | I34: =G34/$K$5 -> 0.016173871
... A36: 01.02.002.014 | B36: Concretagem de sapata corrida, fck 30 mpa, com uso de bomba - lançamento, adensamento e acabamento. af_01/2024 | C36: m3 | D36: 780 | E36: 734.02 | G36: 572535.6 | I36: =G36/$K$5 -> 0.15450214
A37: 01.02.003 | B37: CORTINA ATIRANTADA | G37: =G38+G44 -> 311905.69 | I37: =G37/$K$5 -> 0.084169607
A38: 01.02.003.001 | B38: FUNDAÇÃO - ESTACAS | G38: =SUM(G39:G43) -> 143856.18 | I38: =G38/$K$5 -> 0.038820447
A39: 01.02.003.001.001 | B39: Perfuratriz com torre metálica para execução de estaca hélice contínua, profundidade máxima de 30 m, diâmetro máximo de 800 mm, potência instalada de 268 hp, mesa rotativa com torque máximo de 170 knm - depreciação. af_06/2015 | C39: h | D39: 171.7 | E39: 238.49 | G39: 40948.73 | I39: =G39/$K$5 -> 0.011050259
A40: 01.02.003.001.002 | B40: Execução de estaca hélice contínua monitorada Ø 500mm, concreto fck=40Mpa, inclusive aço, bombeamento; exclusive mobilização e desmobilização de equipamento e bate-estacas | C40: m | D40: 303 | E40: 337.82 | G40: 102359.46 | I40: =G40/$K$5 -> 0.02762231
A41: 01.02.003.001.003 | B41: Transporte horizontal com carrinho de mão, de sacos de 50 kg (unidade: kgxkm). af_07/2019 | C41: kgxkm | D41: 580.75 | E41: 0.76 | G41: 441.37 | I41: =G41/$K$5 -> 0.00011910632
A42: 01.02.003.001.004 | B42: Carga manual de material de 1ª categoria | C42: m3 | D42: 10.1 | E42: 10.49 | G42: 105.95 | I42: =G42/$K$5 -> 2.8591238e-05
A43: 01.02.003.001.005 | B43: Transporte com caminhão basculante de 14 m³, em via urbana pavimentada, adicional para dmt excedente a 30 km (unidade: m3xkm). af_07/2020 | C43: m3xkm | D43: 0.81 | E43: 0.83 | G43: 0.67 | I43: =G43/$K$5 -> 1.8080349e-07
A44: 01.02.003.002 | B44: ESTRUTURA - CORTINA | G44: =SUM(G45:G56) -> 168049.51 | I44: =G44/$K$5 -> 0.045349161
A45: 01.02.003.002.001 | B45: Fabricação, montagem e desmontagem de fôrma para cortina de contenção, em chapa de madeira compensada plastificada, e = 18 mm, 10 utilizações. af_11/2024 | C45: m2 | D45: 50.5 | E45: 42.99 | G45: 2170.99 | I45: =G45/$K$5 -> 0.00058585458
A46: 01.02.003.002.002 | B46: Armação de cortina de contenção em concreto armado, com aço ca-50 de 10 mm - montagem. af_11/2024 | C46: kg | D46: 3030 | E46: 13.5 | G46: 40905 | I46: =G46/$K$5 -> 0.011038458
A47: 01.02.003.002.003 | B47: Armação de cortina de contenção em concreto armado, com aço ca-50 de 16 mm - montagem. af_11/2024 | C47: kg | D47: 5050 | E47: 10.35 | G47: 52267.5 | I47: =G47/$K$5 -> 0.014104696
A48: 01.02.003.002.004 | B48: Concretagem de cortina de contenção, através de bomba - lançamento, adensamento e acabamento. af_11/2024 | C48: m3 | D48: 75.75 | E48: 648.51 | G48: 49124.63 | I48: =G48/$K$5 -> 0.013256574
A49: 01.02.003.002.005 | B49: Junta de dilatação (altura total do pavimento) com preenchimento parcial em isopor h=15cm e preenchimento do complemento com mastique de poliuretano seção 2x2cm, MBT, Basf, ou similar, para pavimentos em concreto | C49: m | D49: 15.15 | E49: 73.32 | G49: 1110.8 | I49: =G49/$K$5 -> 0.00029975599
A50: 01.02.003.002.006 | B50: Execução de perfuração para tirante, comprimento maior ou igual a 6 m e menor que 14 m, com diâmetro de furo de 100 mm executado com haste e tubos de revestimento utilizando perfuratriz sobre esteira. af_11/2023 | C50: m | D50: 35.35 | E50: 100.93 | G50: 3567.88 | I50: =G50/$K$5 -> 0.00096281366
A51: 01.02.003.002.007 | B51: Tirante Permanente de Aço Protendido D = 32 mm - SICRO 5605882 | C51: m | D51: 25.25 | E51: 381.67 | G51: 9637.17 | I51: =G51/$K$5 -> 0.0026006477
A52: 01.02.003.002.008 | B52: Conjunto cilindro e bomba hidráulica para protensão de monobarras para tirantes, esforço máximo de 30 toneladas - materiais na operação. af_05/2023 | C52: h | D52: 7.58 | E52: 7.22 | G52: 54.69 | I52: =G52/$K$5 -> 1.4758422e-05
A53: 01.02.003.002.009 | B53: Execução de proteção da cabeça do tirante com uso de fôrmas metálicas, 50 utilizações, e concreto fck =15 mpa. af_11/2023 | C53: un | D53: 75.75 | E53: 36.69 | G53: 2779.27 | I53: =G53/$K$5 -> 0.00075000255
A54: 01.02.003.002.010 | B54: Dreno barbacã, dn 100 mm, com material drenante. af_07/2021 | C54: un | D54: 54.04 | E54: 29.6 | G54: 1599.44 | I54: =G54/$K$5 -> 0.00043161841
A55: 01.02.003.002.011 | B55: Lastro com material granular (pedra britada n.1 e pedra britada n.2), aplicado em pisos ou lajes sobre solo, espessura de *10 cm*. af_01/2024 | C55: m3 | D55: 10.1 | E55: 218.93 | G55: 2211.19 | I55: =G55/$K$5 -> 0.00059670279
A56: 01.02.003.002.012 | B56: Impermeabilização - Fornecimento e aplicação de manta geotéxtil RT-21, resistencia a tração=21 kN/m (antigo Bidim OP-40 ou similar) em colchões drenantes | C56: m2 | D56: 101 | E56: 25.95 | G56: 2620.95 | I56: =G56/$K$5 -> 0.00070727896
A57: 01.03 | B57: DRENAGEM DAS ESTRUTURAS DE CONTENÇÃO | H57: =G58+G60 -> 20700.43 | I57: =H57/$K$5 -> 0.0055861343
A58: 01.03.001 | B58: CANALETA | G58: =G59 -> 19674.2 | I58: =G58/$K$5 -> 0.0053092
A59: 01.03.001.001 | B59: Canaleta meia cana pré-moldada de concreto (d = 20 cm) - fornecimento e instalação. af_08/2021 | C59: m | D59: 644 | E59: 30.55 | G59: 19674.2 | I59: =G59/$K$5 -> 0.0053092
A60: 01.03.002 | B60: ESCADA HIDRÁULICA | G60: =G61 -> 1026.23 | I60: =G60/$K$5 -> 0.00027693427
A61: 01.03.002.001 | B61: Escada hidráulica, largura até 1m, tipo descida d'água de corte ou aterro em degraus (dcd 02, 04 e dad 02), em concreto usinado, fck = 20 mpa, lançado com bomba, incluindo armação, materiais e fôrmas (3 utilizações). af_08/2022 | C61: m3 | D61: 0.6 | E61: 1710.38 | G61: 1026.23 | I61: =G61/$K$5 -> 0.00027693427
A63: 2 | B63: Setor de Risco A2S1R3 (Contenções e Demolições) | K63: =SUM(H64:H90) -> 1052807.1 | L63: =K63/$G$149 -> 0.20124224
A64: 02.01 | B64: SERVIÇOS PRELIMINARES | H64: =G65 -> 51714.51 | I64: =H64/$K$63 -> 0.049120593
A65: 02.01.001 | B65: LIMPEZA DE TERRENO | G65: =SUM(G66:G69) -> 51714.51 | I65: =G65/$K$63 -> 0.049120593
A66: 02.01.001.001 | B66: Limpeza manual de terreno com vegetação rasteira, incluindo roçagem e queima | C66: m2 | D66: 1885 | E66: 4.38 | G66: 8256.3 | I66: =G66/$K$63 -> 0.0078421773
A67: 02.01.001.002 | B67: Destocamento de árvores de porte médio e raízes profundas, sem auxílio mecânico | C67: un | D67: 47.13 | E67: 217.25 | G67: 10237.91 | I67: =G67/$K$63 -> 0.0097243929
A68: 02.01.001.003 | B68: Coleta e carga manuais de entulho | C68: m3 | D68: 565.5 | E68: 17.54 | G68: 9918.87 | I68: =G68/$K$63 -> 0.0094213554
A69: 02.01.001.004 | B69: Transporte com caminhão basculante de 6 m³, em via urbana em revestimento primário (unidade: txkm). af_07/2020 | C69: txkm | D69: 11366.55 | E69: 2.05 | G69: 23301.43 | I69: =G69/$K$63 -> 0.022132668
A70: 02.02 | B70: ESTRUTURAS DE CONTENÇÃO | H70: =G71 -> 990113.31 | I70: =H70/$K$63 -> 0.94045082
A71: 02.02.002 | B71: MURO DE ARRIMO | G71: =SUM(G72:G85) -> 990113.31 | I71: =G71/$K$63 -> 0.94045082
A72: 02.02.002.001 | B72: Concretagem de pilares, fck = 25 mpa, com uso de bomba - lançamento, adensamento e acabamento. af_02/2022_ps | C72: m3 | D72: 178.8 | E72: 641.26 | G72: 114657.29 | I72: =G72/$K$63 -> 0.10890626
A73: 02.02.002.002 | B73: Armação de cinta de alvenaria estrutural; diâmetro de 16,0 mm. af_09/2021 | C73: kg | D73: 4470 | E73: 8.64 | G73: 38620.8 | I73: =G73/$K$63 -> 0.036683643
A74: 02.02.002.003 | B74: Armação de verga e contraverga de alvenaria estrutural; diâmetro de 16,0 mm. af_09/2021 | C74: kg | D74: 8046 | E74: 9.66 | G74: 77724.36 | I74: =G74/$K$63 -> 0.073825831
A75: 02.02.002.004 | B75: Armação vertical de alvenaria estrutural; diâmetro de 16,0 mm. af_09/2021 | C75: kg | D75: 8046 | E75: 8.84 | G75: 71126.64 | I75: =G75/$K$63 -> 0.067559042
A76: 02.02.002.005 | B76: Reaterro manual de valas, com compactador de solos de percussão. af_08/2023 | C76: m3 | D76: 357.6 | E76: 25.13 | G76: 8986.49 | I76: =G76/$K$63 -> 0.0085357421
A77: 02.02.002.006 | B77: Grauteamento de cinta intermediária ou de contraverga em alvenaria estrutural. af_09/2021 | C77: m3 | D77: 8.94 | E77: 900.01 | G77: 8046.09 | I77: =G77/$K$63 -> 0.0076425111
A78: 02.02.002.007 | B78: Grauteamento de cinta superior ou de verga em alvenaria estrutural. af_09/2021 | C78: m3 | D78: 8.94 | E78: 1002.12 | G78: 8958.95 | I78: =G78/$K$63 -> 0.0085095835
A79: 02.02.002.008 | B79: Grauteamento vertical em alvenaria estrutural. af_09/2021 | C79: m3 | D79: 223.5 | E79: 1037.21 | G79: 231816.43 | I79: =G79/$K$63 -> 0.22018889
A80: 02.02.002.009 | B80: Tubo pvc rigido soldavel, serie reforçada, p/esgoto e aguas pluviais, d= 100mm | C80: m | D80: 223.5 | E80: 45.3 | G80: 10124.55 | I80: =G80/$K$63 -> 0.0096167189
A81: 02.02.002.010 | B81: Alvenaria de blocos de concreto estrutural 14x19x39 cm (espessura 14 cm), fbk = 14 mpa, utilizando colher de pedreiro. af_10/2022 | C81: m2 | D81: 447 | E81: 106.17 | G81: 47457.99 | I81: =G81/$K$63 -> 0.045077574
A82: 02.02.002.011 | B82: Escavação mecanizada para viga baldrame ou sapata corrida com mini-escavadeira (incluindo escavação para colocação de fôrmas). af_01/2024 | C82: m3 | D82: 357.6 | E82: 56.85 | G82: 20329.56 | I82: =G82/$K$63 -> 0.019309862
A83: 02.02.002.012 | B83: Fabricação, montagem e desmontagem de fôrma para sapata corrida, em madeira serrada, e=25 mm, 4 utilizações. af_01/2024 | C83: m2 | D83: 357.6 | E83: 76.84 | G83: 27477.98 | I83: =G83/$K$63 -> 0.026099729
... A85: 02.02.002.014 | B85: Concretagem de sapata corrida, fck 30 mpa, com uso de bomba - lançamento, adensamento e acabamento. af_01/2024 | C85: m3 | D85: 357.6 | E85: 734.02 | G85: 262485.55 | I85: =G85/$K$63 -> 0.2493197
A86: 02.03 | B86: DRENAGEM DAS ESTRUTURAS DE CONTENÇÃO | H86: =G87+G89 -> 10979.29 | I86: =H86/$K$63 -> 0.010428586
A87: 02.03.001 | B87: CANALETA | G87: =G88 -> 9439.95 | I87: =G87/$K$63 -> 0.0089664573
A88: 02.03.001.001 | B88: Canaleta meia cana pré-moldada de concreto (d = 20 cm) - fornecimento e instalação. af_08/2021 | C88: m | D88: 309 | E88: 30.55 | G88: 9439.95 | I88: =G88/$K$63 -> 0.0089664573
A89: 02.03.002 | B89: ESCADA HIDRÁULICA | G89: =G90 -> 1539.34 | I89: =G89/$K$63 -> 0.0014621292
A90: 02.03.002.001 | B90: Escada hidráulica, largura até 1m, tipo descida d'água de corte ou aterro em degraus (dcd 02, 04 e dad 02), em concreto usinado, fck = 20 mpa, lançado com bomba, incluindo armação, materiais e fôrmas (3 utilizações). af_08/2022 | C90: m3 | D90: 0.9 | E90: 1710.38 | G90: 1539.34 | I90: =G90/$K$63 -> 0.0014621292
A92: 3 | B92: Setor de Risco A2S3R3 (Contenções e Demolições) | K92: =SUM(H93:H117) -> 473053.69 | L92: =K92/$G$149 -> 0.090423385
A93: 03.01 | B93: SERVIÇOS PRELIMINARES | H93: =G94 -> 5761.29 | I93: =H93/$K$92 -> 0.012178935
A94: 03.01.001 | B94: LIMPEZA DE TERRENO | G94: =SUM(G95:G98) -> 5761.29 | I94: =G94/$K$92 -> 0.012178935
A95: 03.01.001.001 | B95: Limpeza manual de terreno com vegetação rasteira, incluindo roçagem e queima | C95: m2 | D95: 210 | E95: 4.38 | G95: 919.8 | I95: =G95/$K$92 -> 0.0019443882
A96: 03.01.001.002 | B96: Destocamento de árvores de porte médio e raízes profundas, sem auxílio mecânico | C96: un | D96: 5.25 | E96: 217.25 | G96: 1140.56 | I96: =G96/$K$92 -> 0.0024110582
A97: 03.01.001.003 | B97: Coleta e carga manuais de entulho | C97: m3 | D97: 63 | E97: 17.54 | G97: 1105.02 | I97: =G97/$K$92 -> 0.0023359294
A98: 03.01.001.004 | B98: Transporte com caminhão basculante de 6 m³, em via urbana em revestimento primário (unidade: txkm). af_07/2020 | C98: txkm | D98: 1266.3 | E98: 2.05 | G98: 2595.91 | I98: =G98/$K$92 -> 0.0054875589
A99: 03.02 | B99: ESTRUTURAS DE CONTENÇÃO | H99: =G100 -> 465153.9 | I99: =H99/$K$92 -> 0.98330044
A100: 03.02.001 | B100: MURO DE ARRIMO | G100: =SUM(G101:G114) -> 465153.9 | I100: =G100/$K$92 -> 0.98330044
A101: 03.02.001.001 | B101: Concretagem de pilares, fck = 25 mpa, com uso de bomba - lançamento, adensamento e acabamento. af_02/2022_ps | C101: m3 | D101: 84 | E101: 641.26 | G101: 53865.84 | I101: =G101/$K$92 -> 0.11386834
A102: 03.02.001.002 | B102: Armação de cinta de alvenaria estrutural; diâmetro de 16,0 mm. af_09/2021 | C102: kg | D102: 2100 | E102: 8.64 | G102: 18144 | I102: =G102/$K$92 -> 0.038355054
A103: 03.02.001.003 | B103: Armação de verga e contraverga de alvenaria estrutural; diâmetro de 16,0 mm. af_09/2021 | C103: kg | D103: 3780 | E103: 9.66 | G103: 36514.8 | I103: =G103/$K$92 -> 0.077189547
A104: 03.02.001.004 | B104: Armação vertical de alvenaria estrutural; diâmetro de 16,0 mm. af_09/2021 | C104: kg | D104: 3780 | E104: 8.84 | G104: 33415.2 | I104: =G104/$K$92 -> 0.070637225
A105: 03.02.001.005 | B105: Reaterro manual de valas, com compactador de solos de percussão. af_08/2023 | C105: m3 | D105: 168 | E105: 25.13 | G105: 4221.84 | I105: =G105/$K$92 -> 0.0089246529
...

Sheet 04_Seringal
A1: PMRR DE ILHÉUS
A3: Empreendimento: 000028 - Alto do Seringal (Bairro Esperança) | G3: VALOR TOTAL
A4: ITEM | B4: DESCRIÇÃO DO ITEM | C4: UNID | D4: QUANT | E4: PREÇO UNIT | G4: Valor Parcial | I4: Parcial (%) | K4: Soma | L4: (%)
A5: 1 | B5: Setor de Risco A2S1R3 (Contenções e Demolições) | K5: =SUM(H5:H30) -> 459537.89 | L5: =K5/$G$138 -> 0.17470557
A6: 01.01 | B6: SERVIÇOS PRELIMINARES | H6: =G7 -> 5596.69 | I6: =H6/$K$5 -> 0.012178952
A7: 01.01.001 | B7: LIMPEZA DE TERRENO (204,0 m²) | G7: =SUM(G8:G11) -> 5596.69 | I7: =G7/$K$5 -> 0.012178952
A8: 01.01.001.001 | B8: Limpeza manual de terreno com vegetação rasteira, incluindo roçagem e queima | C8: m2 | D8: 204 | E8: 4.38 | G8: 893.52 | I8: =G8/$K$5 -> 0.0019443881
A9: 01.01.001.002 | B9: Destocamento de árvores de porte médio e raízes profundas, sem auxílio mecânico | C9: un | D9: 5.1 | E9: 217.25 | G9: 1107.97 | I9: =G9/$K$5 -> 0.0024110525
A10: 01.01.001.003 | B10: Coleta e carga manuais de entulho | C10: m3 | D10: 61.2 | E10: 17.54 | G10: 1073.45 | I10: =G10/$K$5 -> 0.0023359336
A11: 01.01.001.004 | B11: Transporte com caminhão basculante de 6 m³, em via urbana em revestimento primário (unidade: txkm). af_07/2020 | C11: txkm | D11: 1230.12 | E11: 2.05 | G11: 2521.75 | I11: =G11/$K$5 -> 0.005487578
A12: 01.02 | B12: ESTRUTURAS DE CONTENÇÃO | H12: =G13 -> 451863.8 | I12: =H12/$K$5 -> 0.98330042
A13: 01.02.001 | B13: MURO DE ARRIMO (204,0 m²) | G13: =SUM(G14:G27) -> 451863.8 | I13: =G13/$K$5 -> 0.98330042
A14: 01.02.001.001 | B14: Concretagem de pilares, fck = 25 mpa, com uso de bomba - lançamento, adensamento e acabamento. af_02/2022_ps | C14: m3 | D14: 81.6 | E14: 641.26 | G14: 52326.82 | I14: =G14/$K$5 -> 0.11386835
A15: 01.02.001.002 | B15: Armação de cinta de alvenaria estrutural; diâmetro de 16,0 mm. af_09/2021 | C15: kg | D15: 2040 | E15: 8.64 | G15: 17625.6 | I15: =G15/$K$5 -> 0.038355053
A16: 01.02.001.003 | B16: Armação de verga e contraverga de alvenaria estrutural; diâmetro de 16,0 mm. af_09/2021 | C16: kg | D16: 3672 | E16: 9.66 | G16: 35471.52 | I16: =G16/$K$5 -> 0.077189544
A17: 01.02.001.004 | B17: Armação vertical de alvenaria estrutural; diâmetro de 16,0 mm. af_09/2021 | C17: kg | D17: 3672 | E17: 8.84 | G17: 32460.48 | I17: =G17/$K$5 -> 0.070637222
A18: 01.02.001.005 | B18: Reaterro manual de valas, com compactador de solos de percussão. af_08/2023 | C18: m3 | D18: 163.2 | E18: 25.13 | G18: 4101.22 | I18: =G18/$K$5 -> 0.0089246613
A19: 01.02.001.006 | B19: Grauteamento de cinta intermediária ou de contraverga em alvenaria estrutural. af_09/2021 | C19: m3 | D19: 4.08 | E19: 900.01 | G19: 3672.04 | I19: =G19/$K$5 -> 0.007990723
A20: 01.02.001.007 | B20: Grauteamento de cinta superior ou de verga em alvenaria estrutural. af_09/2021 | C20: m3 | D20: 4.08 | E20: 1002.12 | G20: 4088.65 | I20: =G20/$K$5 -> 0.0088973077
A21: 01.02.001.008 | B21: Grauteamento vertical em alvenaria estrutural. af_09/2021 | C21: m3 | D21: 102 | E21: 1037.21 | G21: 105795.42 | I21: =G21/$K$5 -> 0.23022132
A22: 01.02.001.009 | B22: Tubo pvc rigido soldavel, serie reforçada, p/esgoto e aguas pluviais, d= 100mm | C22: m | D22: 102 | E22: 45.3 | G22: 4620.6 | I22: =G22/$K$5 -> 0.010054884
A23: 01.02.001.010 | B23: Alvenaria de blocos de concreto estrutural 14x19x39 cm (espessura 14 cm), fbk = 14 mpa, utilizando colher de pedreiro. af_10/2022 | C23: m2 | D23: 204 | E23: 106.17 | G23: 21658.68 | I23: =G23/$K$5 -> 0.047131435
A24: 01.02.001.011 | B24: Escavação mecanizada para viga baldrame ou sapata corrida com mini-escavadeira (incluindo escavação para colocação de fôrmas). af_01/2024 | C24: m3 | D24: 163.2 | E24: 56.85 | G24: 9277.92 | I24: =G24/$K$5 -> 0.020189674
A25: 01.02.001.012 | B25: Fabricação, montagem e desmontagem de fôrma para sapata corrida, em madeira serrada, e=25 mm, 4 utilizações. af_01/2024 | C25: m2 | D25: 163.2 | E25: 76.84 | G25: 12540.29 | I25: =G25/$K$5 -> 0.027288914
... A27: 01.02.001.014 | B27: Concretagem de sapata corrida, fck 30 mpa, com uso de bomba - lançamento, adensamento e acabamento. af_01/2024 | C27: m3 | D27: 163.2 | E27: 734.02 | G27: 119792.06 | I27: =G27/$K$5 -> 0.2606794
A28: 01.03 | B28: DRENAGEM DAS ESTRUTURAS DE CONTENÇÃO | H28: =G29 -> 2077.4 | I28: =H28/$K$5 -> 0.0045206283
A29: 01.03.001 | B29: CANALETA (68,0 m) | G29: =G30 -> 2077.4 | I29: =G29/$K$5 -> 0.0045206283
A30: 01.03.001.001 | B30: Canaleta meia cana pré-moldada de concreto (d = 20 cm) - fornecimento e instalação. af_08/2021 | C30: m | D30: 68 | E30: 30.55 | G30: 2077.4 | I30: =G30/$K$5 -> 0.0045206283
A32: 2 | B32: Setor de Risco A3S1R4 (Contenções e Demolições) | K32: =SUM(H32:H92) -> 2170818.4 | L32: =K32/$G$138 -> 0.82529443
A33: 02.01 | B33: SERVIÇOS PRELIMINARES | H33: =G34+G39 -> 74293.39 | I33: =H33/$K$32 -> 0.034223678
A34: 02.01.001 | B34: LIMPEZA DE TERRENO (2063,0 m²) | G34: =SUM(G35:G38) -> 56597.89 | I34: =G34/$K$32 -> 0.026072144
A35: 02.01.001.001 | B35: Limpeza manual de terreno com vegetação rasteira, incluindo roçagem e queima | C35: m2 | D35: 2063 | E35: 4.38 | G35: 9035.94 | I35: =G35/$K$32 -> 0.0041624578
A36: 02.01.001.002 | B36: Destocamento de árvores de porte médio e raízes profundas, sem auxílio mecânico | C36: un | D36: 51.58 | E36: 217.25 | G36: 11204.67 | I36: =G36/$K$32 -> 0.0051614957
A37: 02.01.001.003 | B37: Coleta e carga manuais de entulho | C37: m3 | D37: 618.9 | E37: 17.54 | G37: 10855.51 | I37: =G37/$K$32 -> 0.0050006532
A38: 02.01.001.004 | B38: Transporte com caminhão basculante de 6 m³, em via urbana em revestimento primário (unidade: txkm). af_07/2020 | C38: txkm | D38: 12439.89 | E38: 2.05 | G38: 25501.77 | I38: =G38/$K$32 -> 0.011747537
A39: 02.01.002 | B39: DEMOLIÇÃO DE EDIFICAÇÕES (183,0 m²) | G39: =SUM(G40:G45) -> 17695.5 | I39: =G39/$K$32 -> 0.0081515339
A40: 02.01.002.001 | B40: Demolição de alvenaria de bloco furado, de forma manual, sem reaproveitamento. af_09/2023 | C40: m3 | D40: 109.8 | E40: 54.08 | G40: 5937.98 | I40: =G40/$K$32 -> 0.0027353647
A41: 02.01.002.002 | B41: Demolição de lajes, em concreto armado, de forma mecanizada com martelete, sem reaproveitamento. af_09/2023 | C41: m3 | D41: 27.45 | E41: 78.37 | G41: 2151.26 | I41: =G41/$K$32 -> 0.0009909903
A42: 02.01.002.003 | B42: Demolição de pilares e vigas em concreto armado, de forma mecanizada com martelete, sem reaproveitamento. af_09/2023 | C42: m3 | D42: 9.61 | E42: 168.28 | G42: 1616.75 | I42: =G42/$K$32 -> 0.00074476519
A43: 02.01.002.004 | B43: Demolição de revestimento cerâmico, de forma mecanizada com martelete, sem reaproveitamento. af_09/2023 | C43: m2 | D43: 146.4 | E43: 6.36 | G43: 931.1 | I43: =G43/$K$32 -> 0.00042891657
A44: 02.01.002.005 | B44: Coleta e carga manuais de entulho | C44: m3 | D44: 146.4 | E44: 17.54 | G44: 2567.86 | I44: =G44/$K$32 -> 0.0011828995
A45: 02.01.002.006 | B45: Transporte com caminhão basculante de 6 m³, em via urbana em revestimento primário (unidade: txkm). af_07/2020 | C45: txkm | D45: 2190.51 | E45: 2.05 | G45: 4490.55 | I45: =G45/$K$32 -> 0.0020685977
A46: 02.02 | B46: ESTRUTURAS DE CONTENÇÃO | H46: =G47+G49+G64+G68 -> 2077835.7 | I46: =H46/$K$32 -> 0.95716698
A47: 02.02.001 | B47: SOLO GRAMPEADO (739,0 m²) | G47: =G48 -> 557738.08 | I47: =G47/$K$32 -> 0.25692526
A48: 02.02.001.001 | B48: Solo Grampeado para controlede erosão com malha hexagonal de dupla torção, revestimento em PVC e com resistência de puncionamento de 105 KN e resistência à tração de 89 KN/m. Associada a geomanta tridimensional verde. | C48: m2 | D48: 739 | E48: 754.72 | G48: 557738.08 | I48: =G48/$K$32 -> 0.25692526
A49: 02.02.002 | B49: MURO DE ARRIMO (606,0 m²) | G49: =SUM(G50:G63) -> 1403098.4 | I49: =G49/$K$32 -> 0.64634533
A50: 02.02.002.001 | B50: Concretagem de pilares, fck = 25 mpa, com uso de bomba - lançamento, adensamento e acabamento. af_02/2022_ps | C50: m3 | D50: 242.4 | E50: 641.26 | G50: =D50*E50 -> 155441.42 | I50: =G50/$K$32 -> 0.071604987
A51: 02.02.002.002 | B51: Armação de cinta de alvenaria estrutural; diâmetro de 16,0 mm. af_09/2021 | C51: kg | D51: 6060 | E51: 8.64 | G51: =D51*E51 -> 52358.4 | I51: =G51/$K$32 -> 0.024119198
A52: 02.02.002.003 | B52: Armação de verga e contraverga de alvenaria estrutural; diâmetro de 16,0 mm. af_09/2021 | C52: kg | D52: 10908 | E52: 9.66 | G52: =D52*E52 -> 105371.28 | I52: =G52/$K$32 -> 0.048539887
A53: 02.02.002.004 | B53: Armação vertical de alvenaria estrutural; diâmetro de 16,0 mm. af_09/2021 | C53: kg | D53: 10908 | E53: 8.84 | G53: =D53*E53 -> 96426.72 | I53: =G53/$K$32 -> 0.044419524
A54: 02.02.002.005 | B54: Reaterro manual de valas, com compactador de solos de percussão. af_08/2023 | C54: m3 | D54: 484.8 | E54: 25.13 | G54: =D54*E54 -> 12183.024 | I54: =G54/$K$32 -> 0.0056121801
A55: 02.02.002.006 | B55: Grauteamento de cinta intermediária ou de contraverga em alvenaria estrutural. af_09/2021 | C55: m3 | D55: 37.53551 | E55: 900.01 | G55: =D55*E55 -> 33782.334 | I55: =G55/$K$32 -> 0.015562027
A56: 02.02.002.007 | B56: Grauteamento de cinta superior ou de verga em alvenaria estrutural. af_09/2021 | C56: m3 | D56: 37 | E56: 1002.12 | G56: =D56*E56 -> 37078.44 | I56: =G56/$K$32 -> 0.017080397
A57: 02.02.002.008 | B57: Grauteamento vertical em alvenaria estrutural. af_09/2021 | C57: m3 | D57: 315 | E57: 1037.21 | G57: =D57*E57 -> 326721.15 | I57: =G57/$K$32 -> 0.15050598
A58: 02.02.002.009 | B58: Tubo pvc rigido soldavel, serie reforçada, p/esgoto e aguas pluviais, d= 100mm | C58: m | D58: 315 | E58: 45.3 | G58: =D58*E58 -> 14269.5 | I58: =G58/$K$32 -> 0.0065733273
A59: 02.02.002.010 | B59: Alvenaria de blocos de concreto estrutural 14x19x39 cm (espessura 14 cm), fbk = 14 mpa, utilizando colher de pedreiro. af_10/2022 | C59: m2 | D59: 606 | E59: 106.17 | G59: =D59*E59 -> 64339.02 | I59: =G59/$K$32 -> 0.02963814
A60: 02.02.002.011 | B60: Escavação mecanizada para viga baldrame ou sapata corrida com mini-escavadeira (incluindo escavação para colocação de fôrmas). af_01/2024 | C60: m3 | D60: 484.8 | E60: 56.85 | G60: =D60*E60 -> 27560.88 | I60: =G60/$K$32 -> 0.012696078
A61: 02.02.002.012 | B61: Fabricação, montagem e desmontagem de fôrma para sapata corrida, em madeira serrada, e=25 mm, 4 utilizações. af_01/2024 | C61: m2 | D61: 484.8 | E61: 76.84 | G61: =D61*E61 -> 37252.032 | I61: =G61/$K$32 -> 0.017160363
... A63: 02.02.002.014 | B63: Concretagem de sapata corrida, fck 30 mpa, com uso de bomba - lançamento, adensamento e acabamento. af_01/2024 | C63: m3 | D63: 484.8 | E63: 734.02 | G63: =D63*E63 -> 355852.9 | I63: =G63/$K$32 -> 0.16392568
A64: 02.02.003 | B64: RETALUDAMENTO / RECONSTRUÇÃO EM CORTE/ATERRO (715,0 m²) | G64: =SUM(G65:G67) -> 107734.77 | I64: =G64/$K$32 -> 0.049628642
A65: 02.02.003.001 | B65: Escavação manual de vala ou cava em material de 1ª categoria, profundidade entre 1,50 e 3,00m | C65: m3 | D65: 1287 | E65: 78.85 | G65: =D65*E65 -> 101479.95 | I65: =G65/$K$32 -> 0.046747323
A66: 02.02.003.002 | B66: Carga manual de material de 1ª categoria | C66: m3 | D66: 214.5 | E66: 10.49 | G66: =D66*E66 -> 2250.105 | I66: =G66/$K$32 -> 0.0010365238
A67: 02.02.003.003 | B67: Compactação manual com compactador a percussão sapinho, a 95% do pn | C67: m3 | D67: 214.5 | E67: 18.67 | G67: =D67*E67 -> 4004.715 | I67: =G67/$K$32 -> 0.001844795
A68: 02.02.004 | B68: CORTINA ATIRANTADA (3,0 m²) | G68: =G69+G75 -> 9264.52 | I68: =G68/$K$32 -> 0.0042677545
A69: 02.02.004.001 | B69: FUNDAÇÃO - ESTACAS | G69: =SUM(G70:G74) -> 4272.96 | I69: =G69/$K$32 -> 0.0019683636
A70: 02.02.004.001.001 | B70: Perfuratriz com torre metálica para execução de estaca hélice contínua, profundidade máxima de 30 m, diâmetro máximo de 800 mm, potência instalada de 268 hp, mesa rotativa com torque máximo de 170 knm - depreciação. af_06/2015 | C70: h | D70: 5.1 | E70: 238.49 | G70: 1216.3 | I70: =G70/$K$32 -> 0.0005602956
A71: 02.02.004.001.002 | B71: Execução de estaca hélice contínua monitorada Ø 500mm, concreto fck=40Mpa, inclusive aço, bombeamento; exclusive mobilização e desmobilização de equipamento e bate-estacas | C71: m | D71: 9 | E71: 337.82 | G71: 3040.38 | I71: =G71/$K$32 -> 0.0014005685
A72: 02.02.004.001.003 | B72: Transporte horizontal com carrinho de mão, de sacos de 50 kg (unidade: kgxkm). af_07/2019 | C72: kgxkm | D72: 17.25 | E72: 0.76 | G72: 13.11 | I72: =G72/$K$32 -> 6.039197e-06
A73: 02.02.004.001.004 | B73: Carga manual de material de 1ª categoria | C73: m3 | D73: 0.3 | E73: 10.49 | G73: 3.15 | I73: =G73/$K$32 -> 1.4510656e-06
A74: 02.02.004.001.005 | B74: Transporte com caminhão basculante de 14 m³, em via urbana pavimentada, adicional para dmt excedente a 30 km (unidade: m3xkm). af_07/2020 | C74: m3xkm | D74: 0.02 | E74: 0.83 | G74: 0.02 | I74: =G74/$K$32 -> 9.2131151e-09
A75: 02.02.004.002 | B75: ESTRUTURA - CORTINA | G75: =SUM(G76:G87) -> 4991.56 | I75: =G75/$K$32 -> 0.0022993908
A76: 02.02.004.002.001 | B76: Fabricação, montagem e desmontagem de fôrma para cortina de contenção, em chapa de madeira compensada plastificada, e = 18 mm, 10 utilizações. af_11/2024 | C76: m2 | D76: 1.5 | E76: 42.99 | G76: 64.48 | I76: =G76/$K$32 -> 2.9703083e-05
A77: 02.02.004.002.002 | B77: Armação de cortina de contenção em concreto armado, com aço ca-50 de 10 mm - montagem. af_11/2024 | C77: kg | D77: 90 | E77: 13.5 | G77: 1215 | I77: =G77/$K$32 -> 0.00055969674
A78: 02.02.004.002.003 | B78: Armação de cortina de contenção em concreto armado, com aço ca-50 de 16 mm - montagem. af_11/2024 | C78: kg | D78: 150 | E78: 10.35 | G78: 1552.5 | I78: =G78/$K$32 -> 0.00071516806
A79: 02.02.004.002.004 | B79: Concretagem de cortina de contenção, através de bomba - lançamento, adensamento e acabamento. af_11/2024 | C79: m3 | D79: 2.25 | E79: 648.51 | G79: 1459.15 | I79: =G79/$K$32 -> 0.00067216585
A80: 02.02.004.002.005 | B80: Junta de dilatação (altura total do pavimento) com preenchimento parcial em isopor h=15cm e preenchimento do complemento com mastique de poliuretano seção 2x2cm, MBT, Basf, ou similar, para pavimentos em concreto | C80: m | D80: 0.45 | E80: 73.32 | G80: 32.99 | I80: =G80/$K$32 -> 1.5197033e-05
A81: 02.02.004.002.006 | B81: Execução de perfuração para tirante, comprimento maior ou igual a 6 m e menor que 14 m, com diâmetro de furo de 100 mm executado com haste e tubos de revestimento utilizando perfuratriz sobre esteira. af_11/2023 | C81: m | D81: 1.05 | E81: 100.93 | G81: 105.98 | I81: =G81/$K$32 -> 4.8820297e-05
A82: 02.02.004.002.007 | B82: Tirante Permanente de Aço Protendido D = 32 mm - SICRO 5605882 | C82: m | D82: 0.75 | E82: 381.67 | G82: 286.25 | I82: =G82/$K$32 -> 0.00013186271
A83: 02.02.004.002.008 | B83: Conjunto cilindro e bomba hidráulica para protensão de monobarras para tirantes, esforço máximo de 30 toneladas - materiais na operação. af_05/2023 | C83: h | D83: 0.23 | E83: 7.22 | G83: 1.62 | I83: =G83/$K$32 -> 7.4626232e-07
A84: 02.02.004.002.009 | B84: Execução de proteção da cabeça do tirante com uso de fôrmas metálicas, 50 utilizações, e concreto fck =15 mpa. af_11/2023 | C84: un | D84: 2.25 | E84: 36.69 | G84: 82.55 | I84: =G84/$K$32 -> 3.8027133e-05
A85: 02.02.004.002.010 | B85: Dreno barbacã, dn 100 mm, com material drenante. af_07/2021 | C85: un | D85: 1.61 | E85: 29.6 | G85: 47.51 | I85: =G85/$K$32 -> 2.1885755e-05
A86: 02.02.004.002.011 | B86: Lastro com material granular (pedra britada n.1 e pedra britada n.2), aplicado em pisos ou lajes sobre solo, espessura de *10 cm*. af_01/2024 | C86: m3 | D86: 0.3 | E86: 218.93 | G86: 65.68 | I86: =G86/$K$32 -> 3.025587e-05
A87: 02.02.004.002.012 | B87: Impermeabilização - Fornecimento e aplicação de manta geotéxtil RT-21, resistencia a tração=21 kN/m (antigo Bidim OP-40 ou similar) em colchões drenantes | C87: m2 | D87: 3 | E87: 25.95 | G87: 77.85 | I87: =G87/$K$32 -> 3.5862051e-05
A88: 02.03 | B88: DRENAGEM DAS ESTRUTURAS DE CONTENÇÃO | H88: =G89+G91 -> 18689.31 | I88: =H88/$K$32 -> 0.0086093382
A89: 02.03.001 | B89: CANALETA (455,0 m) | G89: =G90 -> 13900.25 | I89: =G89/$K$32 -> 0.0064032302
A90: 02.03.001.001 | B90: Canaleta meia cana pré-moldada de concreto (d = 20 cm) - fornecimento e instalação. af_08/2021 | C90: m | D90: 455 | E90: 30.55 | G90: 13900.25 | I90: =G90/$K$32 -> 0.0064032302
A91: 02.03.002 | B91: ESCADA HIDRÁULICA (28,0 m) | G91: =G92 -> 4789.06 | I91: =G91/$K$32 -> 0.0022061081
A92: 02.03.002.001 | B92: Escada hidráulica, largura até 1m, tipo descida d'água de corte ou aterro em degraus (dcd 02, 04 e dad 02), em concreto usinado, fck = 20 mpa, lançado com bomba, incluindo armação, materiais e fôrmas (3 utilizações). af_08/2022 | C92: m3 | D92: 2.8 | E92: 1710.38 | G92: 4789.06 | I92: =G92/$K$32 -> 0.0022061081
A94: 3 | B94: Obras Complementares | K94: =SUM(H94:H135) -> 413458.15 | L94: 1
A95: 03.01 | B95: DRENAGEM | H95: =G96+G98+G100 -> 203825.04 | I95: =H95/$K$94 -> 0.49297623
A96: 03.01.001 | B96: CANALETA | G96: =G97 -> 14602.9 | I96: =G96/$K$94 -> 0.035318931
A97: 03.01.001.001 | B97: Canaleta meia cana pré-moldada de concreto (d = 20 cm) - fornecimento e instalação. af_08/2021 | C97: m | D97: 478 | E97: 30.55 | G97: 14602.9 | I97: =G97/$K$94 -> 0.035318931
A98: 03.01.002 | B98: ESCADA HIDRÁULICA | G98: =G99 -> 57126.69 | I98: =G98/$K$94 -> 0.13816801
A99: 03.01.002.001 | B99: Escada hidráulica, largura até 1m, tipo descida d'água de corte ou aterro em degraus (dcd 02, 04 e dad 02), em concreto usinado, fck = 20 mpa, lançado com bomba, incluindo armação, materiais e fôrmas (3 utilizações). af_08/2022 | C99: m3 | D99: 33.4 | E99: 1710.38 | G99: 57126.69 | I99: =G99/$K$94 -> 0.13816801
A100: 03.01.003 | B100: REDE COLETORA PLUVIAL (REDE+PV) | G100: =SUM(G101:G102) -> 132095.45 | I100: =G100/$K$94 -> 0.31948929
A101: 03.01.003.001 | B101: Fornecimento e assentamento de tubo corrugado parede dupla PEAD, d= 300mm (12"), p/sistemas drenagem, Tigre-ADS N-12 ou similar | C101: m | D101: 624 | E101: 206.46 | G101: 128831.04 | I101: =G101/$K$94 -> 0.31159391
A102: 03.01.003.002 | B102: Caixa de inspeção 0,30 x 0,30 x 0,40m | C102: un | D102: 20.78 | E102: 157.1 | G102: 3264.41 | I102: =G102/$K$94 -> 0.0078953819
A103: 03.02 | B103: MOBILIDADE | H103: =G104+G106+G120 -> 150790.72 | I103: =H103/$K$94 -> 0.36470613
A104: 03.02.001 | B104: VIELA (CAMINHO PAVIMENTADO/BECO) | G104: =G105 -> 6373.78 | I104: =G104/$K$94 -> 0.01541578
A105: 03.02.001.001 | B105: Execução de passeio (calçada) ou piso de concreto com concreto moldado in loco, feito em obra, acabamento convencional, não armado. af_08/2022 | C105: m3 | D105: 8.16 | E105: 781.1 | G105: 6373.78 | I105: =G105/$K$94 -> 0.01541578
...

Sheet 05_Vila Freitas
A1: PMRR DE ILHÉUS
A3: Empreendimento: 000016 - Alto Vila Freitas (Bairro Esperança) | G3: VALOR TOTAL
A4: ITEM | B4: DESCRIÇÃO DO ITEM | C4: UNID | D4: QUANT | E4: PREÇO UNIT | G4: Valor Parcial | I4: Parcial (%) | K4: Soma | L4: (%)
A5: 1 | B5: Setor de Risco A1S1R3 (Contenções e Demolições) | K5: =SUM(H5:H37) -> 800252.69 | L5: 1
A6: 01.01 | B6: SERVIÇOS PRELIMINARES | H6: =G7+G12 -> 18665.827 | I6: =H6/$K$5 -> 0.023324916
A7: 01.01.001 | B7: LIMPEZA DE TERRENO | G7: =SUM(G8:G11) -> 11897.07 | I7: =G7/$K$5 -> 0.014866642
A8: 01.01.001.001 | B8: Limpeza manual de terreno com vegetação rasteira, incluindo roçagem e queima | C8: m2 | D8: 342 | E8: 5.55 | G8: 1898.1 | I8: =G8/$K$5 -> 0.0023718758
A9: 01.01.001.002 | B9: Destocamento de árvores de porte médio e raízes profundas, sem auxílio mecânico | C9: un | D9: 8.55 | E9: 275.47 | G9: 2355.27 | I9: =G9/$K$5 -> 0.0029431579
A10: 01.01.001.003 | B10: Coleta e carga manuais de entulho | C10: m3 | D10: 102.6 | E10: 22.24 | G10: 2281.82 | I10: =G10/$K$5 -> 0.0028513744
A11: 01.01.001.004 | B11: Transporte com caminhão basculante de 6 m³, em via urbana em revestimento primário (unidade: txkm). af_07/2020 | C11: txkm | D11: 2062.26 | E11: 2.6 | G11: 5361.88 | I11: =G11/$K$5 -> 0.0067002336
A12: 01.01.002 | B12: DEMOLIÇÃO DE EDIFICAÇÕES | G12: =SUM(G13:G18) -> 6768.757 | I12: =G12/$K$5 -> 0.0084582746
A13: 01.01.002.001 | B13: Demolição de alvenaria de bloco furado, de forma manual, sem reaproveitamento. af_09/2023 | C13: m3 | D13: 20 | E13: 68.57 | G13: 1371.4 | I13: =G13/$K$5 -> 0.0017137087
A14: 01.01.002.002 | B14: Demolição de lajes, em concreto armado, de forma mecanizada com martelete, sem reaproveitamento. af_09/2023 | C14: m3 | D14: 7.5 | E14: 99.37 | G14: 745.27 | I14: =G14/$K$5 -> 0.00093129334
A15: 01.01.002.003 | B15: Demolição de pilares e vigas em concreto armado, de forma mecanizada com martelete, sem reaproveitamento. af_09/2023 | C15: m3 | D15: 3.68 | E15: 213.38 | G15: 784.17 | I15: =G15/$K$5 -> 0.00097990298
A16: 01.01.002.004 | B16: Demolição de revestimento cerâmico, de forma mecanizada com martelete, sem reaproveitamento. af_09/2023 | C16: m2 | D16: 56 | E16: 8.06 | G16: 451.36 | I16: =G16/$K$5 -> 0.00056402185
A17: 01.01.002.005 | B17: Coleta e carga manuais de entulho | C17: m3 | D17: 56 | E17: 22.24 | G17: 1245.44 | I17: =G17/$K$5 -> 0.0015563084
A18: 01.01.002.006 | B18: Transporte com caminhão basculante de 6 m³, em via urbana em revestimento primário (unidade: txkm). af_07/2020 | C18: txkm | D18: 835.045 | E18: 2.6 | G18: =D18*E18 -> 2171.117 | I18: =G18/$K$5 -> 0.0027130393
A19: 01.02 | B19: ESTRUTURAS DE CONTENÇÃO | H19: =G20 -> 777170.5 | I19: =H19/$K$5 -> 0.97115638
A20: 01.02.001 | B20: MURO DE ARRIMO | G20: =SUM(G21:G34) -> 777170.5 | I20: =G20/$K$5 -> 0.97115638
A21: 01.02.001.001 | B21: Concretagem de pilares, fck = 25 mpa, com uso de bomba - lançamento, adensamento e acabamento. af_02/2022_ps | C21: m3 | D21: 118 | E21: 813.12 | G21: =D21*E21 -> 95948.16 | I21: =G21/$K$5 -> 0.11989733
A22: 01.02.001.002 | B22: Armação de cinta de alvenaria estrutural; diâmetro de 16,0 mm. af_09/2021 | C22: kg | D22: 2100.4831 | E22: 10.96 | G22: =D22*E22 -> 23021.295 | I22: =G22/$K$5 -> 0.028767532
A23: 01.02.001.003 | B23: Armação de verga e contraverga de alvenaria estrutural; diâmetro de 16,0 mm. af_09/2021 | C23: kg | D23: 4300 | E23: 12.25 | G23: =D23*E23 -> 52675 | I23: =G23/$K$5 -> 0.065822959
A24: 01.02.001.004 | B24: Armação vertical de alvenaria estrutural; diâmetro de 16,0 mm. af_09/2021 | C24: kg | D24: 4300 | E24: 11.21 | G24: =D24*E24 -> 48203 | I24: =G24/$K$5 -> 0.060234724
A25: 01.02.001.005 | B25: Reaterro manual de valas, com compactador de solos de percussão. af_08/2023 | C25: m3 | D25: 273.6 | E25: 31.86 | G25: 8716.9 | I25: =G25/$K$5 -> 0.010892684
A26: 01.02.001.006 | B26: Grauteamento de cinta intermediária ou de contraverga em alvenaria estrutural. af_09/2021 | C26: m3 | D26: 6.84 | E26: 1141.21 | G26: 7805.88 | I26: =G26/$K$5 -> 0.009754269
A27: 01.02.001.007 | B27: Grauteamento de cinta superior ou de verga em alvenaria estrutural. af_09/2021 | C27: m3 | D27: 6.84 | E27: 1270.69 | G27: 8691.52 | I27: =G27/$K$5 -> 0.010860969
A28: 01.02.001.008 | B28: Grauteamento vertical em alvenaria estrutural. af_09/2021 | C28: m3 | D28: 120 | E28: 1315.18 | G28: =D28*E28 -> 157821.6 | I28: =G28/$K$5 -> 0.19721471
A29: 01.02.001.009 | B29: Tubo pvc rigido soldavel, serie reforçada, p/esgoto e aguas pluviais, d= 100mm | C29: m | D29: 171 | E29: 57.44 | G29: 9822.24 | I29: =G29/$K$5 -> 0.012273923
A30: 01.02.001.010 | B30: Alvenaria de blocos de concreto estrutural 14x19x39 cm (espessura 14 cm), fbk = 14 mpa, utilizando colher de pedreiro. af_10/2022 | C30: m2 | D30: 342 | E30: 134.62 | G30: 46040.04 | I30: =G30/$K$5 -> 0.057531878
A31: 01.02.001.011 | B31: Escavação mecanizada para viga baldrame ou sapata corrida com mini-escavadeira (incluindo escavação para colocação de fôrmas). af_01/2024 | C31: m3 | D31: 273.6 | E31: 72.09 | G31: 19723.82 | I31: =G31/$K$5 -> 0.02464699
A32: 01.02.001.012 | B32: Fabricação, montagem e desmontagem de fôrma para sapata corrida, em madeira serrada, e=25 mm, 4 utilizações. af_01/2024 | C32: m2 | D32: 273.6 | E32: 97.43 | G32: 26656.85 | I32: =G32/$K$5 -> 0.033310541
A33: 01.02.001.013 | B33: Armação de bloco, sapata isolada, viga baldrame e sapata corrida utilizando aço ca-50 de 16 mm - montagem. af_01/2024 | C33: kg | D33: 4100 | E33: 14.14 | G33: =D33*E33 -> 57974 | I33: =G33/$K$5 -> 0.072444617
A34: 01.02.001.014 | B34: Concretagem de sapata corrida, fck 30 mpa, com uso de bomba - lançamento, adensamento e acabamento. af_01/2024 | C34: m3 | D34: 230 | E34: 930.74 | G34: =D34*E34 -> 214070.2 | I34: =G34/$K$5 -> 0.26750326
A35: 01.03 | B35: DRENAGEM DAS ESTRUTURAS DE CONTENÇÃO | H35: =G36 -> 4416.36 | I35: =H35/$K$5 -> 0.0055187068
A36: 01.03.001 | B36: CANALETA | G36: =G37 -> 4416.36 | I36: =G36/$K$5 -> 0.0055187068
A37: 01.03.001.001 | B37: Canaleta meia cana pré-moldada de concreto (d = 20 cm) - fornecimento e instalação. af_08/2021 | C37: m | D37: 114 | E37: 38.74 | G37: 4416.36 | I37: =G37/$K$5 -> 0.0055187068
A39: 2 | B39: Obras Complementares
A40: 02.01 | B40: DRENAGEM | H40: =G41+G43+G45 -> 475239.53 | I40: =H40/$K$40 -> 0.46295686 | K40: =SUM(H40:H59) -> 1026530.9 | L40: 1
A41: 02.01.001 | B41: CANALETA | G41: =G42 -> 78642.2 | I41: =G41/$K$40 -> 0.076609675
A42: 02.01.001.001 | B42: Canaleta meia cana pré-moldada de concreto (d = 20 cm) - fornecimento e instalação. af_08/2021 | C42: m | D42: 2030 | E42: 38.74 | G42: 78642.2 | I42: =G42/$K$40 -> 0.076609675
A43: 02.01.002 | B43: ESCADA HIDRÁULICA | G43: =G44 -> 58556.52 | I43: =G43/$K$40 -> 0.057043114
A44: 02.01.002.001 | B44: Escada hidráulica, largura até 1m, tipo descida d'água de corte ou aterro em degraus (dcd 02, 04 e dad 02), em concreto usinado, fck = 20 mpa, lançado com bomba, incluindo armação, materiais e fôrmas (3 utilizações). af_08/2022 | C44: m3 | D44: 27 | E44: 2168.76 | G44: 58556.52 | I44: =G44/$K$40 -> 0.057043114
A45: 02.01.003 | B45: REDE COLETORA PLUVIAL (REDE+PV) | G45: =SUM(G46:G47) -> 338040.81 | I45: =G45/$K$40 -> 0.32930407
A46: 02.01.003.001 | B46: Fornecimento e assentamento de tubo corrugado parede dupla PEAD, d= 300mm (12"), p/sistemas drenagem, Tigre-ADS N-12 ou similar | C46: m | D46: 1240.4634 | E46: 261.79 | G46: =D46*E46 -> 324740.92 | I46: =G46/$K$40 -> 0.31634792
A47: 02.01.003.002 | B47: Caixa de inspeção 0,30 x 0,30 x 0,40m | C47: un | D47: 66.77 | E47: 199.2 | G47: 13299.89 | I47: =G47/$K$40 -> 0.012956151
A48: 02.02 | B48: MOBILIDADE | H48: =G49+G51 -> 495930.39 | I48: =H48/$K$40 -> 0.48311296
A49: 02.02.001 | B49: VIELA (CAMINHO PAVIMENTADO/BECO) | G49: =G50 -> 31535.29 | I49: =G49/$K$40 -> 0.030720254
A50: 02.02.001.001 | B50: Execução de passeio (calçada) ou piso de concreto com concreto moldado in loco, feito em obra, acabamento convencional, não armado. af_08/2022 | C50: m3 | D50: 31.84 | E50: 990.43 | G50: 31535.29 | I50: =G50/$K$40 -> 0.030720254
A51: 02.02.002 | B51: ESCADA | G51: =G52+G53 -> 464395.1 | I51: =G51/$K$40 -> 0.45239271
A52: 02.02.002.001 | B52: Escada em concreto armado moldado in loco, fck 25 mpa, com 1 lance e laje plana, fôrma em chapa de madeira compensada resinada. af_11/2020_pa | C52: m3 | D52: 84.5 | E52: 4960 | G52: =D52*E52 -> 419120 | I52: =G52/$K$40 -> 0.40828775
A53: 02.02.002.002 | B53: Corrimão simples, diâmetro externo = 1 1/2", em aço galvanizado. af_04/2019_ps | C53: m | D53: 338 | E53: 133.95 | G53: 45275.1 | I53: =G53/$K$40 -> 0.044104955
A54: 02.03 | B54: ESGOTAMENTO SANITÁRIO | H54: =G55 -> 31269 | I54: =H54/$K$40 -> 0.030460846
A55: 02.03.001 | B55: REDE COLETORA DE 150 mm | G55: =G56 -> 31269 | I55: =G55/$K$40 -> 0.030460846
A56: 02.03.001.001 | B56: Tubo de pvc para rede coletora de esgoto de parede maciça, dn 150 mm, junta elástica - fornecimento e assentamento. af_01/2021 | C56: m | D56: 350 | E56: 89.34 | G56: 31269 | I56: =G56/$K$40 -> 0.030460846
A57: 02.04 | B57: RESÍDUOS SÓLIDOS URBANOS | H57: =G58 -> 24092 | I57: =H57/$K$40 -> 0.023469337
A58: 02.04.001 | B58: LIXEIRA 240 L | G58: =G59 -> 24092 | I58: =G58/$K$40 -> 0.023469337
A59: 02.04.001.001 | B59: Lixeira de Plástico de 240 L com Rodas | C59: un | D59: 38 | E59: 634 | G59: 24092 | I59: =G59/$K$40 -> 0.023469337
B61: Subtotal - Áreas de Risco | G61: =K5 -> 800252.69 | L61: 1
B62: Subtotal - Obras Complementares | G62: =K40 -> 1026530.9 | L62: 1
B63: Valor Total | G63: =G61+G62 -> 1826783.6

Sheet 06_Nova Esperança
A1: PMRR DE ILHÉUS
A3: Empreendimento: 000029 - Alto Nova Esperança (Bairro Esperança) | G3: VALOR TOTAL
A4: ITEM | B4: DESCRIÇÃO DO ITEM | C4: UNID | D4: QUANT | E4: PREÇO UNIT | G4: Valor Parcial | I4: Parcial (%) | K4: Soma | L4: (%)
A5: 1 | B5: Setor de Risco A1S1R3 (Contenções e Demolições) | K5: =SUM(H5:H37) -> 1071693.6 | L5: 1
A6: 01.01 | B6: SERVIÇOS PRELIMINARES | H6: =G7+G12 -> 22548.902 | I6: =H6/$K$5 -> 0.021040437
A7: 01.01.001 | B7: LIMPEZA DE TERRENO | G7: =SUM(G8:G11) -> 16071.48 | I7: =G7/$K$5 -> 0.014996339
A8: 01.01.001.001 | B8: Limpeza manual de terreno com vegetação rasteira, incluindo roçagem e queima | C8: m2 | D8: 462 | E8: 5.55 | G8: 2564.1 | I8: =G8/$K$5 -> 0.0023925682
A9: 01.01.001.002 | B9: Destocamento de árvores de porte médio e raízes profundas, sem auxílio mecânico | C9: un | D9: 11.55 | E9: 275.47 | G9: 3181.68 | I9: =G9/$K$5 -> 0.0029688336
A10: 01.01.001.003 | B10: Coleta e carga manuais de entulho | C10: m3 | D10: 138.6 | E10: 22.24 | G10: 3082.46 | I10: =G10/$K$5 -> 0.0028762512
A11: 01.01.001.004 | B11: Transporte com caminhão basculante de 6 m³, em via urbana em revestimento primário (unidade: txkm). af_07/2020 | C11: txkm | D11: 2785.86 | E11: 2.6 | G11: 7243.24 | I11: =G11/$K$5 -> 0.0067586855
A12: 01.01.002 | B12: DEMOLIÇÃO DE EDIFICAÇÕES | G12: =SUM(G13:G18) -> 6477.4218 | I12: =G12/$K$5 -> 0.0060440986
A13: 01.01.002.001 | B13: Demolição de alvenaria de bloco furado, de forma manual, sem reaproveitamento. af_09/2023 | C13: m3 | D13: 30 | E13: 68.57 | G13: =D13*E13 -> 2057.1 | I13: =G13/$K$5 -> 0.0019194852
A14: 01.01.002.002 | B14: Demolição de lajes, em concreto armado, de forma mecanizada com martelete, sem reaproveitamento. af_09/2023 | C14: m3 | D14: 10.05 | E14: 99.37 | G14: 998.67 | I14: =G14/$K$5 -> 0.0009318615
A15: 01.01.002.003 | B15: Demolição de pilares e vigas em concreto armado, de forma mecanizada com martelete, sem reaproveitamento. af_09/2023 | C15: m3 | D15: 3.51 | E15: 213.38 | G15: 748.96 | I15: =G15/$K$5 -> 0.00069885646
A16: 01.01.002.004 | B16: Demolição de revestimento cerâmico, de forma mecanizada com martelete, sem reaproveitamento. af_09/2023 | C16: m2 | D16: 53.6 | E16: 8.06 | G16: 432.02 | I16: =G16/$K$5 -> 0.00040311895
A17: 01.01.002.005 | B17: Coleta e carga manuais de entulho | C17: m3 | D17: 40 | E17: 22.24 | G17: =D17*E17 -> 889.6 | I17: =G17/$K$5 -> 0.000830088
A18: 01.01.002.006 | B18: Transporte com caminhão basculante de 6 m³, em via urbana em revestimento primário (unidade: txkm). af_07/2020 | C18: txkm | D18: 519.643 | E18: 2.6 | G18: =D18*E18 -> 1351.0718 | I18: =G18/$K$5 -> 0.0012606885
A19: 01.02 | B19: ESTRUTURAS DE CONTENÇÃO | H19: =G20 -> 1045425.7 | I19: =H19/$K$5 -> 0.97548932
A20: 01.02.001 | B20: MURO DE ARRIMO | G20: =SUM(G21:G34) -> 1045425.7 | I20: =G20/$K$5 -> 0.97548932
A21: 01.02.001.001 | B21: Concretagem de pilares, fck = 25 mpa, com uso de bomba - lançamento, adensamento e acabamento. af_02/2022_ps | C21: m3 | D21: 160 | E21: 813.12 | G21: =D21*E21 -> 130099.2 | I21: =G21/$K$5 -> 0.12139589
A22: 01.02.001.002 | B22: Armação de cinta de alvenaria estrutural; diâmetro de 16,0 mm. af_09/2021 | C22: kg | D22: 3600 | E22: 10.96 | G22: =D22*E22 -> 39456 | I22: =G22/$K$5 -> 0.036816493
A23: 01.02.001.003 | B23: Armação de verga e contraverga de alvenaria estrutural; diâmetro de 16,0 mm. af_09/2021 | C23: kg | D23: 5500 | E23: 12.25 | G23: =D23*E23 -> 67375 | I23: =G23/$K$5 -> 0.062867782
A24: 01.02.001.004 | B24: Armação vertical de alvenaria estrutural; diâmetro de 16,0 mm. af_09/2021 | C24: kg | D24: 5500 | E24: 11.21 | G24: =D24*E24 -> 61655 | I24: =G24/$K$5 -> 0.057530436
A25: 01.02.001.005 | B25: Reaterro manual de valas, com compactador de solos de percussão. af_08/2023 | C25: m3 | D25: 369.6 | E25: 31.86 | G25: =D25*E25 -> 11775.456 | I25: =G25/$K$5 -> 0.010987708
A26: 01.02.001.006 | B26: Grauteamento de cinta intermediária ou de contraverga em alvenaria estrutural. af_09/2021 | C26: m3 | D26: 9.24 | E26: 1141.21 | G26: =D26*E26 -> 10544.78 | I26: =G26/$K$5 -> 0.0098393612
A27: 01.02.001.007 | B27: Grauteamento de cinta superior ou de verga em alvenaria estrutural. af_09/2021 | C27: m3 | D27: 9.24 | E27: 1270.69 | G27: =D27*E27 -> 11741.176 | I27: =G27/$K$5 -> 0.010955721
A28: 01.02.001.008 | B28: Grauteamento vertical em alvenaria estrutural. af_09/2021 | C28: m3 | D28: 182 | E28: 1315.18 | G28: =D28*E28 -> 239362.76 | I28: =G28/$K$5 -> 0.22334999
A29: 01.02.001.009 | B29: Tubo pvc rigido soldavel, serie reforçada, p/esgoto e aguas pluviais, d= 100mm | C29: m | D29: 222.5845 | E29: 57.44 | G29: =D29*E29 -> 12785.254 | I29: =G29/$K$5 -> 0.011929952
A30: 01.02.001.010 | B30: Alvenaria de blocos de concreto estrutural 14x19x39 cm (espessura 14 cm), fbk = 14 mpa, utilizando colher de pedreiro. af_10/2022 | C30: m2 | D30: 462 | E30: 134.62 | G30: =D30*E30 -> 62194.44 | I30: =G30/$K$5 -> 0.058033789
A31: 01.02.001.011 | B31: Escavação mecanizada para viga baldrame ou sapata corrida com mini-escavadeira (incluindo escavação para colocação de fôrmas). af_01/2024 | C31: m3 | D31: 369.6 | E31: 72.09 | G31: =D31*E31 -> 26644.464 | I31: =G31/$K$5 -> 0.024862017
A32: 01.02.001.012 | B32: Fabricação, montagem e desmontagem de fôrma para sapata corrida, em madeira serrada, e=25 mm, 4 utilizações. af_01/2024 | C32: m2 | D32: 369.6 | E32: 97.43 | G32: =D32*E32 -> 36010.128 | I32: =G32/$K$5 -> 0.033601141
... A34: 01.02.001.014 | B34: Concretagem de sapata corrida, fck 30 mpa, com uso de bomba - lançamento, adensamento e acabamento. af_01/2024 | C34: m3 | D34: 300 | E34: 930.74 | G34: =D34*E34 -> 279222 | I34: =G34/$K$5 -> 0.26054275
A35: 01.03 | B35: DRENAGEM DAS ESTRUTURAS DE CONTENÇÃO | H35: =G36 -> 3719.04 | I35: =H35/$K$5 -> 0.0034702456
A36: 01.03.001 | B36: CANALETA | G36: =G37 -> 3719.04 | I36: =G36/$K$5 -> 0.0034702456
A37: 01.03.001.001 | B37: Canaleta meia cana pré-moldada de concreto (d = 20 cm) - fornecimento e instalação. af_08/2021 | C37: m | D37: 96 | E37: 38.74 | G37: 3719.04 | I37: =G37/$K$5 -> 0.0034702456
A39: 2 | B39: Obras Complementares | K39: =SUM(H40:H50) -> 212923.88 | L39: 1
A40: 02.01 | B40: DRENAGEM | H40: =G41+G43+G45 -> 207217.88 | I40: =H40/$K$39 -> 0.97320169
A41: 02.01.001 | B41: CANALETA | G41: =G42 -> 79992 | I41: =G41/$K$39 -> 0.37568356
A42: 02.01.001.001 | B42: Escavação manual de vala ou cava em material de 1ª categoria, profundidade até 1,50m | C42: m3 | D42: 1200 | E42: 66.66 | G42: =D42*E42 -> 79992 | I42: =G42/$K$39 -> 0.37568356
A43: 02.01.002 | B43: ESCADA HIDRÁULICA | G43: 26025.12 | I43: =G43/$K$39 -> 0.12222734
A44: 02.01.002.001 | B44: Escada hidráulica, largura até 1m, tipo descida d'água de corte ou aterro em degraus (dcd 02, 04 e dad 02), em concreto usinado, fck = 20 mpa, lançado com bomba, incluindo armação, materiais e fôrmas (3 utilizações). af_08/2022 | C44: m3 | D44: 12 | E44: 2168.76 | G44: 26025.12 | I44: =G44/$K$39 -> 0.12222734
A45: 02.01.003 | B45: REDE COLETORA PLUVIAL (REDE+PV) | G45: =G46+G47 -> 101200.76 | I45: =G45/$K$39 -> 0.47529079
A46: 02.01.003.001 | B46: Fornecimento e assentamento de tubo corrugado parede dupla PEAD, d= 300mm (12"), p/sistemas drenagem, Tigre-ADS N-12 ou similar | C46: m | D46: 374.2835 | E46: 261.79 | G46: =D46*E46 -> 97983.677 | I46: =G46/$K$39 -> 0.46018173
A47: 02.01.003.002 | B47: Caixa de inspeção 0,30 x 0,30 x 0,40m | C47: un | D47: 16.15 | E47: 199.2 | G47: =D47*E47 -> 3217.08 | I47: =G47/$K$39 -> 0.015109062
A48: 02.02 | B48: RESÍDUOS SÓLIDOS URBANOS | H48: =G49 -> 5706 | I48: =H48/$K$39 -> 0.02679831
A49: 02.02.001 | B49: LIXEIRA 240 L | G49: 5706 | I49: =G50/$K$39 -> 0.02679831
A50: 02.02.001.001 | B50: Lixeira de Plástico de 240 L com Rodas | C50: un | D50: 9 | E50: 634 | G50: 5706 | I50: =G51/$K$39 -> 0
B52: Subtotal - Áreas de Risco | G52: =K5 -> 1071693.6 | L52: 1
B53: Subtotal - Obras Complementares | G53: =K39 -> 212923.88 | L53: 1
B54: Valor Total | G54: =G52+G53 -> 1284617.5

Sheet 07_Floresta
A1: PMRR DE ILHÉUS
A3: Empreendimento: 000060 - Alto da Floresta (Bairro Malhado) | G3: VALOR TOTAL
A4: ITEM | B4: DESCRIÇÃO DO ITEM | C4: UNID | D4: QUANT | E4: PREÇO UNIT | G4: Valor Parcial | I4: Parcial (%) | K4: Soma | L4: (%)
A5: 1 | B5: Setor de Risco A4S2R3 (Contenções e Demolições) | K5: =SUM(H5:H14) -> 504489.82 | L5: =K5/$G$62 -> 0.12753314
A6: 01.01 | B6: SERVIÇOS PRELIMINARES | H6: =G7 -> 17695.42 | I6: =H6/$K$5 -> 0.035075871
A7: 01.01.001 | B7: LIMPEZA DE TERRENO | G7: =SUM(G8:G11) -> 17695.42 | I7: =G7/$K$5 -> 0.035075871
A8: 01.01.001.001 | B8: Limpeza manual de terreno com vegetação rasteira, incluindo roçagem e queima | C8: m2 | D8: 645 | E8: 4.38 | G8: 2825.1 | I8: =G8/$K$5 -> 0.0055999148
A9: 01.01.001.002 | B9: Destocamento de árvores de porte médio e raízes profundas, sem auxílio mecânico | C9: un | D9: 16.13 | E9: 217.25 | G9: 3503.16 | I9: =G9/$K$5 -> 0.0069439657
A10: 01.01.001.003 | B10: Coleta e carga manuais de entulho | C10: m3 | D10: 193.5 | E10: 17.54 | G10: 3393.99 | I10: =G10/$K$5 -> 0.0067275689
A11: 01.01.001.004 | B11: Transporte com caminhão basculante de 6 m³, em via urbana em revestimento primário (unidade: txkm). af_07/2020 | C11: txkm | D11: 3889.35 | E11: 2.05 | G11: 7973.17 | I11: =G11/$K$5 -> 0.015804422
A12: 01.02 | B12: ESTRUTURAS DE CONTENÇÃO | H12: =G13 -> 486794.4 | I12: =H12/$K$5 -> 0.96492413
A13: 01.02.001 | B13: SOLO GRAMPEADO | G13: =G14 -> 486794.4 | I13: =G13/$K$5 -> 0.96492413
A14: 01.02.001.001 | B14: Solo Grampeado para controlede erosão com malha hexagonal de dupla torção, revestimento em PVC e com resistência de puncionamento de 105 KN e resistência à tração de 89 KN/m. Associada a geomanta tridimensional verde. | C14: m2 | D14: 645 | E14: 754.72 | G14: 486794.4 | I14: =G14/$K$5 -> 0.96492413
A16: 2 | B16: Setor de Risco A4S5R3 (Contenções e Demolições) | K16: =SUM(H17:H45) -> 2693265.8 | L16: =K16/$G$62 -> 0.6808475
A17: 02.01 | B17: SERVIÇOS PRELIMINARES | H17: =G18 -> 89190.37 | I17: =H17/$K$16 -> 0.033116067
A18: 02.01.001 | B18: LIMPEZA DE TERRENO | G18: =SUM(G19:G22) -> 89190.37 | I18: =G18/$K$16 -> 0.033116067
A19: 02.01.001.001 | B19: Limpeza manual de terreno com vegetação rasteira, incluindo roçagem e queima | C19: m2 | D19: 3251 | E19: 4.38 | G19: 14239.38 | I19: =G19/$K$16 -> 0.0052870311
A20: 02.01.001.002 | B20: Destocamento de árvores de porte médio e raízes profundas, sem auxílio mecânico | C20: un | D20: 81.28 | E20: 217.25 | G20: 17656.99 | I20: =G20/$K$16 -> 0.0065559775
A21: 02.01.001.003 | B21: Coleta e carga manuais de entulho | C21: m3 | D21: 975.3 | E21: 17.54 | G21: 17106.76 | I21: =G21/$K$16 -> 0.006351679
A22: 02.01.001.004 | B22: Transporte com caminhão basculante de 6 m³, em via urbana em revestimento primário (unidade: txkm). af_07/2020 | C22: txkm | D22: 19603.53 | E22: 2.05 | G22: 40187.24 | I22: =G22/$K$16 -> 0.014921379
A23: 02.02 | B23: ESTRUTURAS DE CONTENÇÃO | H23: =G24+G26 -> 2580640.7 | I23: =H23/$K$16 -> 0.9581827
A24: 02.02.001 | B24: SOLO GRAMPEADO | G24: =G25 -> 2387934.1 | I24: =G24/$K$16 -> 0.88663142
A25: 02.02.001.001 | B25: Solo Grampeado para controlede erosão com malha hexagonal de dupla torção, revestimento em PVC e com resistência de puncionamento de 105 KN e resistência à tração de 89 KN/m. Associada a geomanta tridimensional verde. | C25: m2 | D25: 3164 | E25: 754.72 | G25: 2387934.1 | I25: =G25/$K$16 -> 0.88663142
A26: 02.02.002 | B26: MURO DE ARRIMO | G26: =SUM(G27:G40) -> 192706.63 | I26: =G26/$K$16 -> 0.071551285
A27: 02.02.002.001 | B27: Concretagem de pilares, fck = 25 mpa, com uso de bomba - lançamento, adensamento e acabamento. af_02/2022_ps | C27: m3 | D27: 34.8 | E27: 641.26 | G27: 22315.85 | I27: =G27/$K$16 -> 0.0082857956
A28: 02.02.002.002 | B28: Armação de cinta de alvenaria estrutural; diâmetro de 16,0 mm. af_09/2021 | C28: kg | D28: 870 | E28: 8.64 | G28: 7516.8 | I28: =G28/$K$16 -> 0.0027909611
A29: 02.02.002.003 | B29: Armação de verga e contraverga de alvenaria estrutural; diâmetro de 16,0 mm. af_09/2021 | C29: kg | D29: 1566 | E29: 9.66 | G29: 15127.56 | I29: =G29/$K$16 -> 0.0056168091
A30: 02.02.002.004 | B30: Armação vertical de alvenaria estrutural; diâmetro de 16,0 mm. af_09/2021 | C30: kg | D30: 1566 | E30: 8.84 | G30: 13843.44 | I30: =G30/$K$16 -> 0.00514002
A31: 02.02.002.005 | B31: Reaterro manual de valas, com compactador de solos de percussão. af_08/2023 | C31: m3 | D31: 69.6 | E31: 25.13 | G31: 1749.05 | I31: =G31/$K$16 -> 0.00064941603
A32: 02.02.002.006 | B32: Grauteamento de cinta intermediária ou de contraverga em alvenaria estrutural. af_09/2021 | C32: m3 | D32: 1.74 | E32: 900.01 | G32: 1566.02 | I32: =G32/$K$16 -> 0.00058145765
A33: 02.02.002.007 | B33: Grauteamento de cinta superior ou de verga em alvenaria estrutural. af_09/2021 | C33: m3 | D33: 1.74 | E33: 1002.12 | G33: 1743.69 | I33: =G33/$K$16 -> 0.00064742588
A34: 02.02.002.008 | B34: Grauteamento vertical em alvenaria estrutural. af_09/2021 | C34: m3 | D34: 43.5 | E34: 1037.21 | G34: 45118.64 | I34: =G34/$K$16 -> 0.01675239
A35: 02.02.002.009 | B35: Tubo pvc rigido soldavel, serie reforçada, p/esgoto e aguas pluviais, d= 100mm | C35: m | D35: 43.5 | E35: 45.3 | G35: 1970.55 | I35: =G35/$K$16 -> 0.00073165819
A36: 02.02.002.010 | B36: Alvenaria de blocos de concreto estrutural 14x19x39 cm (espessura 14 cm), fbk = 14 mpa, utilizando colher de pedreiro. af_10/2022 | C36: m2 | D36: 87 | E36: 106.17 | G36: 9236.79 | I36: =G36/$K$16 -> 0.0034295872
A37: 02.02.002.011 | B37: Escavação mecanizada para viga baldrame ou sapata corrida com mini-escavadeira (incluindo escavação para colocação de fôrmas). af_01/2024 | C37: m3 | D37: 69.6 | E37: 56.85 | G37: 3956.76 | I37: =G37/$K$16 -> 0.0014691309
A38: 02.02.002.012 | B38: Fabricação, montagem e desmontagem de fôrma para sapata corrida, em madeira serrada, e=25 mm, 4 utilizações. af_01/2024 | C38: m2 | D38: 69.6 | E38: 76.84 | G38: 5348.06 | I38: =G38/$K$16 -> 0.0019857156
... A40: 02.02.002.014 | B40: Concretagem de sapata corrida, fck 30 mpa, com uso de bomba - lançamento, adensamento e acabamento. af_01/2024 | C40: m3 | D40: 69.6 | E40: 734.02 | G40: 51087.79 | I40: =G40/$K$16 -> 0.018968714
A41: 02.03 | B41: DRENAGEM DAS ESTRUTURAS DE CONTENÇÃO | H41: =G42+G44 -> 23434.73 | I41: =H41/$K$16 -> 0.0087012318
A42: 02.03.001 | B42: CANALETA | G42: =G43 -> 10264.8 | I42: =G42/$K$16 -> 0.0038112837
A43: 02.03.001.001 | B43: Canaleta meia cana pré-moldada de concreto (d = 20 cm) - fornecimento e instalação. af_08/2021 | C43: m | D43: 336 | E43: 30.55 | G43: 10264.8 | I43: =G43/$K$16 -> 0.0038112837
A44: 02.03.002 | B44: ESCADA HIDRÁULICA | G44: =G45 -> 13169.93 | I44: =G44/$K$16 -> 0.0048899481
A45: 02.03.002.001 | B45: Escada hidráulica, largura até 1m, tipo descida d'água de corte ou aterro em degraus (dcd 02, 04 e dad 02), em concreto usinado, fck = 20 mpa, lançado com bomba, incluindo armação, materiais e fôrmas (3 utilizações). af_08/2022 | C45: m3 | D45: 7.7 | E45: 1710.38 | G45: 13169.93 | I45: =G45/$K$16 -> 0.0048899481
A47: 3 | B47: Setor de Risco A4S6R4 (Contenções e Demolições) | K47: =SUM(H48:H60) -> 757999.24 | L47: =K47/$G$62 -> 0.19161937
A48: 03.01 | B48: SERVIÇOS PRELIMINARES | H48: =G49 -> 26447.11 | I48: =H48/$K$47 -> 0.034890681
A49: 03.01.001 | B49: LIMPEZA DE TERRENO | G49: =SUM(G50:G53) -> 26447.11 | I49: =G49/$K$47 -> 0.034890681
A50: 03.01.001.001 | B50: Limpeza manual de terreno com vegetação rasteira, incluindo roçagem e queima | C50: m2 | D50: 964 | E50: 4.38 | G50: 4222.32 | I50: =G50/$K$47 -> 0.0055703486
A51: 03.01.001.002 | B51: Destocamento de árvores de porte médio e raízes profundas, sem auxílio mecânico | C51: un | D51: 24.1 | E51: 217.25 | G51: 5235.73 | I51: =G51/$K$47 -> 0.0069073024
A52: 03.01.001.003 | B52: Coleta e carga manuais de entulho | C52: m3 | D52: 289.2 | E52: 17.54 | G52: 5072.57 | I52: =G52/$K$47 -> 0.0066920516
A53: 03.01.001.004 | B53: Transporte com caminhão basculante de 6 m³, em via urbana em revestimento primário (unidade: txkm). af_07/2020 | C53: txkm | D53: 5812.92 | E53: 2.05 | G53: 11916.49 | I53: =G53/$K$47 -> 0.015720979
A54: 03.02 | B54: ESTRUTURAS DE CONTENÇÃO | H54: =G55 -> 727550.08 | I54: =H54/$K$47 -> 0.95982956
A55: 03.02.001 | B55: SOLO GRAMPEADO | G55: =G56 -> 727550.08 | I55: =G55/$K$47 -> 0.95982956
A56: 03.02.001.001 | B56: Solo Grampeado para controlede erosão com malha hexagonal de dupla torção, revestimento em PVC e com resistência de puncionamento de 105 KN e resistência à tração de 89 KN/m. Associada a geomanta tridimensional verde. | C56: m2 | D56: 964 | E56: 754.72 | G56: 727550.08 | I56: =G56/$K$47 -> 0.95982956
A57: 03.03 | B57: DRENAGEM DAS ESTRUTURAS DE CONTENÇÃO | H57: =G58 -> 4002.05 | I57: =H57/$K$47 -> 0.0052797546
A58: 03.03.001 | B58: CANALETA | G58: =G59 -> 4002.05 | I58: =G58/$K$47 -> 0.0052797546
A59: 03.03.001.001 | B59: Canaleta meia cana pré-moldada de concreto (d = 20 cm) - fornecimento e instalação. af_08/2021 | C59: m | D59: 131 | E59: 30.55 | G59: 4002.05 | I59: =G59/$K$47 -> 0.0052797546
B60: TOTAL DO ORÇAMENTO
B62: Subtotal - Áreas de Risco | G62: =SUM(K5:K60) -> 3955754.9 | L62: 1
B63: Subtotal - Obras Complementares | G63: 0 | L63: 1
B64: Valor Total | G64: =G62+G63 -> 3955754.9

Sheet 08_Coqueiro
A1: PMRR DE ILHÉUS
A3: Empreendimento: 000059 - Alto do Coqueiro (Bairro Malhado) | G3: VALOR TOTAL
A4: ITEM | B4: DESCRIÇÃO DO ITEM | C4: UNID | D4: QUANT | E4: PREÇO UNIT | G4: Valor Parcial | I4: Parcial (%) | K4: Soma | L4: (%)
A5: 1 | B5: Setor de Risco A2S1R3 (Contenções e Demolições) | K5: =SUM(H5:H39) -> 995770.49 | L5: =K5/$G$135 -> 0.18641407
A6: 01.01 | B6: SERVIÇOS PRELIMINARES | H6: =G7 -> 28587 | I6: =H6/$K$5 -> 0.028708423
A7: 01.01.001 | B7: LIMPEZA DE TERRENO | G7: =SUM(G8:G11) -> 28587 | I7: =H7/$K$5 -> 0
A8: 01.01.001.001 | B8: Limpeza manual de terreno com vegetação rasteira, incluindo roçagem e queima | C8: m2 | D8: 1042 | E8: 4.38 | G8: 4563.96 | I8: =H8/$K$5 -> 0
A9: 01.01.001.002 | B9: Destocamento de árvores de porte médio e raízes profundas, sem auxílio mecânico | C9: un | D9: 26.05 | E9: 217.25 | G9: 5659.36 | I9: =H9/$K$5 -> 0
A10: 01.01.001.003 | B10: Coleta e carga manuais de entulho | C10: m3 | D10: 312.6 | E10: 17.54 | G10: 5483 | I10: =H10/$K$5 -> 0
A11: 01.01.001.004 | B11: Transporte com caminhão basculante de 6 m³, em via urbana em revestimento primário (unidade: txkm). af_07/2020 | C11: txkm | D11: 6283.26 | E11: 2.05 | G11: 12880.68 | I11: =H11/$K$5 -> 0
A12: 01.02 | B12: ESTRUTURAS DE CONTENÇÃO | H12: =G13+G15 -> 945093.17 | I12: =H12/$K$5 -> 0.94910743
A13: 01.02.001 | B13: SOLO GRAMPEADO | G13: =G14 -> 735097.28 | I13: =H13/$K$5 -> 0
A14: 01.02.001.001 | B14: Solo Grampeado para controlede erosão com malha hexagonal de dupla torção, revestimento em PVC e com resistência de puncionamento de 105 KN e resistência à tração de 89 KN/m. Associada a geomanta tridimensional verde. | C14: m2 | D14: 974 | E14: 754.72 | G14: 735097.28 | I14: =H14/$K$5 -> 0
A15: 01.02.002 | B15: CORTINA ATIRANTADA | G15: =G16+G22 -> 209995.89 | I15: =H15/$K$5 -> 0
A16: 01.02.002.001 | B16: FUNDAÇÃO - ESTACAS | G16: =SUM(G17:G21) -> 96853.66 | I16: =H16/$K$5 -> 0
A17: 01.02.002.001.001 | B17: Perfuratriz com torre metálica para execução de estaca hélice contínua, profundidade máxima de 30 m, diâmetro máximo de 800 mm, potência instalada de 268 hp, mesa rotativa com torque máximo de 170 knm - depreciação. af_06/2015 | C17: h | D17: 115.6 | E17: 238.49 | G17: 27569.44 | I17: =H17/$K$5 -> 0
A18: 01.02.002.001.002 | B18: Execução de estaca hélice contínua monitorada Ø 500mm, concreto fck=40Mpa, inclusive aço, bombeamento; exclusive mobilização e desmobilização de equipamento e bate-estacas | C18: m | D18: 204 | E18: 337.82 | G18: 68915.28 | I18: =H18/$K$5 -> 0
A19: 01.02.002.001.003 | B19: Transporte horizontal com carrinho de mão, de sacos de 50 kg (unidade: kgxkm). af_07/2019 | C19: kgxkm | D19: 391 | E19: 0.76 | G19: 297.16 | I19: =H19/$K$5 -> 0
A20: 01.02.002.001.004 | B20: Carga manual de material de 1ª categoria | C20: m3 | D20: 6.8 | E20: 10.49 | G20: 71.33 | I20: =H20/$K$5 -> 0
A21: 01.02.002.001.005 | B21: Transporte com caminhão basculante de 14 m³, em via urbana pavimentada, adicional para dmt excedente a 30 km (unidade: m3xkm). af_07/2020 | C21: m3xkm | D21: 0.54 | E21: 0.83 | G21: 0.45 | I21: =H21/$K$5 -> 0
A22: 01.02.002.002 | B22: ESTRUTURA - CORTINA | G22: =SUM(G23:G34) -> 113142.23 | I22: =H22/$K$5 -> 0
A23: 01.02.002.002.001 | B23: Fabricação, montagem e desmontagem de fôrma para cortina de contenção, em chapa de madeira compensada plastificada, e = 18 mm, 10 utilizações. af_11/2024 | C23: m2 | D23: 34 | E23: 42.99 | G23: 1461.66 | I23: =H23/$K$5 -> 0
A24: 01.02.002.002.002 | B24: Armação de cortina de contenção em concreto armado, com aço ca-50 de 10 mm - montagem. af_11/2024 | C24: kg | D24: 2040 | E24: 13.5 | G24: 27540 | I24: =H24/$K$5 -> 0
A25: 01.02.002.002.003 | B25: Armação de cortina de contenção em concreto armado, com aço ca-50 de 16 mm - montagem. af_11/2024 | C25: kg | D25: 3400 | E25: 10.35 | G25: 35190 | I25: =H25/$K$5 -> 0
A26: 01.02.002.002.004 | B26: Concretagem de cortina de contenção, através de bomba - lançamento, adensamento e acabamento. af_11/2024 | C26: m3 | D26: 51 | E26: 648.51 | G26: 33074.01 | I26: =H26/$K$5 -> 0
A27: 01.02.002.002.005 | B27: Junta de dilatação (altura total do pavimento) com preenchimento parcial em isopor h=15cm e preenchimento do complemento com mastique de poliuretano seção 2x2cm, MBT, Basf, ou similar, para pavimentos em concreto | C27: m | D27: 10.2 | E27: 73.32 | G27: 747.86 | I27: =H27/$K$5 -> 0
A28: 01.02.002.002.006 | B28: Execução de perfuração para tirante, comprimento maior ou igual a 6 m e menor que 14 m, com diâmetro de furo de 100 mm executado com haste e tubos de revestimento utilizando perfuratriz sobre esteira. af_11/2023 | C28: m | D28: 23.8 | E28: 100.93 | G28: 2402.13 | I28: =H28/$K$5 -> 0
A29: 01.02.002.002.007 | B29: Tirante Permanente de Aço Protendido D = 32 mm - SICRO 5605882 | C29: m | D29: 17 | E29: 381.67 | G29: 6488.39 | I29: =H29/$K$5 -> 0
A30: 01.02.002.002.008 | B30: Conjunto cilindro e bomba hidráulica para protensão de monobarras para tirantes, esforço máximo de 30 toneladas - materiais na operação. af_05/2023 | C30: h | D30: 5.1 | E30: 7.22 | G30: 36.82 | I30: =H30/$K$5 -> 0
A31: 01.02.002.002.009 | B31: Execução de proteção da cabeça do tirante com uso de fôrmas metálicas, 50 utilizações, e concreto fck =15 mpa. af_11/2023 | C31: un | D31: 51 | E31: 36.69 | G31: 1871.19 | I31: =H31/$K$5 -> 0
A32: 01.02.002.002.010 | B32: Dreno barbacã, dn 100 mm, com material drenante. af_07/2021 | C32: un | D32: 36.38 | E32: 29.6 | G32: 1076.85 | I32: =H32/$K$5 -> 0
A33: 01.02.002.002.011 | B33: Lastro com material granular (pedra britada n.1 e pedra britada n.2), aplicado em pisos ou lajes sobre solo, espessura de *10 cm*. af_01/2024 | C33: m3 | D33: 6.8 | E33: 218.93 | G33: 1488.72 | I33: =H33/$K$5 -> 0
A34: 01.02.002.002.012 | B34: Impermeabilização - Fornecimento e aplicação de manta geotéxtil RT-21, resistencia a tração=21 kN/m (antigo Bidim OP-40 ou similar) em colchões drenantes | C34: m2 | D34: 68 | E34: 25.95 | G34: 1764.6 | I34: =H34/$K$5 -> 0
A35: 01.03 | B35: DRENAGEM DAS ESTRUTURAS DE CONTENÇÃO | H35: =G36+G38 -> 22090.32 | I35: =H35/$K$5 -> 0.022184148
A36: 01.03.001 | B36: CANALETA | G36: 8065.2 | I36: =H36/$K$5 -> 0
A37: 01.03.001.001 | B37: Canaleta meia cana pré-moldada de concreto (d = 20 cm) - fornecimento e instalação. af_08/2021 | C37: m | D37: 264 | E37: 30.55 | G37: 8065.2 | I37: =H37/$K$5 -> 0
A38: 01.03.002 | B38: ESCADA HIDRÁULICA | G38: 14025.12 | I38: =H38/$K$5 -> 0
A39: 01.03.002.001 | B39: Escada hidráulica, largura até 1m, tipo descida d'água de corte ou aterro em degraus (dcd 02, 04 e dad 02), em concreto usinado, fck = 20 mpa, lançado com bomba, incluindo armação, materiais e fôrmas (3 utilizações). af_08/2022 | C39: m3 | D39: 8.2 | E39: 1710.38 | G39: 14025.12 | I39: =H39/$K$5 -> 0
A41: 2 | B41: Setor de Risco A3S2R3 (Contenções e Demolições) | K41: =SUM(H41:H55) -> 3858154.4 | L41: =K41/$G$135 -> 0.72226911
A42: 02.01 | B42: SERVIÇOS PRELIMINARES | H42: =G43 -> 134155.93 | I42: =H42/$K$41 -> 0.034772048
A43: 02.01.001 | B43: LIMPEZA DE TERRENO | G43: =SUM(G44:G47) -> 134155.93 | I43: =H43/$K$41 -> 0
A44: 02.01.001.001 | B44: Limpeza manual de terreno com vegetação rasteira, incluindo roçagem e queima | C44: m2 | D44: 4890 | E44: 4.38 | G44: 21418.2 | I44: =H44/$K$41 -> 0
A45: 02.01.001.002 | B45: Destocamento de árvores de porte médio e raízes profundas, sem auxílio mecânico | C45: un | D45: 122.25 | E45: 217.25 | G45: 26558.81 | I45: =H45/$K$41 -> 0
A46: 02.01.001.003 | B46: Coleta e carga manuais de entulho | C46: m3 | D46: 1467 | E46: 17.54 | G46: 25731.18 | I46: =H46/$K$41 -> 0
A47: 02.01.001.004 | B47: Transporte com caminhão basculante de 6 m³, em via urbana em revestimento primário (unidade: txkm). af_07/2020 | C47: txkm | D47: 29486.7 | E47: 2.05 | G47: 60447.74 | I47: =H47/$K$41 -> 0
A48: 02.02 | B48: ESTRUTURAS DE CONTENÇÃO | H48: =G49 -> 3690580.8 | I48: =H48/$K$41 -> 0.95656637
A49: 02.02.001 | B49: SOLO GRAMPEADO | G49: =G50 -> 3690580.8 | I49: =H49/$K$41 -> 0
A50: 02.02.001.001 | B50: Solo Grampeado para controlede erosão com malha hexagonal de dupla torção, revestimento em PVC e com resistência de puncionamento de 105 KN e resistência à tração de 89 KN/m. Associada a geomanta tridimensional verde. | C50: m2 | D50: 4890 | E50: 754.72 | G50: 3690580.8 | I50: =H50/$K$41 -> 0
A51: 02.03 | B51: DRENAGEM DAS ESTRUTURAS DE CONTENÇÃO | H51: =G52+G54 -> 33417.71 | I51: =H51/$K$41 -> 0.0086615791
A52: 02.03.001 | B52: CANALETA | G52: 17169.1 | I52: =H52/$K$41 -> 0
A53: 02.03.001.001 | B53: Canaleta meia cana pré-moldada de concreto (d = 20 cm) - fornecimento e instalação. af_08/2021 | C53: m | D53: 562 | E53: 30.55 | G53: 17169.1 | I53: =H53/$K$41 -> 0
A54: 02.03.002 | B54: ESCADA HIDRÁULICA | G54: 16248.61 | I54: =H54/$K$41 -> 0
A55: 02.03.002.001 | B55: Escada hidráulica, largura até 1m, tipo descida d'água de corte ou aterro em degraus (dcd 02, 04 e dad 02), em concreto usinado, fck = 20 mpa, lançado com bomba, incluindo armação, materiais e fôrmas (3 utilizações). af_08/2022 | C55: m3 | D55: 9.5 | E55: 1710.38 | G55: 16248.61 | I55: =H55/$K$41 -> 0
A57: 3 | B57: Setor de Risco A5S1R3 (Contenções e Demolições) | K57: =SUM(H57:H71) -> 34360.77 | L57: =K57/$G$135 -> 0.0064325374
A58: 03.01 | B58: SERVIÇOS PRELIMINARES | H58: =G59 -> 5212.6 | I58: =H58/$K$57 -> 0.15170207
A59: 03.01.001 | B59: LIMPEZA DE TERRENO | G59: =SUM(G60:G63) -> 5212.6 | I59: =G59/$K$57 -> 0.15170207
A60: 03.01.001.001 | B60: Limpeza manual de terreno com vegetação rasteira, incluindo roçagem e queima | C60: m2 | D60: 190 | E60: 4.38 | G60: 832.2 | I60: =G60/$K$57 -> 0.024219481
A61: 03.01.001.002 | B61: Destocamento de árvores de porte médio e raízes profundas, sem auxílio mecânico | C61: un | D61: 4.75 | E61: 217.25 | G61: 1031.94 | I61: =G61/$K$57 -> 0.030032505
A62: 03.01.001.003 | B62: Coleta e carga manuais de entulho | C62: m3 | D62: 57 | E62: 17.54 | G62: 999.78 | I62: =G62/$K$57 -> 0.029096554
A63: 03.01.001.004 | B63: Transporte com caminhão basculante de 6 m³, em via urbana em revestimento primário (unidade: txkm). af_07/2020 | C63: txkm | D63: 1145.7 | E63: 2.05 | G63: 2348.68 | I63: =G63/$K$57 -> 0.068353532
A64: 03.02 | B64: ESTRUTURAS DE CONTENÇÃO | H64: =G65 -> 28628.82 | I64: =H64/$K$57 -> 0.83318331
A65: 03.02.001 | B65: RETALUDAMENTO / RECONSTRUÇÃO EM CORTE/ATERRO | G65: =SUM(G66:G68) -> 28628.82 | I65: =G65/$K$57 -> 0.83318331
A66: 03.02.001.001 | B66: Escavação manual de vala ou cava em material de 1ª categoria, profundidade entre 1,50 e 3,00m | C66: m3 | D66: 342 | E66: 78.85 | G66: 26966.7 | I66: =G66/$K$57 -> 0.7848107
A67: 03.02.001.002 | B67: Carga manual de material de 1ª categoria | C67: m3 | D67: 57 | E67: 10.49 | G67: 597.93 | I67: =G67/$K$57 -> 0.017401531
A68: 03.02.001.003 | B68: Compactação manual com compactador a percussão sapinho, a 95% do pn | C68: m3 | D68: 57 | E68: 18.67 | G68: 1064.19 | I68: =G68/$K$57 -> 0.030971075
A69: 03.03 | B69: DRENAGEM DAS ESTRUTURAS DE CONTENÇÃO | H69: =G70 -> 519.35 | I69: =H69/$K$57 -> 0.015114621
A70: 03.03.001 | B70: CANALETA | G70: 519.35 | I70: =G70/$K$57 -> 0.015114621
A71: 03.03.001.001 | B71: Canaleta meia cana pré-moldada de concreto (d = 20 cm) - fornecimento e instalação. af_08/2021 | C71: m | D71: 17 | E71: 30.55 | G71: 519.35 | I71: =G71/$K$57 -> 0.015114621
A73: 4 | B73: Setor de Risco A6S1R4 (Contenções e Demolições) | K73: =SUM(H74:H91) -> 453427.49 | L73: =K73/$G$135 -> 0.084884282
A74: 04.01 | B74: SERVIÇOS PRELIMINARES | H74: =G75 -> 17366.2 | I74: =H74/$K$73 -> 0.038299839
A75: 04.01.001 | B75: LIMPEZA DE TERRENO | G75: =SUM(G76:G79) -> 17366.2 | I75: =G75/$K$73 -> 0.038299839
A76: 04.01.001.001 | B76: Limpeza manual de terreno com vegetação rasteira, incluindo roçagem e queima | C76: m2 | D76: 633 | E76: 4.38 | G76: 2772.54 | I76: =G76/$K$73 -> 0.0061146271
A77: 04.01.001.002 | B77: Destocamento de árvores de porte médio e raízes profundas, sem auxílio mecânico | C77: un | D77: 15.83 | E77: 217.25 | G77: 3437.98 | I77: =G77/$K$73 -> 0.0075822046
A78: 04.01.001.003 | B78: Coleta e carga manuais de entulho | C78: m3 | D78: 189.9 | E78: 17.54 | G78: 3330.85 | I78: =G78/$K$73 -> 0.0073459375
A79: 04.01.001.004 | B79: Transporte com caminhão basculante de 6 m³, em via urbana em revestimento primário (unidade: txkm). af_07/2020 | C79: txkm | D79: 3816.99 | E79: 2.05 | G79: 7824.83 | I79: =G79/$K$73 -> 0.01725707
A80: 04.02 | B80: ESTRUTURAS DE CONTENÇÃO | H80: =G81+G83 -> 428810.36 | I80: =H80/$K$73 -> 0.94570878
A81: 04.02.001 | B81: SOLO GRAMPEADO | G81: =G82 -> 416605.44 | I81: =G81/$K$73 -> 0.91879176
A82: 04.02.001.001 | B82: Solo Grampeado para controlede erosão com malha hexagonal de dupla torção, revestimento em PVC e com resistência de puncionamento de 105 KN e resistência à tração de 89 KN/m. Associada a geomanta tridimensional verde. | C82: m2 | D82: 552 | E82: 754.72 | G82: 416605.44 | I82: =G82/$K$73 -> 0.91879176
A83: 04.02.002 | B83: RETALUDAMENTO / RECONSTRUÇÃO EM CORTE/ATERRO | G83: =SUM(G84:G86) -> 12204.92 | I83: =G83/$K$73 -> 0.026917027
A84: 04.02.002.001 | B84: Escavação manual de vala ou cava em material de 1ª categoria, profundidade entre 1,50 e 3,00m | C84: m3 | D84: 145.8 | E84: 78.85 | G84: 11496.33 | I84: =G84/$K$73 -> 0.025354285
A85: 04.02.002.002 | B85: Carga manual de material de 1ª categoria | C85: m3 | D85: 24.3 | E85: 10.49 | G85: 254.91 | I85: =G85/$K$73 -> 0.00056218471
A86: 04.02.002.003 | B86: Compactação manual com compactador a percussão sapinho, a 95% do pn | C86: m3 | D86: 24.3 | E86: 18.67 | G86: 453.68 | I86: =G86/$K$73 -> 0.0010005569
A87: 04.03 | B87: DRENAGEM DAS ESTRUTURAS DE CONTENÇÃO | H87: =G88+G90 -> 7250.93 | I87: =H87/$K$73 -> 0.015991377
A88: 04.03.001 | B88: CANALETA | G88: 580.45 | I88: =G88/$K$73 -> 0.0012801385
A89: 04.03.001.001 | B89: Canaleta meia cana pré-moldada de concreto (d = 20 cm) - fornecimento e instalação. af_08/2021 | C89: m | D89: 19 | E89: 30.55 | G89: 580.45 | I89: =G89/$K$73 -> 0.0012801385
A90: 04.03.002 | B90: ESCADA HIDRÁULICA | G90: 6670.48 | I90: =G90/$K$73 -> 0.014711239
A91: 04.03.002.001 | B91: Escada hidráulica, largura até 1m, tipo descida d'água de corte ou aterro em degraus (dcd 02, 04 e dad 02), em concreto usinado, fck = 20 mpa, lançado com bomba, incluindo armação, materiais e fôrmas (3 utilizações). af_08/2022 | C91: m3 | D91: 3.9 | E91: 1710.38 | G91: 6670.48 | I91: =G91/$K$73 -> 0.014711239
A93: 5 | B93: Obras Complementares | K93: =SUM(H93:H133) -> 5806534.8 | L93: 1
A94: 05.01 | B94: SERVIÇOS PRELIMINARES | H94: =G95 -> 139725.19 | I94: =H94/$K$93 -> 0.024063438
A95: 05.01.001 | B95: LIMPEZA DE TERRENO | G95: =SUM(G96:G99) -> 139725.19 | I95: =G95/$K$93 -> 0.024063438
A96: 05.01.001.001 | B96: Limpeza manual de terreno com vegetação rasteira, incluindo roçagem e queima | C96: m2 | D96: 5093 | E96: 4.38 | G96: 22307.34 | I96: =G96/$K$93 -> 0.0038417646
A97: 05.01.001.002 | B97: Destocamento de árvores de porte médio e raízes profundas, sem auxílio mecânico | C97: un | D97: 127.33 | E97: 217.25 | G97: 27661.36 | I97: =G97/$K$93 -> 0.0047638326
A98: 05.01.001.003 | B98: Coleta e carga manuais de entulho | C98: m3 | D98: 1527.9 | E98: 17.54 | G98: 26799.37 | I98: =G98/$K$93 -> 0.0046153809
A99: 05.01.001.004 | B99: Transporte com caminhão basculante de 6 m³, em via urbana em revestimento primário (unidade: txkm). af_07/2020 | C99: txkm | D99: 30710.79 | E99: 2.05 | G99: 62957.12 | I99: =G99/$K$93 -> 0.01084246
A100: 05.02 | B100: DRENAGEM | H100: =G101+G103 -> 487554.32 | I100: =H100/$K$93 -> 0.083966485
A101: 05.02.001 | B101: CANALETA | G101: =G102 -> 92749.8 | I101: =G101/$K$93 -> 0.015973348
A102: 05.02.001.001 | B102: Canaleta meia cana pré-moldada de concreto (d = 20 cm) - fornecimento e instalação. af_08/2021 | C102: m | D102: 3036 | E102: 30.55 | G102: 92749.8 | I102: =G102/$K$93 -> 0.015973348
A103: 05.02.002 | B103: REDE COLETORA PLUVIAL (REDE+PV) | G103: =G104+G105 -> 394804.52 | I103: =G103/$K$93 -> 0.067993138
A104: 05.02.002.001 | B104: Fornecimento e assentamento de tubo corrugado parede dupla PEAD, d= 300mm (12"), p/sistemas drenagem, Tigre-ADS N-12 ou similar | C104: m | D104: 1865 | E104: 206.46 | G104: 385047.9 | I104: =G104/$K$93 -> 0.066312855
A105: 05.02.002.002 | B105: Caixa de inspeção 0,30 x 0,30 x 0,40m | C105: un | D105: 62.1 | E105: 157.1 | G105: 9756.62 | I105: =G105/$K$93 -> 0.0016802827
...

Sheet 09_Legião
A1: PMRR DE ILHÉUS
A3: Empreendimento: 000062 - Alto da Legião (Bairro Malhado) | G3: VALOR TOTAL
A4: ITEM | B4: DESCRIÇÃO DO ITEM | C4: UNID | D4: QUANT | E4: PREÇO UNIT | G4: Valor Parcial | I4: Parcial (%) | K4: Soma | L4: (%)
A5: 1 | B5: Setor de risco A4S3R3 (Contenções e Demolições) | K5: =SUM(H5:H30) -> 74337.03 | L5: =K5/$G$88 -> 0.039673322
A6: 01.01 | B6: SERVIÇOS PRELIMINARES | H6: =G7 -> 905.35 | I6: =H6/$K$5 -> 0.012178991
A7: 01.01.001 | B7: LIMPEZA DE TERRENO | G7: =SUM(G8:G11) -> 905.35 | I7: =G7/$K$5 -> 0.012178991
A8: 01.01.001.001 | B8: Limpeza manual de terreno com vegetação rasteira, incluindo roçagem e queima | C8: m2 | D8: 33 | E8: 4.38 | G8: 144.54 | I8: =G8/$K$5 -> 0.0019443876
A9: 01.01.001.002 | B9: Destocamento de árvores de porte médio e raízes profundas, sem auxílio mecânico | C9: un | D9: 0.83 | E9: 217.25 | G9: 179.23 | I9: =G9/$K$5 -> 0.002411046
A10: 01.01.001.003 | B10: Coleta e carga manuais de entulho | C10: m3 | D10: 9.9 | E10: 17.54 | G10: 173.65 | I10: =G10/$K$5 -> 0.0023359825
A11: 01.01.001.004 | B11: Transporte com caminhão basculante de 6 m³, em via urbana em revestimento primário (unidade: txkm). af_07/2020 | C11: txkm | D11: 198.99 | E11: 2.05 | G11: 407.93 | I11: =G11/$K$5 -> 0.0054875746
A12: 01.02 | B12: ESTRUTURAS DE CONTENÇÃO | H12: =G13 -> 73095.63 | I12: =H12/$K$5 -> 0.98330038
A13: 01.02.001 | B13: MURO DE ARRIMO | G13: =SUM(G14:G27) -> 73095.63 | I13: =G13/$K$5 -> 0.98330038
A14: 01.02.001.001 | B14: Concretagem de pilares, fck = 25 mpa, com uso de bomba - lançamento, adensamento e acabamento. af_02/2022_ps | C14: m3 | D14: 13.2 | E14: 641.26 | G14: 8464.63 | I14: =G14/$K$5 -> 0.11386828
A15: 01.02.001.002 | B15: Armação de cinta de alvenaria estrutural; diâmetro de 16,0 mm. af_09/2021 | C15: kg | D15: 330 | E15: 8.64 | G15: 2851.2 | I15: =G15/$K$5 -> 0.038355043
A16: 01.02.001.003 | B16: Armação de verga e contraverga de alvenaria estrutural; diâmetro de 16,0 mm. af_09/2021 | C16: kg | D16: 594 | E16: 9.66 | G16: 5738.04 | I16: =G16/$K$5 -> 0.077189525
A17: 01.02.001.004 | B17: Armação vertical de alvenaria estrutural; diâmetro de 16,0 mm. af_09/2021 | C17: kg | D17: 594 | E17: 8.84 | G17: 5250.96 | I17: =G17/$K$5 -> 0.070637205
A18: 01.02.001.005 | B18: Reaterro manual de valas, com compactador de solos de percussão. af_08/2023 | C18: m3 | D18: 26.4 | E18: 25.13 | G18: 663.43 | I18: =G18/$K$5 -> 0.0089246234
A19: 01.02.001.006 | B19: Grauteamento de cinta intermediária ou de contraverga em alvenaria estrutural. af_09/2021 | C19: m3 | D19: 0.66 | E19: 900.01 | G19: 594.01 | I19: =G19/$K$5 -> 0.0079907685
A20: 01.02.001.007 | B20: Grauteamento de cinta superior ou de verga em alvenaria estrutural. af_09/2021 | C20: m3 | D20: 0.66 | E20: 1002.12 | G20: 661.4 | I20: =G20/$K$5 -> 0.0088973154
A21: 01.02.001.008 | B21: Grauteamento vertical em alvenaria estrutural. af_09/2021 | C21: m3 | D21: 16.5 | E21: 1037.21 | G21: 17113.97 | I21: =G21/$K$5 -> 0.23022133
A22: 01.02.001.009 | B22: Tubo pvc rigido soldavel, serie reforçada, p/esgoto e aguas pluviais, d= 100mm | C22: m | D22: 16.5 | E22: 45.3 | G22: 747.45 | I22: =G22/$K$5 -> 0.010054881
A23: 01.02.001.010 | B23: Alvenaria de blocos de concreto estrutural 14x19x39 cm (espessura 14 cm), fbk = 14 mpa, utilizando colher de pedreiro. af_10/2022 | C23: m2 | D23: 33 | E23: 106.17 | G23: 3503.61 | I23: =G23/$K$5 -> 0.047131423
A24: 01.02.001.011 | B24: Escavação mecanizada para viga baldrame ou sapata corrida com mini-escavadeira (incluindo escavação para colocação de fôrmas). af_01/2024 | C24: m3 | D24: 26.4 | E24: 56.85 | G24: 1500.84 | I24: =G24/$K$5 -> 0.020189669
A25: 01.02.001.012 | B25: Fabricação, montagem e desmontagem de fôrma para sapata corrida, em madeira serrada, e=25 mm, 4 utilizações. af_01/2024 | C25: m2 | D25: 26.4 | E25: 76.84 | G25: 2028.58 | I25: =G25/$K$5 -> 0.027288957
... A27: 01.02.001.014 | B27: Concretagem de sapata corrida, fck 30 mpa, com uso de bomba - lançamento, adensamento e acabamento. af_01/2024 | C27: m3 | D27: 26.4 | E27: 734.02 | G27: 19378.13 | I27: =G27/$K$5 -> 0.26067937
A28: 01.03 | B28: DRENAGEM DAS ESTRUTURAS DE CONTENÇÃO | H28: =G29 -> 336.05 | I28: =H28/$K$5 -> 0.0045206272
A29: 01.03.001 | B29: CANALETA | G29: =G30 -> 336.05 | I29: =G29/$K$5 -> 0.0045206272
A30: 01.03.001.001 | B30: Canaleta meia cana pré-moldada de concreto (d = 20 cm) - fornecimento e instalação. af_08/2021 | C30: m | D30: 11 | E30: 30.55 | G30: 336.05 | I30: =G30/$K$5 -> 0.0045206272
A32: 2 | B32: Setor de risco A4S5R3 (Contenções e Demolições) | K32: =SUM(H32:H50) -> 767384.04 | L32: =K32/$G$88 -> 0.40954924
A33: 02.01 | B33: SERVIÇOS PRELIMINARES | H33: =G34 -> 73931.22 | I33: =H33/$K$32 -> 0.096341879
A34: 02.01.001 | B34: LIMPEZA DE TERRENO | G34: =SUM(G35:G38) -> 73931.22 | I34: =G34/$K$32 -> 0.096341879
A35: 02.01.001.001 | B35: Limpeza manual de terreno com vegetação rasteira, incluindo roçagem e queima | C35: m2 | D35: 2695 | E35: 4.38 | G35: 11804.1 | I35: =G35/$K$32 -> 0.015382259
A36: 02.01.001.002 | B36: Destocamento de árvores de porte médio e raízes profundas, sem auxílio mecânico | C36: un | D36: 67.35 | E36: 217.25 | G36: 14631.79 | I36: =G36/$K$32 -> 0.019067102
A37: 02.01.001.003 | B37: Coleta e carga manuais de entulho | C37: m3 | D37: 808.5 | E37: 17.54 | G37: 14181.09 | I37: =G37/$K$32 -> 0.018479782
A38: 02.01.001.004 | B38: Transporte com caminhão basculante de 6 m³, em via urbana em revestimento primário (unidade: txkm). af_07/2020 | C38: txkm | D38: 16250.85 | E38: 2.05 | G38: 33314.24 | I38: =G38/$K$32 -> 0.043412735
A39: 02.02 | B39: ESTRUTURAS DE CONTENÇÃO | H39: =G40+G42 -> 680916.32 | I39: =H39/$K$32 -> 0.88732145
A40: 02.02.001 | B40: SOLO GRAMPEADO | G40: =G41 -> 343397.6 | I40: =G40/$K$32 -> 0.44749119
A41: 02.02.001.001 | B41: Solo Grampeado para controlede erosão com malha hexagonal de dupla torção, revestimento em PVC e com resistência de puncionamento de 105 KN e resistência à tração de 89 KN/m. Associada a geomanta tridimensional verde. | C41: m2 | D41: 455 | E41: 754.72 | G41: 343397.6 | I41: =G41/$K$32 -> 0.44749119
A42: 02.02.002 | B42: RETALUDAMENTO / RECONSTRUÇÃO EM CORTE/ATERRO | G42: =SUM(G43:G45) -> 337518.72 | I42: =G42/$K$32 -> 0.43983026
A43: 02.02.002.001 | B43: Escavação manual de vala ou cava em material de 1ª categoria, profundidade entre 1,50 e 3,00m | C43: m3 | D43: 4032 | E43: 78.85 | G43: 317923.2 | I43: =G43/$K$32 -> 0.41429478
A44: 02.02.002.002 | B44: Carga manual de material de 1ª categoria | C44: m3 | D44: 672 | E44: 10.49 | G44: 7049.28 | I44: =G44/$K$32 -> 0.0091861176
A45: 02.02.002.003 | B45: Compactação manual com compactador a percussão sapinho, a 95% do pn | C45: m3 | D45: 672 | E45: 18.67 | G45: 12546.24 | I45: =G45/$K$32 -> 0.016349363
A46: 02.03 | B46: DRENAGEM DAS ESTRUTURAS DE CONTENÇÃO | H46: =G47+G49 -> 12536.5 | I46: =H46/$K$32 -> 0.01633667
A47: 02.03.001 | B47: CANALETA | G47: =G48 -> 7576.4 | I47: =G47/$K$32 -> 0.0098730226
A48: 02.03.001.001 | B48: Canaleta meia cana pré-moldada de concreto (d = 20 cm) - fornecimento e instalação. af_08/2021 | C48: m | D48: 248 | E48: 30.55 | G48: 7576.4 | I48: =G48/$K$32 -> 0.0098730226
A49: 02.03.002 | B49: ESCADA HIDRÁULICA | G49: =G50 -> 4960.1 | I49: =G49/$K$32 -> 0.0064636476
A50: 02.03.002.001 | B50: Escada hidráulica, largura até 1m, tipo descida d'água de corte ou aterro em degraus (dcd 02, 04 e dad 02), em concreto usinado, fck = 20 mpa, lançado com bomba, incluindo armação, materiais e fôrmas (3 utilizações). af_08/2022 | C50: m3 | D50: 2.9 | E50: 1710.38 | G50: 4960.1 | I50: =G50/$K$32 -> 0.0064636476
A52: 3 | B52: Setor de risco A4S7R3 (Contenções e Demolições) | K52: =SUM(H52:H85) -> 1032007.3 | L52: =K52/$G$88 -> 0.55077744
A53: 03.01 | B53: ESCADA HIDRÁULICA | H53: =G54 -> 46254.99 | I53: =H53/$K$52 -> 0.044820409
A54: 03.01.001 | B54: LIMPEZA DE TERRENO | G54: =SUM(G55:G58) -> 46254.99 | I54: =G54/$K$52 -> 0.044820409
A55: 03.01.001.001 | B55: Limpeza manual de terreno com vegetação rasteira, incluindo roçagem e queima | C55: m2 | D55: 1686 | E55: 4.38 | G55: 7384.68 | I55: =G55/$K$52 -> 0.0071556469
A56: 03.01.001.002 | B56: Destocamento de árvores de porte médio e raízes profundas, sem auxílio mecânico | C56: un | D56: 42.15 | E56: 217.25 | G56: 9157.09 | I56: =G56/$K$52 -> 0.0088730863
A57: 03.01.001.003 | B57: Coleta e carga manuais de entulho | C57: m3 | D57: 505.8 | E57: 17.54 | G57: 8871.73 | I57: =G57/$K$52 -> 0.0085965766
A58: 03.01.001.004 | B58: Transporte com caminhão basculante de 6 m³, em via urbana em revestimento primário (unidade: txkm). af_07/2020 | C58: txkm | D58: 10166.58 | E58: 2.05 | G58: 20841.49 | I58: =G58/$K$52 -> 0.020195099
A59: 03.02 | B59: ESTRUTURAS DE CONTENÇÃO | H59: =G60+G62+G77 -> 972952.72 | I59: =H59/$K$52 -> 0.94277696
A60: 03.02.001 | B60: SOLO GRAMPEADO | G60: =G61 -> 727720.36 | I60: =G60/$K$52 -> 0.70515039
A61: 03.02.001.001 | B61: Solo Grampeado para controlede erosão com malha hexagonal de dupla torção, revestimento em PVC e com resistência de puncionamento de 105 KN e resistência à tração de 89 KN/m. Associada a geomanta tridimensional verde. | C61: m2 | D61: 964.22562 | E61: 754.72 | G61: =D61*E61 -> 727720.36 | I61: =G61/$K$52 -> 0.70515039
A62: 03.02.002 | B62: MURO DE ARRIMO | G62: =SUM(G63:G76) -> 166126.41 | I62: =G62/$K$52 -> 0.16097406
A63: 03.02.002.001 | B63: Concretagem de pilares, fck = 25 mpa, com uso de bomba - lançamento, adensamento e acabamento. af_02/2022_ps | C63: m3 | D63: 30 | E63: 641.26 | G63: 19237.8 | I63: =G63/$K$52 -> 0.018641147
A64: 03.02.002.002 | B64: Armação de cinta de alvenaria estrutural; diâmetro de 16,0 mm. af_09/2021 | C64: kg | D64: 750 | E64: 8.64 | G64: 6480 | I64: =G64/$K$52 -> 0.0062790252
A65: 03.02.002.003 | B65: Armação de verga e contraverga de alvenaria estrutural; diâmetro de 16,0 mm. af_09/2021 | C65: kg | D65: 1350 | E65: 9.66 | G65: 13041 | I65: =G65/$K$52 -> 0.012636538
A66: 03.02.002.004 | B66: Armação vertical de alvenaria estrutural; diâmetro de 16,0 mm. af_09/2021 | C66: kg | D66: 1350 | E66: 8.84 | G66: 11934 | I66: =G66/$K$52 -> 0.011563871
A67: 03.02.002.005 | B67: Reaterro manual de valas, com compactador de solos de percussão. af_08/2023 | C67: m3 | D67: 60 | E67: 25.13 | G67: 1507.8 | I67: =G67/$K$52 -> 0.0014610361
A68: 03.02.002.006 | B68: Grauteamento de cinta intermediária ou de contraverga em alvenaria estrutural. af_09/2021 | C68: m3 | D68: 1.5 | E68: 900.01 | G68: 1350.02 | I68: =G68/$K$52 -> 0.0013081496
A69: 03.02.002.007 | B69: Grauteamento de cinta superior ou de verga em alvenaria estrutural. af_09/2021 | C69: m3 | D69: 1.5 | E69: 1002.12 | G69: 1503.18 | I69: =G69/$K$52 -> 0.0014565594
A70: 03.02.002.008 | B70: Grauteamento vertical em alvenaria estrutural. af_09/2021 | C70: m3 | D70: 37.5 | E70: 1037.21 | G70: 38895.38 | I70: =G70/$K$52 -> 0.037689054
A71: 03.02.002.009 | B71: Tubo pvc rigido soldavel, serie reforçada, p/esgoto e aguas pluviais, d= 100mm | C71: m | D71: 37.5 | E71: 45.3 | G71: 1698.75 | I71: =G71/$K$52 -> 0.0016460639
A72: 03.02.002.010 | B72: Alvenaria de blocos de concreto estrutural 14x19x39 cm (espessura 14 cm), fbk = 14 mpa, utilizando colher de pedreiro. af_10/2022 | C72: m2 | D72: 75 | E72: 106.17 | G72: 7962.75 | I72: =G72/$K$52 -> 0.0077157883
A73: 03.02.002.011 | B73: Escavação mecanizada para viga baldrame ou sapata corrida com mini-escavadeira (incluindo escavação para colocação de fôrmas). af_01/2024 | C73: m3 | D73: 60 | E73: 56.85 | G73: 3411 | I73: =G73/$K$52 -> 0.0033052091
A74: 03.02.002.012 | B74: Fabricação, montagem e desmontagem de fôrma para sapata corrida, em madeira serrada, e=25 mm, 4 utilizações. af_01/2024 | C74: m2 | D74: 60 | E74: 76.84 | G74: 4610.4 | I74: =G74/$K$52 -> 0.0044674102
... A76: 03.02.002.014 | B76: Concretagem de sapata corrida, fck 30 mpa, com uso de bomba - lançamento, adensamento e acabamento. af_01/2024 | C76: m3 | D76: 60 | E76: 734.02 | G76: 44041.2 | I76: =G76/$K$52 -> 0.042675279
A77: 03.02.003 | B77: RETALUDAMENTO / RECONSTRUÇÃO EM CORTE/ATERRO | G77: =SUM(G78:G80) -> 79105.95 | I77: =G77/$K$52 -> 0.076652509
A78: 03.02.003.001 | B78: Escavação manual de vala ou cava em material de 1ª categoria, profundidade entre 1,50 e 3,00m | C78: m3 | D78: 945 | E78: 78.85 | G78: 74513.25 | I78: =G78/$K$52 -> 0.07220225
A79: 03.02.003.002 | B79: Carga manual de material de 1ª categoria | C79: m3 | D79: 157.5 | E79: 10.49 | G79: 1652.17 | I79: =G79/$K$52 -> 0.0016009286
A80: 03.02.003.003 | B80: Compactação manual com compactador a percussão sapinho, a 95% do pn | C80: m3 | D80: 157.5 | E80: 18.67 | G80: 2940.53 | I80: =G80/$K$52 -> 0.0028493306
A81: 03.03 | B81: DRENAGEM DAS ESTRUTURAS DE CONTENÇÃO | H81: =G82+G84 -> 12799.61 | I81: =H81/$K$52 -> 0.012402635
A82: 03.03.001 | B82: CANALETA | G82: =G83 -> 9378.85 | I82: =G82/$K$52 -> 0.0090879685
A83: 03.03.001.001 | B83: Canaleta meia cana pré-moldada de concreto (d = 20 cm) - fornecimento e instalação. af_08/2021 | C83: m | D83: 307 | E83: 30.55 | G83: 9378.85 | I83: =G83/$K$52 -> 0.0090879685
A84: 03.03.002 | B84: ESCADA HIDRÁULICA | G84: =G85 -> 3420.76 | I84: =G84/$K$52 -> 0.0033146664
A85: 03.03.002.001 | B85: Escada hidráulica, largura até 1m, tipo descida d'água de corte ou aterro em degraus (dcd 02, 04 e dad 02), em concreto usinado, fck = 20 mpa, lançado com bomba, incluindo armação, materiais e fôrmas (3 utilizações). af_08/2022 | C85: m3 | D85: 2 | E85: 1710.38 | G85: 3420.76 | I85: =G85/$K$52 -> 0.0033146664
B86: TOTAL DO ORÇAMENTO
B88: Subtotal - Áreas de Risco | G88: =SUM(K5:K86) -> 1873728.4 | L88: 1
B89: Subtotal - Obras Complementares | G89: 0 | L89: 1
B90: Valor Total | G90: =G88+G89 -> 1873728.4

Sheet 10_Amparo
A1: PMRR DE ILHÉUS
A3: Empreendimento: 000061 - Alto do Amparo (Bairro Malhado) | G3: VALOR TOTAL
A4: ITEM | B4: DESCRIÇÃO DO ITEM | C4: UNID | D4: QUANT | E4: PREÇO UNIT | G4: Valor Parcial | I4: Parcial (%) | K4: Soma | L4: (%)
A5: 1 | B5: Setor de Risco A2S1R3 (Contenções e Demolições) | K5: =SUM(H5:H19) -> 901859.2 | L5: =K5/$G$133 -> 0.22923039
A6: 01.01 | B6: SERVIÇOS PRELIMINARES | H6: =G7 -> 138024.23 | I6: =H6/$K$5 -> 0.1530441
A7: 01.01.001 | B7: LIMPEZA DE TERRENO | G7: =SUM(G8:G11) -> 138024.23 | I7: =G7/$K$5 -> 0.1530441
A8: 01.01.001.001 | B8: Limpeza manual de terreno com vegetação rasteira, incluindo roçagem e queima | C8: m2 | D8: 5031 | E8: 4.38 | G8: 22035.78 | I8: =G8/$K$5 -> 0.024433725
A9: 01.01.001.002 | B9: Destocamento de árvores de porte médio e raízes profundas, sem auxílio mecânico | C9: un | D9: 125.78 | E9: 217.25 | G9: 27324.62 | I9: =G9/$K$5 -> 0.0302981
A10: 01.01.001.003 | B10: Coleta e carga manuais de entulho | C10: m3 | D10: 1509.3 | E10: 17.54 | G10: 26473.12 | I10: =G10/$K$5 -> 0.029353939
A11: 01.01.001.004 | B11: Transporte com caminhão basculante de 6 m³, em via urbana em revestimento primário (unidade: txkm). af_07/2020 | C11: txkm | D11: 30336.93 | E11: 2.05 | G11: 62190.71 | I11: =G11/$K$5 -> 0.068958336
A12: 01.02 | B12: ESTRUTURAS DE CONTENÇÃO | H12: =G13 -> 758061.02 | I12: =H12/$K$5 -> 0.84055363
A13: 01.02.001 | B13: RETALUDAMENTO / RECONSTRUÇÃO EM CORTE/ATERRO | G13: 758061.02 | I13: =G13/$K$5 -> 0.84055363
A14: 01.02.001.001 | B14: Escavação manual de vala ou cava em material de 1ª categoria, profundidade entre 1,50 e 3,00m | C14: m3 | D14: 9055.8 | E14: 78.85 | G14: 714049.83 | I14: =G14/$K$5 -> 0.79175311
A15: 01.02.001.002 | B15: Carga manual de material de 1ª categoria | C15: m3 | D15: 1509.3 | E15: 10.49 | G15: 15832.56 | I15: =G15/$K$5 -> 0.017555468
A16: 01.02.001.003 | B16: Compactação manual com compactador a percussão sapinho, a 95% do pn | C16: m3 | D16: 1509.3 | E16: 18.67 | G16: 28178.63 | I16: =G16/$K$5 -> 0.031245044
A17: 01.03 | B17: DRENAGEM DAS ESTRUTURAS DE CONTENÇÃO | H17: =G18 -> 5773.95 | I17: =H17/$K$5 -> 0.0064022743
A18: 01.03.001 | B18: CANALETA | G18: =G19 -> 5773.95 | I18: =G18/$K$5 -> 0.0064022743
A19: 01.03.001.001 | B19: Canaleta meia cana pré-moldada de concreto (d = 20 cm) - fornecimento e instalação. af_08/2021 | C19: m | D19: 189 | E19: 30.55 | G19: 5773.95 | I19: =G19/$K$5 -> 0.0064022743
A21: 2 | B21: Setor de Risco A3S3R4 (Contenções e Demolições) | K21: =SUM(H22:H35) -> 116492.07 | L21: =K21/$G$133 -> 0.029609414
A22: 02.01 | B22: SERVIÇOS PRELIMINARES | H22: =G23 -> 17585.67 | I22: =H22/$K$21 -> 0.15096023
A23: 02.01.001 | B23: LIMPEZA DE TERRENO | G23: =SUM(G24:G27) -> 17585.67 | I23: =G23/$K$21 -> 0.15096023
A24: 02.01.001.001 | B24: Limpeza manual de terreno com vegetação rasteira, incluindo roçagem e queima | C24: m2 | D24: 641 | E24: 4.38 | G24: 2807.58 | I24: =G24/$K$21 -> 0.02410104
A25: 02.01.001.002 | B25: Destocamento de árvores de porte médio e raízes profundas, sem auxílio mecânico | C25: un | D25: 16.03 | E25: 217.25 | G25: 3481.43 | I25: =G25/$K$21 -> 0.029885554
A26: 02.01.001.003 | B26: Coleta e carga manuais de entulho | C26: m3 | D26: 192.3 | E26: 17.54 | G26: 3372.94 | I26: =G26/$K$21 -> 0.028954246
A27: 02.01.001.004 | B27: Transporte com caminhão basculante de 6 m³, em via urbana em revestimento primário (unidade: txkm). af_07/2020 | C27: txkm | D27: 3865.23 | E27: 2.05 | G27: 7923.72 | I27: =G27/$K$21 -> 0.068019394
A28: 02.02 | B28: ESTRUTURAS DE CONTENÇÃO | H28: =G29 -> 96584.6 | I28: =H28/$K$21 -> 0.8291088
A29: 02.02.001 | B29: RETALUDAMENTO / RECONSTRUÇÃO EM CORTE/ATERRO | G29: =SUM(G30:G32) -> 96584.6 | I29: =G29/$K$21 -> 0.8291088
A30: 02.02.001.001 | B30: Escavação manual de vala ou cava em material de 1ª categoria, profundidade entre 1,50 e 3,00m | C30: m3 | D30: 1153.8 | E30: 78.85 | G30: 90977.13 | I30: =G30/$K$21 -> 0.78097273
A31: 02.02.001.002 | B31: Carga manual de material de 1ª categoria | C31: m3 | D31: 192.3 | E31: 10.49 | G31: 2017.23 | I31: =G31/$K$21 -> 0.017316458
A32: 02.02.001.003 | B32: Compactação manual com compactador a percussão sapinho, a 95% do pn | C32: m3 | D32: 192.3 | E32: 18.67 | G32: 3590.24 | I32: =G32/$K$21 -> 0.030819609
A33: 02.03 | B33: DRENAGEM DAS ESTRUTURAS DE CONTENÇÃO | H33: =G34 -> 2321.8 | I33: =H33/$K$21 -> 0.01993097
A34: 02.03.001 | B34: CANALETA | G34: =G35 -> 2321.8 | I34: =G34/$K$21 -> 0.01993097
A35: 02.03.001.001 | B35: Canaleta meia cana pré-moldada de concreto (d = 20 cm) - fornecimento e instalação. af_08/2021 | C35: m | D35: 76 | E35: 30.55 | G35: 2321.8 | I35: =G35/$K$21 -> 0.01993097
A37: 3 | B37: Setor de Risco A3S5R3 (Contenções e Demolições) | K37: =SUM(H37:H51) -> 1154361.5 | L37: =K37/$G$133 -> 0.29341025
A38: 03.01 | B38: SERVIÇOS PRELIMINARES | H38: =G39 -> 40246.77 | I38: =H38/$K$37 -> 0.034864963
A39: 03.01.001 | B39: LIMPEZA DE TERRENO | G39: =SUM(G40:G43) -> 40246.77 | I39: =G39/$K$37 -> 0.034864963
A40: 03.01.001.001 | B40: Limpeza manual de terreno com vegetação rasteira, incluindo roçagem e queima | C40: m2 | D40: 1467 | E40: 4.38 | G40: 6425.46 | I40: =G40/$K$37 -> 0.0055662461
A41: 03.01.001.002 | B41: Destocamento de árvores de porte médio e raízes profundas, sem auxílio mecânico | C41: un | D41: 36.68 | E41: 217.25 | G41: 7967.64 | I41: =G41/$K$37 -> 0.0069022054
A42: 03.01.001.003 | B42: Coleta e carga manuais de entulho | C42: m3 | D42: 440.1 | E42: 17.54 | G42: 7719.35 | I42: =G42/$K$37 -> 0.0066871168
A43: 03.01.001.004 | B43: Transporte com caminhão basculante de 6 m³, em via urbana em revestimento primário (unidade: txkm). af_07/2020 | C43: txkm | D43: 8846.01 | E43: 2.05 | G43: 18134.32 | I43: =G43/$K$37 -> 0.015709395
A44: 03.02 | B44: ESTRUTURAS DE CONTENÇÃO | H44: =G45 -> 1107174.2 | I44: =H44/$K$37 -> 0.95912266
A45: 03.02.001 | B45: SOLO GRAMPEADO | G45: =G46 -> 1107174.2 | I45: =G46/$K$37 -> 0.95912266
A46: 03.02.001.001 | B46: Solo Grampeado para controlede erosão com malha hexagonal de dupla torção, revestimento em PVC e com resistência de puncionamento de 105 KN e resistência à tração de 89 KN/m. Associada a geomanta tridimensional verde. | C46: m2 | D46: 1467 | E46: 754.72 | G46: =D46*E46 -> 1107174.2 | I46: =G47/$K$37 -> 0
A47: 03.03 | B47: DRENAGEM DAS ESTRUTURAS DE CONTENÇÃO | H47: =G48+G50 -> 6940.46 | I47: =H47/$K$37 -> 0.0060123802
A48: 03.03.001 | B48: CANALETA | G48: =G49 -> 4888 | I48: =G48/$K$37 -> 0.0042343756
A49: 03.03.001.001 | B49: Canaleta meia cana pré-moldada de concreto (d = 20 cm) - fornecimento e instalação. af_08/2021 | C49: m | D49: 160 | E49: 30.55 | G49: 4888 | I49: =G49/$K$37 -> 0.0042343756
A50: 03.03.002 | B50: ESCADA HIDRÁULICA | G50: =G51 -> 2052.46 | I50: =G50/$K$37 -> 0.0017780046
A51: 03.03.002.001 | B51: Escada hidráulica, largura até 1m, tipo descida d'água de corte ou aterro em degraus (dcd 02, 04 e dad 02), em concreto usinado, fck = 20 mpa, lançado com bomba, incluindo armação, materiais e fôrmas (3 utilizações). af_08/2022 | C51: m3 | D51: 1.2 | E51: 1710.38 | G51: 2052.46 | I51: =G51/$K$37 -> 0.0017780046
A53: 4 | B53: Setor de Risco A3S6R4 (Contenções e Demolições) | K53: =SUM(H53:H69) -> 734263.17 | L53: =K53/$G$133 -> 0.18663161
A54: 04.01 | B54: SERVIÇOS PRELIMINARES | H54: =G55 -> 110150.52 | I54: =H54/$K$53 -> 0.15001504
A55: 04.01.001 | B55: LIMPEZA DE TERRENO | G55: =SUM(G56:G59) -> 110150.52 | I55: =G55/$K$53 -> 0.15001504
A56: 04.01.001.001 | B56: Limpeza manual de terreno com vegetação rasteira, incluindo roçagem e queima | C56: m2 | D56: 4015 | E56: 4.38 | G56: 17585.7 | I56: =G56/$K$53 -> 0.023950132
A57: 04.01.001.002 | B57: Destocamento de árvores de porte médio e raízes profundas, sem auxílio mecânico | C57: un | D57: 100.38 | E57: 217.25 | G57: 21806.47 | I57: =G57/$K$53 -> 0.029698439
A58: 04.01.001.003 | B58: Coleta e carga manuais de entulho | C58: m3 | D58: 1204.5 | E58: 17.54 | G58: 21126.93 | I58: =G58/$K$53 -> 0.028772967
A59: 04.01.001.004 | B59: Transporte com caminhão basculante de 6 m³, em via urbana em revestimento primário (unidade: txkm). af_07/2020 | C59: txkm | D59: 24210.45 | E59: 2.05 | G59: 49631.42 | I59: =G59/$K$53 -> 0.067593503
A60: 04.02 | B60: ESTRUTURAS DE CONTENÇÃO | H60: =G61 -> 604972.16 | I60: =H60/$K$53 -> 0.82391734
A61: 04.02.001 | B61: RETALUDAMENTO / RECONSTRUÇÃO EM CORTE/ATERRO | G61: =SUM(G62:G64) -> 604972.16 | I61: =G61/$K$53 -> 0.82391734
A62: 04.02.001.001 | B62: Escavação manual de vala ou cava em material de 1ª categoria, profundidade entre 1,50 e 3,00m | C62: m3 | D62: 7227 | E62: 78.85 | G62: 569848.95 | I62: =G62/$K$53 -> 0.77608271
A63: 04.02.001.002 | B63: Carga manual de material de 1ª categoria | C63: m3 | D63: 1204.5 | E63: 10.49 | G63: 12635.2 | I63: =G63/$K$53 -> 0.017207999
A64: 04.02.001.003 | B64: Compactação manual com compactador a percussão sapinho, a 95% do pn | C64: m3 | D64: 1204.5 | E64: 18.67 | G64: 22488.01 | I64: =G64/$K$53 -> 0.030626635
A65: 04.03 | B65: DRENAGEM DAS ESTRUTURAS DE CONTENÇÃO | H65: =G66+G68 -> 19140.49 | I65: =H65/$K$53 -> 0.026067616
A66: 04.03.001 | B66: CANALETA | G66: =G67 -> 10417.55 | I66: =G66/$K$53 -> 0.014187761
A67: 04.03.001.001 | B67: Canaleta meia cana pré-moldada de concreto (d = 20 cm) - fornecimento e instalação. af_08/2021 | C67: m | D67: 341 | E67: 30.55 | G67: 10417.55 | I67: =G67/$K$53 -> 0.014187761
A68: 04.03.002 | B68: ESCADA HIDRÁULICA | G68: =G69 -> 8722.94 | I68: =G68/$K$53 -> 0.011879855
A69: 04.03.002.001 | B69: Escada hidráulica, largura até 1m, tipo descida d'água de corte ou aterro em degraus (dcd 02, 04 e dad 02), em concreto usinado, fck = 20 mpa, lançado com bomba, incluindo armação, materiais e fôrmas (3 utilizações). af_08/2022 | C69: m3 | D69: 5.1 | E69: 1710.38 | G69: 8722.94 | I69: =G69/$K$53 -> 0.011879855
A71: 5 | B71: Setor de Risco A2S2R3 (Contenções e Demolições) | K71: =SUM(H71:H85) -> 1027315.7 | L71: =K71/$G$133 -> 0.26111834
A72: 05.01 | B72: SERVIÇOS PRELIMINARES | H72: =G73 -> 157640.07 | I72: =H72/$K$53 -> 0.21469152
A73: 05.01.001 | B73: LIMPEZA DE TERRENO | G73: =SUM(G74:G77) -> 157640.07 | I73: =G73/$K$53 -> 0.21469152
A74: 05.01.001.001 | B74: Limpeza manual de terreno com vegetação rasteira, incluindo roçagem e queima | C74: m2 | D74: 5746 | E74: 4.38 | G74: =D74*E74 -> 25167.48 | I74: =G74/$K$53 -> 0.034275831
A75: 05.01.001.002 | B75: Destocamento de árvores de porte médio e raízes profundas, sem auxílio mecânico | C75: un | D75: 143.65 | E75: 217.25 | G75: =D75*E75 -> 31207.963 | I75: =G75/$K$53 -> 0.042502421
A76: 05.01.001.003 | B76: Coleta e carga manuais de entulho | C76: m3 | D76: 1723.8 | E76: 17.54 | G76: =D76*E76 -> 30235.452 | I76: =G76/$K$53 -> 0.04117795
A77: 05.01.001.004 | B77: Transporte com caminhão basculante de 6 m³, em via urbana em revestimento primário (unidade: txkm). af_07/2020 | C77: txkm | D77: 34648.38 | E77: 2.05 | G77: =D77*E77 -> 71029.179 | I77: =G77/$K$53 -> 0.096735315
A78: 05.02 | B78: ESTRUTURAS DE CONTENÇÃO | H78: =G79 -> 865795.79 | I78: =H78/$K$53 -> 1.1791355
A79: 05.02.001 | B79: RETALUDAMENTO / RECONSTRUÇÃO EM CORTE/ATERRO | G79: =SUM(G80:G82) -> 865795.79 | I79: =G79/$K$53 -> 1.1791355
A80: 05.02.001.001 | B80: Escavação manual de vala ou cava em material de 1ª categoria, profundidade entre 1,50 e 3,00m | C80: m3 | D80: 10342.8 | E80: 78.85 | G80: =D80*E80 -> 815529.78 | I80: =G80/$K$53 -> 1.1106778
A81: 05.02.001.002 | B81: Carga manual de material de 1ª categoria | C81: m3 | D81: 1723.8 | E81: 10.49 | G81: =D81*E81 -> 18082.662 | I81: =G81/$K$53 -> 0.024626949
A82: 05.02.001.003 | B82: Compactação manual com compactador a percussão sapinho, a 95% do pn | C82: m3 | D82: 1723.8 | E82: 18.67 | G82: =D82*E82 -> 32183.346 | I82: =G82/$K$53 -> 0.043830805
A83: 05.03 | B83: DRENAGEM DAS ESTRUTURAS DE CONTENÇÃO | H83: =G84 -> 3879.85 | I83: =H83/$K$53 -> 0.0052840046
A84: 05.03.001 | B84: CANALETA | G84: =G85 -> 3879.85 | I84: =G84/$K$53 -> 0.0052840046
A85: 05.03.001.001 | B85: Canaleta meia cana pré-moldada de concreto (d = 20 cm) - fornecimento e instalação. af_08/2021 | C85: m | D85: 127 | E85: 30.55 | G85: =D85*E85 -> 3879.85 | I85: =G85/$K$53 -> 0.0052840046
A87: 5 | B87: Obras Complementares | K87: =SUM(H87:H131) -> 5397967.3 | L87: =K87/G134 -> 1
A88: 05.01 | B88: SERVIÇOS PRELIMINARES | H88: =G89 -> 876930.38 | I88: =H88/$K$87 -> 0.16245567
A89: 05.01.001 | B89: LIMPEZA DE TERRENO | G89: =SUM(G90:G93) -> 876930.38
A90: 05.01.001.001 | B90: Limpeza manual de terreno com vegetação rasteira, incluindo roçagem e queima | C90: m2 | D90: 3327 | E90: 4.38 | G90: =D90*E90 -> 14572.26
A91: 05.01.001.002 | B91: Destocamento de árvores de porte médio e raízes profundas, sem auxílio mecânico | C91: un | D91: 1181.548 | E91: 217.25 | G91: =D91*E91 -> 256691.29
A92: 05.01.001.003 | B92: Coleta e carga manuais de entulho | C92: m3 | D92: 10310.1 | E92: 17.54 | G92: =D92*E92 -> 180839.15
A93: 05.01.001.004 | B93: Transporte com caminhão basculante de 6 m³, em via urbana em revestimento primário (unidade: txkm). af_07/2020 | C93: txkm | D93: 207233.01 | E93: 2.05 | G93: =D93*E93 -> 424827.67
A94: 05.03 | B94: DRENAGEM | H94: =G95+G97+G99 -> 579371.19 | I94: =H94/$K$87 -> 0.10733136
A95: 05.03.001 | B95: CANALETA | G95: =G96 -> 228506.77
A96: 05.03.001.001 | B96: Canaleta meia cana pré-moldada de concreto (d = 20 cm) - fornecimento e instalação. af_08/2021 | C96: m | D96: 5322 | E96: 30.55 | G96: =G98 -> 228506.77
A97: 05.03.002 | B97: ESCADA HIDRÁULICA | G97: 228506.77
A98: 05.03.002.001 | B98: Escada hidráulica, largura até 1m, tipo descida d'água de corte ou aterro em degraus (dcd 02, 04 e dad 02), em concreto usinado, fck = 20 mpa, lançado com bomba, incluindo armação, materiais e fôrmas (3 utilizações). af_08/2022 | C98: m3 | D98: 133.6 | E98: 1710.38 | G98: 228506.77
A99: 05.03.003 | B99: REDE COLETORA PLUVIAL (REDE+PV) | G99: =G100+G101 -> 122357.65
A100: 05.03.003.001 | B100: Fornecimento e assentamento de tubo corrugado parede dupla PEAD, d= 300mm (12"), p/sistemas drenagem, Tigre-ADS N-12 ou similar | C100: m | D100: 578 | E100: 206.46 | G100: 119333.88
A101: 05.03.003.002 | B101: Caixa de inspeção 0,30 x 0,30 x 0,40m | C101: un | D101: 19.25 | E101: 157.1 | G101: 3023.77
A102: 05.04 | B102: MOBILIDADE | H102: =G103+G105+G119 -> 3619626.2 | I102: =H102/$K$87 -> 0.67055356
A103: 05.04.001 | B103: VIELA (CAMINHO PAVIMENTADO/BECO) | G103: =G104 -> 177340.94
A104: 05.04.001.001 | B104: Execução de passeio (calçada) ou piso de concreto com concreto moldado in loco, feito em obra, acabamento convencional, não armado. af_08/2022 | C104: m3 | D104: 227.04 | E104: 781.1 | G104: 177340.94
A105: 05.04.002 | B105: PASSARELA | G105: =SUM(G106:G118) -> 911094.95
A106: 05.04.002.001 | B106: Escavação manual para bloco de coroamento ou sapata (incluindo escavação para colocação de fôrmas). af_01/2024 | C106: m3 | D106: 74.9 | E106: 89.09 | G106: 6672.84
...

Sheet 11_Nerival
A1: PMRR DE ILHÉUS
A3: Empreendimento: 000056 - Alto Nerival (Bairro Barra Taipe) | G3: VALOR TOTAL
A4: ITEM | B4: DESCRIÇÃO DO ITEM | C4: UNID | D4: QUANT | E4: PREÇO UNIT | G4: Valor Parcial | I4: Parcial (%) | K4: Soma | L4: (%)
A5: 1 | B5: Setor de Risco A1S1R4 (Contenções e Demolições) | K5: =SUM(H5:H17) -> 264588.04 | L5: =K5/$G$253 -> 0.049202885
A6: 01.01 | B6: SERVIÇOS PRELIMINARES | H6: =G7 -> 9190.64 | I6: =H6/$K$5 -> 0.034735659
A7: 01.01.001 | B7: LIMPEZA DE TERRENO | G7: =SUM(G8:G11) -> 9190.64 | I7: =G7/$K$5 -> 0.034735659
A8: 01.01.001.001 | B8: Limpeza manual de terreno com vegetação rasteira, incluindo roçagem e queima | C8: m2 | D8: 335 | E8: 4.38 | G8: 1467.3 | I8: =G8/$K$5 -> 0.0055456021
A9: 01.01.001.002 | B9: Destocamento de árvores de porte médio e raízes profundas, sem auxílio mecânico | C9: un | D9: 8.38 | E9: 217.25 | G9: 1819.47 | I9: =G9/$K$5 -> 0.0068766147
A10: 01.01.001.003 | B10: Coleta e carga manuais de entulho | C10: m3 | D10: 100.5 | E10: 17.54 | G10: 1762.77 | I10: =G10/$K$5 -> 0.0066623193
A11: 01.01.001.004 | B11: Transporte com caminhão basculante de 6 m³, em via urbana em revestimento primário (unidade: txkm). af_07/2020 | C11: txkm | D11: 2020.05 | E11: 2.05 | G11: 4141.1 | I11: =G11/$K$5 -> 0.015651123
A12: 01.02 | B12: ESTRUTURAS DE CONTENÇÃO | H12: =G13 -> 252831.2 | I12: =H12/$K$5 -> 0.95556549
A13: 01.02.001 | B13: SOLO GRAMPEADO | G13: =G14 -> 252831.2 | I13: =G13/$K$5 -> 0.95556549
A14: 01.02.001.001 | B14: Solo Grampeado para controlede erosão com malha hexagonal de dupla torção, revestimento em PVC e com resistência de puncionamento de 105 KN e resistência à tração de 89 KN/m. Associada a geomanta tridimensional verde. | C14: m2 | D14: 335 | E14: 754.72 | G14: 252831.2 | I14: =G14/$K$5 -> 0.95556549
A15: 01.03 | B15: DRENAGEM DAS ESTRUTURAS DE CONTENÇÃO | H15: =G16 -> 2566.2 | I15: =H15/$K$5 -> 0.0096988511
A16: 01.03.001 | B16: CANALETA | G16: =G17 -> 2566.2 | I16: =G16/$K$5 -> 0.0096988511
A17: 01.03.001.001 | B17: Canaleta meia cana pré-moldada de concreto (d = 20 cm) - fornecimento e instalação. af_08/2021 | C17: m | D17: 84 | E17: 30.55 | G17: 2566.2 | I17: =G17/$K$5 -> 0.0096988511
A19: 2 | B19: Setor de Risco A1S2R3 (Contenções e Demoliçoes) | K19: =SUM(H19:H52) -> 296480.31 | L19: =K19/$G$253 -> 0.055133583
A20: 02.01 | B20: SERVIÇOS PRELIMINARES | H20: =G21 -> 10315.46 | I20: =H20/$K$19 -> 0.034793069
A21: 02.01.001 | B21: LIMPEZA DE TERRENO | G21: =SUM(G22:G25) -> 10315.46 | I21: =G21/$K$19 -> 0.034793069
A22: 02.01.001.001 | B22: Limpeza manual de terreno com vegetação rasteira, incluindo roçagem e queima | C22: m2 | D22: 376 | E22: 4.38 | G22: 1646.88 | I22: =G22/$K$19 -> 0.0055547702
A23: 02.01.001.002 | B23: Destocamento de árvores de porte médio e raízes profundas, sem auxílio mecânico | C23: un | D23: 9.4 | E23: 217.25 | G23: 2042.15 | I23: =G23/$K$19 -> 0.0068879785
A24: 02.01.001.003 | B24: Coleta e carga manuais de entulho | C24: m3 | D24: 112.8 | E24: 17.54 | G24: 1978.51 | I24: =G24/$K$19 -> 0.0066733268
A25: 02.01.001.004 | B25: Transporte com caminhão basculante de 6 m³, em via urbana em revestimento primário (unidade: txkm). af_07/2020 | C25: txkm | D25: 2267.28 | E25: 2.05 | G25: 4647.92 | I25: =G25/$K$19 -> 0.015676994
A26: 02.02 | B26: ESTRUTURAS DE CONTENÇÃO | H26: =G27+G29+G44 -> 279292.15 | I26: =H26/$K$19 -> 0.94202596
A27: 02.02.001 | B27: SOLO GRAMPEADO | G27: 46037.92 | I27: =G27/$K$19 -> 0.15528154
A28: 02.02.001.001 | B28: Solo Grampeado para controlede erosão com malha hexagonal de dupla torção, revestimento em PVC e com resistência de puncionamento de 105 KN e resistência à tração de 89 KN/m. Associada a geomanta tridimensional verde. | C28: m2 | D28: 61 | E28: 754.72 | G28: 46037.92 | I28: =G28/$K$19 -> 0.15528154
A29: 02.02.002 | B29: MURO DE ARRIMO | G29: =SUM(G30:G43) -> 199351.68 | I29: =G29/$K$19 -> 0.67239433
A30: 02.02.002.001 | B30: Concretagem de pilares, fck = 25 mpa, com uso de bomba - lançamento, adensamento e acabamento. af_02/2022_ps | C30: m3 | D30: 36 | E30: 641.26 | G30: 23085.36 | I30: =G30/$K$19 -> 0.077864732
A31: 02.02.002.002 | B31: Armação de cinta de alvenaria estrutural; diâmetro de 16,0 mm. af_09/2021 | C31: kg | D31: 900 | E31: 8.64 | G31: 7776 | I31: =G31/$K$19 -> 0.026227711
A32: 02.02.002.003 | B32: Armação de verga e contraverga de alvenaria estrutural; diâmetro de 16,0 mm. af_09/2021 | C32: kg | D32: 1620 | E32: 9.66 | G32: 15649.2 | I32: =G32/$K$19 -> 0.052783269
A33: 02.02.002.004 | B33: Armação vertical de alvenaria estrutural; diâmetro de 16,0 mm. af_09/2021 | C33: kg | D33: 1620 | E33: 8.84 | G33: 14320.8 | I33: =G33/$K$19 -> 0.048302702
A34: 02.02.002.005 | B34: Reaterro manual de valas, com compactador de solos de percussão. af_08/2023 | C34: m3 | D34: 72 | E34: 25.13 | G34: 1809.36 | I34: =G34/$K$19 -> 0.0061027999
A35: 02.02.002.006 | B35: Grauteamento de cinta intermediária ou de contraverga em alvenaria estrutural. af_09/2021 | C35: m3 | D35: 1.8 | E35: 900.01 | G35: 1620.02 | I35: =G35/$K$19 -> 0.005464174
A36: 02.02.002.007 | B36: Grauteamento de cinta superior ou de verga em alvenaria estrutural. af_09/2021 | C36: m3 | D36: 1.8 | E36: 1002.12 | G36: 1803.82 | I36: =G36/$K$19 -> 0.006084114
A37: 02.02.002.008 | B37: Grauteamento vertical em alvenaria estrutural. af_09/2021 | C37: m3 | D37: 45 | E37: 1037.21 | G37: 46674.45 | I37: =G37/$K$19 -> 0.1574285
A38: 02.02.002.009 | B38: Tubo pvc rigido soldavel, serie reforçada, p/esgoto e aguas pluviais, d= 100mm | C38: m | D38: 45 | E38: 45.3 | G38: 2038.5 | I38: =G38/$K$19 -> 0.0068756674
A39: 02.02.002.010 | B39: Alvenaria de blocos de concreto estrutural 14x19x39 cm (espessura 14 cm), fbk = 14 mpa, utilizando colher de pedreiro. af_10/2022 | C39: m2 | D39: 90 | E39: 106.17 | G39: 9555.3 | I39: =G39/$K$19 -> 0.032229122
A40: 02.02.002.011 | B40: Escavação mecanizada para viga baldrame ou sapata corrida com mini-escavadeira (incluindo escavação para colocação de fôrmas). af_01/2024 | C40: m3 | D40: 72 | E40: 56.85 | G40: 4093.2 | I40: =G40/$K$19 -> 0.013805976
A41: 02.02.002.012 | B41: Fabricação, montagem e desmontagem de fôrma para sapata corrida, em madeira serrada, e=25 mm, 4 utilizações. af_01/2024 | C41: m2 | D41: 72 | E41: 76.84 | G41: 5532.48 | I41: =G41/$K$19 -> 0.018660531
... A43: 02.02.002.014 | B43: Concretagem de sapata corrida, fck 30 mpa, com uso de bomba - lançamento, adensamento e acabamento. af_01/2024 | C43: m3 | D43: 72 | E43: 734.02 | G43: 52849.44 | I43: =G43/$K$19 -> 0.17825615
A44: 02.02.003 | B44: RETALUDAMENTO / RECONSTRUÇÃO EM CORTE/ATERRO | G44: =SUM(G45:G47) -> 33902.55 | I44: =G44/$K$19 -> 0.11435009
A45: 02.02.003.001 | B45: Escavação manual de vala ou cava em material de 1ª categoria, profundidade entre 1,50 e 3,00m | C45: m3 | D45: 405 | E45: 78.85 | G45: 31934.25 | I45: =G45/$K$19 -> 0.1077112
A46: 02.02.003.002 | B46: Carga manual de material de 1ª categoria | C46: m3 | D46: 67.5 | E46: 10.49 | G46: 708.08 | I46: =G46/$K$19 -> 0.0023882868
A47: 02.02.003.003 | B47: Compactação manual com compactador a percussão sapinho, a 95% do pn | C47: m3 | D47: 67.5 | E47: 18.67 | G47: 1260.22 | I47: =G47/$K$19 -> 0.0042506027
A48: 02.03 | B48: DRENAGEM DAS ESTRUTURAS DE CONTENÇÃO | H48: =G49+G51 -> 6872.7 | I48: =H48/$K$19 -> 0.023180966
A49: 02.03.001 | B49: CANALETA | G49: 2596.75 | I49: =G49/$K$19 -> 0.0087585918
A50: 02.03.001.001 | B50: Canaleta meia cana pré-moldada de concreto (d = 20 cm) - fornecimento e instalação. af_08/2021 | C50: m | D50: 85 | E50: 30.55 | G50: 2596.75 | I50: =G50/$K$19 -> 0.0087585918
A51: 02.03.002 | B51: ESCADA HIDRÁULICA | G51: 4275.95 | I51: =G51/$K$19 -> 0.014422374
A52: 02.03.002.001 | B52: Escada hidráulica, largura até 1m, tipo descida d'água de corte ou aterro em degraus (dcd 02, 04 e dad 02), em concreto usinado, fck = 20 mpa, lançado com bomba, incluindo armação, materiais e fôrmas (3 utilizações). af_08/2022 | C52: m3 | D52: 2.5 | E52: 1710.38 | G52: 4275.95 | I52: =G52/$K$19 -> 0.014422374
A54: 3 | B54: Setor de Risco A2S1R4 (Contenções e Demolições) | K54: =SUM(H54:H83) -> 836296 | L54: =K54/$G$253 -> 0.1555179
A55: 03.01 | B55: SERVIÇOS PRELIMINARES | H55: =G56 -> 20630.93 | I55: =H55/$K$54 -> 0.024669411
A56: 03.01.001 | B56: LIMPEZA DE TERRENO | G56: =SUM(G57:G60) -> 20630.93 | I56: =G56/$K$54 -> 0.024669411
A57: 03.01.001.001 | B57: Limpeza manual de terreno com vegetação rasteira, incluindo roçagem e queima | C57: m2 | D57: 752 | E57: 4.38 | G57: 3293.76 | I57: =G57/$K$54 -> 0.0039385098
A58: 03.01.001.002 | B58: Destocamento de árvores de porte médio e raízes profundas, sem auxílio mecânico | C58: un | D58: 18.8 | E58: 217.25 | G58: 4084.3 | I58: =G58/$K$54 -> 0.0048837971
A59: 03.01.001.003 | B59: Coleta e carga manuais de entulho | C59: m3 | D59: 225.6 | E59: 17.54 | G59: 3957.02 | I59: =G59/$K$54 -> 0.0047316022
A60: 03.01.001.004 | B60: Transporte com caminhão basculante de 6 m³, em via urbana em revestimento primário (unidade: txkm). af_07/2020 | C60: txkm | D60: 4534.56 | E60: 2.05 | G60: 9295.85 | I60: =G60/$K$54 -> 0.011115502
A61: 03.02 | B61: ESTRUTURAS DE CONTENÇÃO | H61: =G62+G64 -> 808498.71 | I61: =H61/$K$54 -> 0.96676142
